{"videos": [
{"videoId": "IqLaqNiUNBg"},
{"videoId": "cKz5gnDpkmQ"},
{"videoId": "vQKYh8Du1Jo"},
{"videoId": "ZokBJx3AQTE"},
{"videoId": "0JCGDm9NqzI"},
{"videoId": "-WNgQK4XSuA"},
{"videoId": "8QQ6nlhQXyg"},
{"videoId": "BwUx4iAWiIo"},
{"videoId": "UQd_8U5cB6M"},
{"videoId": "CcCjvSZQ-Xc"},
{"videoId": "NXs-It1iB28"},
{"videoId": "MkuKicGxT9M"},
{"videoId": "jXvjbCXatGo"},
{"videoId": "DrKB7JDlthg"},
{"videoId": "urq-GcubCbg"},
{"videoId": "5CTZKQjlZNs"},
{"videoId": "H73BjBl6ZyA"},
{"videoId": "UMbr5mQVE9U"},
{"videoId": "R-82VSIivKc"},
{"videoId": "VVMzGQ2ASCo"},
{"videoId": "OHfMrb7Slxw"},
{"videoId": "dbofhUfQ1p4"},
{"videoId": "BmsaVPcMxBs"},
{"videoId": "9VrzPfkL3rE"},
{"videoId": "O5_jxkEBSZU"},
{"videoId": "0dMD0w474qE"},
{"videoId": "19UrxtUzPL0"},
{"videoId": "iGMdRY0rNVo"},
{"videoId": "JuQcdpsexsY"},
{"videoId": "R8cvvy2lYgI"},
{"videoId": "CRYd-KJtpV8"},
{"videoId": "OuV9VS8hLGA"},
{"videoId": "_7ZYRkBIEg8"},
{"videoId": "5_8rjTspXGo"},
{"videoId": "DP7Y9Kipieg"},
{"videoId": "x_IJDXzQa-Y"},
{"videoId": "2v8uecv5LEQ"},
{"videoId": "J1AmlhFG6d4"},
{"videoId": "BUQV6wCn9jc"},
{"videoId": "crxcYu2QuAQ"},
{"videoId": "Zx7nNUGtEfA"},
{"videoId": "ebTwnu00Ch0"},
{"videoId": "ySIQ6AWac2c"},
{"videoId": "xotMJEWJVqM"},
{"videoId": "sr3O7ArQTYY"},
{"videoId": "ljf8yxDQ1d0"},
{"videoId": "QetOhPG0iws"},
{"videoId": "giQBy1EUwbI"},
{"videoId": "Hxzj5wayyP4"},
{"videoId": "dDNWd3nqx_Q"},
{"videoId": "Uuh4Q-GNtjw"},
{"videoId": "2WiZCaupqZE"},
{"videoId": "Hj44ky2T3GI"},
{"videoId": "z2nk3F5UNl0"},
{"videoId": "QdVpiaDzFH8"},
{"videoId": "hY3ZvWFOFlM"},
{"videoId": "KwSQ1t0FIks"},
{"videoId": "WxTvN4y050g"},
{"videoId": "Uu6PHveo_TQ"},
{"videoId": "TNmPG_o2ikg"},
{"videoId": "WGdPQPWI2hM"},
{"videoId": "gegA_0BngGI"},
{"videoId": "lSi--RJevNY"},
{"videoId": "8Oj81nemVm4"},
{"videoId": "x76t-l69_6E"},
{"videoId": "SUKMf-syolg"},
{"videoId": "UVnxkkpQXs8"},
{"videoId": "kVOyi38snrY"},
{"videoId": "q27LIoMgAhA"},
{"videoId": "YPh3sUYqwUY"},
{"videoId": "GU-oWC2N8Jo"},
{"videoId": "Cdu32FVXL-w"},
{"videoId": "VqG6H-6w8sU"},
{"videoId": "Nbo4qT-OrRc"},
{"videoId": "1mf3r3LVp_k"},
{"videoId": "3RSOX_8qqOo"},
{"videoId": "oYRAjhmHYfA"},
{"videoId": "kRZE3P8bhAc"},
{"videoId": "eREftfTRsaQ"},
{"videoId": "pkgbFFJ9Ux8"},
{"videoId": "6qRv2Tn4RVI"},
{"videoId": "im51iC4avfw"},
{"videoId": "zPuLGkluoTY"},
{"videoId": "QY_R0gP23eg"},
{"videoId": "_PwN_S-1K_k"},
{"videoId": "9353G80X7Yc"},
{"videoId": "I15E5uq9QKg"},
{"videoId": "dllFod6dhfI"},
{"videoId": "RQ0MYzjhNaE"},
{"videoId": "prNm5IblJYc"},
{"videoId": "ZHci71eDC5o"},
{"videoId": "lVWgVXRB3h8"},
{"videoId": "CIZcqwJr55Y"},
{"videoId": "TQoVe3FkPM0"},
{"videoId": "iVmNJEJ6WZU"},
{"videoId": "2mmrHipFnnE"},
{"videoId": "l7bOGdJL_HU"},
{"videoId": "8bNLr57-Luo"},
{"videoId": "RiAGHxeKyWQ"},
{"videoId": "xnZDGJPcWSM"},
{"videoId": "7eR5HMhfXWc"},
{"videoId": "hL8lCod3PKo"},
{"videoId": "O8LcKHkEM8Q"},
{"videoId": "Frt8aL5XMf0"},
{"videoId": "qvpqK4K2gyM"},
{"videoId": "ccle-EFauSI"},
{"videoId": "CJYQjM7GfhM"},
{"videoId": "JIgWgrM0K5U"},
{"videoId": "syU-3UtU0gw"},
{"videoId": "8awiOqG88gc"},
{"videoId": "ycFpxiBK4ng"},
{"videoId": "QGYUrSHsYBM"},
{"videoId": "wCnT7VvPDb8"},
{"videoId": "caWR_dYnjUk"},
{"videoId": "A_YfXN1cODY"},
{"videoId": "137vIpNJh8I"},
{"videoId": "PYsrXe4-X_M"},
{"videoId": "FqUQMq27AcA"},
{"videoId": "2ccV6D6Qk94"},
{"videoId": "85bPyo3iBWU"},
{"videoId": "53GgjqLoF8w"},
{"videoId": "IOHXsl7vDow"},
{"videoId": "SWX9XDdUsDc"},
{"videoId": "PbI2dSe9bu8"},
{"videoId": "VZ95mJxhKmE"},
{"videoId": "G_BBM7CGRko"},
{"videoId": "ATRE2DQHosw"},
{"videoId": "LeDShzpCflI"},
{"videoId": "-wiRYfPpInU"},
{"videoId": "ngCmN6_m8Yg"},
{"videoId": "I0B21LjeSUQ"},
{"videoId": "OHrdC83NVlE"},
{"videoId": "rBT1q82oJtM"},
{"videoId": "veFk68Fv73w"},
{"videoId": "tqrqiyPC14Q"},
{"videoId": "n2ZE2Xo9O_Q"},
{"videoId": "HYlwYjRPbPo"},
{"videoId": "TbUlBj3e0XU"},
{"videoId": "zO_uA5EYwlE"},
{"videoId": "Eqq5y2CUUwY"},
{"videoId": "iravQHqJqR0"},
{"videoId": "_57H7tdl9lo"},
{"videoId": "B-vOARc_zGw"},
{"videoId": "iqRanUDnDpI"},
{"videoId": "uztj01bBx4Y"},
{"videoId": "lfhpm_rSlKY"},
{"videoId": "pXuKwYH-f5g"},
{"videoId": "weB_mj0cQX8"},
{"videoId": "1Mp3fRZxq1o"},
{"videoId": "yLbByHU55FA"},
{"videoId": "HWPy6r8iXiE"},
{"videoId": "Cbt5mnGr0oc"},
{"videoId": "Mt4s1Gg2-d4"},
{"videoId": "9McZRi-UhJ0"},
{"videoId": "jkWRy0RwIpU"},
{"videoId": "xHi_us9B2DY"},
{"videoId": "vqwOoWSeQK0"},
{"videoId": "k4zlA2ou7tQ"},
{"videoId": "UH5yttxF-uI"},
{"videoId": "yG9b1BDjO8c"},
{"videoId": "oib4qGPy5r0"},
{"videoId": "y4QqUpkP6Lk"},
{"videoId": "GalLzn7Tyzo"},
{"videoId": "v4Am-6ipNuw"},
{"videoId": "paUZs41-pvY"},
{"videoId": "AmmDp69IvHU"},
{"videoId": "SA-VhiTqPz8"},
{"videoId": "El4BdcZTsEk"},
{"videoId": "yZxXamn2Gbw"},
{"videoId": "7KhwA3rkvmE"},

{"videoId": "UVtywBFUuBg"},
{"videoId": "bztOrupnn2o"},
{"videoId": "yH_3S9mUTJE"},
{"videoId": "KObyc70Y7bI"},
{"videoId": "Z0weBeMc7Ck"},
{"videoId": "sx-Vn6IqK4U"},
{"videoId": "e6OoSnAlbgU"},
{"videoId": "qUfwwJXKGiI"},
{"videoId": "5lrMZgCay84"},
{"videoId": "8tSzABBxCS0"},
{"videoId": "tlDyOUUYnQI"},
{"videoId": "3Ugrbh9laeo"},
{"videoId": "XJFIqtKwcQA"},
{"videoId": "NPYHOo35P6w"},
{"videoId": "KUDu6vacbZg"},
{"videoId": "exaobCsJvGY"},
{"videoId": "M5xIKKSM-Js"},
{"videoId": "VYQuA0HCnsI"},
{"videoId": "VnDxsqL5AuE"},
{"videoId": "DFhRBFdw2R0"},
{"videoId": "ikm9yR1Sym4"},
{"videoId": "7iLVSo0nUUU"},
{"videoId": "LYXHVva0EAM"},
{"videoId": "bxCXbEyGrRQ"},
{"videoId": "Qs1Dl90sxOs"},
{"videoId": "DBOJVI_WlOI"},
{"videoId": "D-N_LqOr7gM"},
{"videoId": "BkkOUXHLusQ"},
{"videoId": "NxcL7gydx1U"},
{"videoId": "Zrb8SmG3gUc"},
{"videoId": "QIKN0vhnLVI"},
{"videoId": "hzoRWnZKCI0"},
{"videoId": "XlWO3878K5g"},
{"videoId": "YEyxbtRbjqs"},
{"videoId": "9WE3wCA13-A"},
{"videoId": "rsN3t8JnOdo"},
{"videoId": "-YVLAooFpXU"},
{"videoId": "Sa1V5ScT5CA"},
{"videoId": "V2CZ3DJM8G0"},
{"videoId": "JuDaGGsypNs"},
{"videoId": "PgHmkpvXR78"},
{"videoId": "RbpKkvlHYTw"},
{"videoId": "I6fpQqgHfGE"},
{"videoId": "snDKi_qj-Ug"},
{"videoId": "xng0v30yXqo"},
{"videoId": "8h84R_CJCLI"},
{"videoId": "lVPCJYWamJE"},
{"videoId": "bx0u67Mj5bY"},
{"videoId": "-V2EsniQw-A"},
{"videoId": "iXM4BzIJ3xk"},
{"videoId": "DroUNTghQIU"},
{"videoId": "v4KG-HNWT6U"},
{"videoId": "QdddKu556pc"},
{"videoId": "OEIr501F1T4"},
{"videoId": "jnPDeoCK4WU"},
{"videoId": "_I0r1p-iUWA"},
{"videoId": "PkyuTy6oKXE"},
{"videoId": "nfrgOeb1AHY"},
{"videoId": "htlrUHv5Nic"},
{"videoId": "NZsOzCYoEyc"},
{"videoId": "NuKmQ5ZMaxE"},
{"videoId": "70rijjnK5GQ"},
{"videoId": "TgNszu-Ax00"},
{"videoId": "3aas-RT7Ul8"},
{"videoId": "tsKDSmY34xs"},
{"videoId": "LRr9w7LxmhM"},
{"videoId": "YJMXO7RYycQ"},
{"videoId": "OnRjPEJwGjs"},
{"videoId": "jM8Ca1dzAKM"},
{"videoId": "-WSrY-xH5pI"},
{"videoId": "U_oMNpql10U"},
{"videoId": "Gs5sKDCMuYg"},
{"videoId": "kUbZmTWXQp8"},
{"videoId": "XP36tRBFbbU"},
{"videoId": "bIkxl4BieaM"},
{"videoId": "Td3wV8Lb4LE"},
{"videoId": "i7gHSJOT96Q"},
{"videoId": "qXu-DOPzsRI"},
{"videoId": "RRHyfMOgAg8"},
{"videoId": "Q_q7Md2YV84"},
{"videoId": "ub1WfnpqXFc"},
{"videoId": "Ylx4knDgkcc"},
{"videoId": "fFb31gnFymI"},
{"videoId": "3tgjUW6cQtA"},
{"videoId": "ww3XgG3ISIA"},
{"videoId": "ZpPNG6PG5kM"},
{"videoId": "iMOzAqRntks"},
{"videoId": "nPmQzYjIxig"},
{"videoId": "F4c0tVe0Gcs"},
{"videoId": "Bwhq3Ti7Vjc"},
{"videoId": "XqQtsfpDjq4"},
{"videoId": "OoOvSftk_ug"},
{"videoId": "eVFMDMpY36o"},
{"videoId": "c8Lpk3MWryo"},
{"videoId": "K8SXsOc-t5o"},
{"videoId": "yp5ps00yYdo"},
{"videoId": "hCACUJSz47o"},
{"videoId": "e9sq7E5Ea4M"},
{"videoId": "1lB1tJbN_aQ"},
{"videoId": "r4FrvrDzUpw"},
{"videoId": "3-Btbp2azAs"},
{"videoId": "w8c-d-1p2j4"},
{"videoId": "O_uMjpZ7U1U"},
{"videoId": "LZutRnL-Ye8"},
{"videoId": "6DzUsDehvCw"},
{"videoId": "fwa2bNkVnz0"},
{"videoId": "7s0SQlpEeBg"},
{"videoId": "oITn256uIUs"},
{"videoId": "94S3w376w90"},
{"videoId": "HQ9UuV2m40E"},
{"videoId": "m4mHqYJa4dk"},
{"videoId": "IeTWWDWmSyc"},
{"videoId": "CsKAvA9EVM4"},
{"videoId": "pURUaVb8fbw"},
{"videoId": "dyZn-vspZAo"},
{"videoId": "UnpoV_Jw4_4"},
{"videoId": "bGd3J4B4-1E"},
{"videoId": "QJ8cxgDDSRM"},
{"videoId": "_Eyz1euFink"},
{"videoId": "Vud8TGPspmQ"},
{"videoId": "QzpqzTYue2s"},
{"videoId": "tmFE-7Q1Q4Y"},
{"videoId": "fJAYbGAEPqI"},
{"videoId": "M1zoyyj0jMg"},
{"videoId": "3UKMmKuFQJY"},
{"videoId": "bi5ZOejXJh4"},
{"videoId": "28dUuwuaOvo"},
{"videoId": "Rk9d5RRIj08"},
{"videoId": "zpkhcZJXdWw"},
{"videoId": "zKBc-4i_7wM"},
{"videoId": "4OJFYzdVjQ4"},
{"videoId": "l0ukHmzXJ8o"},
{"videoId": "IFP9eSx8ieI"},
{"videoId": "4hE93vkDlno"},
{"videoId": "aYOt3g_R7Xk"},
{"videoId": "9P-7difmPrE"},
{"videoId": "odARmtJNL-w"},
{"videoId": "kUP8MEKJ1XA"},
{"videoId": "y87bxy4y8nA"},
{"videoId": "EyxaoXUuBXo"},
{"videoId": "2XiMdGB5cQU"},
{"videoId": "rULu90lLbFk"},
{"videoId": "8-wDc8d4q_Q"},
{"videoId": "AytS6vNg-NU"},
{"videoId": "LJaIGjruqtE"},
{"videoId": "GqasAh7uL3c"},
{"videoId": "lKJwQqcjvW4"},
{"videoId": "Njj67nD0Vos"},
{"videoId": "T8efi73kGrI"},
{"videoId": "OjLQAT2aYJY"},
{"videoId": "C6Xf8UMGtV8"},
{"videoId": "PtR_ef6Ea9Q"},
{"videoId": "_pI5kWNVpQw"},
{"videoId": "Ie_kKEomolI"},
{"videoId": "vxVjPI_i54A"},
{"videoId": "mGazUzdIdiA"},
{"videoId": "6lx_9DFdvTA"},
{"videoId": "H3X_Wf89sBQ"},
{"videoId": "2-x9sNMUIBY"},
{"videoId": "j6Gsvjnq2_8"},
{"videoId": "dB3ruVS4GMg"},
{"videoId": "WfaXzhYlTIA"},
{"videoId": "2WEMKaZNfqI"},
{"videoId": "lqLQ0QpAMkg"},
{"videoId": "E9QAPfWg_jU"},
{"videoId": "IBZVGE-EWn4"},
{"videoId": "bVYwg56Udw0"},
{"videoId": "mvmlp3hQjq8"},
{"videoId": "sVwL8Lxk49I"},
{"videoId": "aQfWxm9oQpk"},
{"videoId": "2AQpIYarJEk"},
{"videoId": "7y597CU0tfM"},
{"videoId": "2zddnWUjWG8"},
{"videoId": "tIa1BCvIGqI"},
{"videoId": "eXBrn5wvl4A"},
{"videoId": "8TRHdN9O2jw"},
{"videoId": "2dGekkoSI2E"},
{"videoId": "thrV0eO3d68"},
{"videoId": "ykLwVt5p3ms"},
{"videoId": "fnhLkI1JGAM"},
{"videoId": "IErEtxrl_8Y"},
{"videoId": "X3sD3rSMSus"},
{"videoId": "2F_LhO6x31E"},
{"videoId": "6MlYJrs8CQ0"},
{"videoId": "FwJecrmbi58"},
{"videoId": "m5T_mM9MpzM"},
{"videoId": "4UEi2oJimKg"},
{"videoId": "RueXIkYdKhU"},
{"videoId": "YBpCVT4J6tM"},
{"videoId": "UMeyNK3xScg"},
{"videoId": "C8BohjuUd6U"},
{"videoId": "V8ejfaSf1Zw"},
{"videoId": "r_kAPW17P14"},
{"videoId": "-ZaOgGV108c"},
{"videoId": "l57Q9WksEuw"},
{"videoId": "TmY5vT_YjWg"},
{"videoId": "0of4qYqPYAk"},
{"videoId": "ZtZKerTU1zc"},
{"videoId": "kAyw9K0v93A"},
{"videoId": "xC3UDo-E6sg"},
{"videoId": "Q_51M1NT2_I"},
{"videoId": "zuZsAaxcDxw"},
{"videoId": "C83WOaDDolU"},
{"videoId": "_O3c-Ahmi8E"},
{"videoId": "Kzq_XWynT2Y"},
{"videoId": "HzI_vqENyko"},
{"videoId": "gzDnTh4RJeo"},
{"videoId": "8wUqy9NVZn8"},
{"videoId": "1V4yEpbc-z0"},
{"videoId": "_cCRTvUMlUM"},
{"videoId": "rfUB0q7R_xM"},
{"videoId": "I8wYaj-0YdM"},
{"videoId": "cezb0JlMHZ0"},
{"videoId": "s_m1QKaQXVc"},
{"videoId": "BgrYoOdpgto"},
{"videoId": "bW0pkhlNycE"},
{"videoId": "wBwkGQngcLA"},
{"videoId": "WHSuzJa6W2g"},
{"videoId": "fRLVHR3V9is"},
{"videoId": "TvyCDmWXTdc"},
{"videoId": "nlhTC5KBw2I"},
{"videoId": "err2QhxPKbs"},
{"videoId": "o-DWzNpBc_E"},
{"videoId": "AKc2amIwXPY"},
{"videoId": "szDYnZbJ44Y"},
{"videoId": "sPOcKAZGIic"},
{"videoId": "4-h2kNRGN-A"},
{"videoId": "SAg1HHRgXgU"},
{"videoId": "0oQ0zuwX6zI"},
{"videoId": "BxeeskRdlu8"},
{"videoId": "4KA_mIim1tU"},
{"videoId": "gDucoHDTqMM"},
{"videoId": "mR8T-o6rrXs"},
{"videoId": "k2v3WDsDbrw"},
{"videoId": "HNiS28gsFYw"},
{"videoId": "VZHGHqtKlOY"},
{"videoId": "aKoMpfqR8wQ"},
{"videoId": "M8gQS0fB5Xs"},
{"videoId": "hI7NCBLlRgA"},
{"videoId": "O41Nm6l0sbY"},
{"videoId": "Ryz33TjXDts"},
{"videoId": "dZKJXVYH_o0"},
{"videoId": "fdy3Q9GSCPQ"},
{"videoId": "BpALiQo1lwI"},
{"videoId": "zROgqWE-yVE"},
{"videoId": "4TkoCHIQe4A"},
{"videoId": "f1Pmaiqeixc"},
{"videoId": "BPXW6vS7tK4"},
{"videoId": "biaGGHjXPak"},
{"videoId": "QD9rdRd-toY"},
{"videoId": "ADMH1FI5FyM"},
{"videoId": "1L-2ms2N-pc"},
{"videoId": "cv7rdX3QAGk"},
{"videoId": "fysb8ikZgvM"},
{"videoId": "_iaEt4VIl04"},
{"videoId": "_V5tSnSP_vQ"},
{"videoId": "BCEZrasP27s"},
{"videoId": "I9D8Ej4GMW4"},
{"videoId": "7kmJ-EetcRQ"},
{"videoId": "Et6WoGeqXZ8"},
{"videoId": "llHQmFegCmk"},
{"videoId": "JrvzJp8J1YU"},
{"videoId": "iXmovdeEqig"},
{"videoId": "9YYXtKBo9u0"},
{"videoId": "aDSWbHSQ8Nk"},
{"videoId": "x379RevBP40"},
{"videoId": "GKEZRfqdl8Y"},
{"videoId": "4Hpwomu7Efk"},
{"videoId": "RD56imgeI8k"},
{"videoId": "ktgqJhbC9VM"},
{"videoId": "7fNM3yJidxc"},
{"videoId": "Jy6gc70AwOQ"},
{"videoId": "E-1V89y5J_M"},
{"videoId": "cMOSi6gHMlw"},
{"videoId": "YihMxGyS498"},
{"videoId": "hWwzUhmA47s"},
{"videoId": "6XiI2da3c1A"},
{"videoId": "hsNaXfLzf_0"},
{"videoId": "rulpcR8N89c"},
{"videoId": "kO8TvWfrkWs"},
{"videoId": "3EapcrXKht0"},
{"videoId": "fpz7imHeUgc"},
{"videoId": "uN1GEI6i4vw"},
{"videoId": "Aero3GMlLCk"},
{"videoId": "7bOuSKt92g0"},
{"videoId": "RCz_MSOo03o"},
{"videoId": "-_szs5M2BXc"},
{"videoId": "aooIpwlyTJY"},
{"videoId": "SyrgH56IFNM"},
{"videoId": "x1cfQTkPEgo"},
{"videoId": "7ry2IhtQvgY"},
{"videoId": "3ovM4dq0OrU"},
{"videoId": "S7f6bQvkV3o"},
{"videoId": "h5bgRMz5B1E"},
{"videoId": "_mHMjZhWcnA"},
{"videoId": "vO3A6om4dWc"},
{"videoId": "Yy5EPvY9kT0"},
{"videoId": "nR9dvyAf-DY"},
{"videoId": "kryi1uTmVqc"},
{"videoId": "ZOvjRY8rvnA"},
{"videoId": "Ab4T62dYCFs"},
{"videoId": "BTUhl97iiNc"},
{"videoId": "1JIOAUEPYLQ"},
{"videoId": "HUbjF3RbbNQ"},
{"videoId": "0V8xwnlQCN4"},
{"videoId": "pnWlbAsrkaQ"},
{"videoId": "bW6yxXeQ86s"},
{"videoId": "iJl014n1i-Q"},
{"videoId": "yz6wmtcCwnc"},
{"videoId": "BAqW_h61TZE"},
{"videoId": "kbP-3-2yJpc"},
{"videoId": "i_Mg2a9OC8g"},
{"videoId": "8dBDmVJ6-7Q"},
{"videoId": "hX92uoAG-YA"},
{"videoId": "GrbfcoaSKsc"},
{"videoId": "AoFT3DzR4Mg"},
{"videoId": "ehKGmdzTWIc"},
{"videoId": "6uhnkdJ6Mqo"},
{"videoId": "SkQjQ0GAA3w"},
{"videoId": "G6m00187z_I"},
{"videoId": "-xlmBoQ4paI"},
{"videoId": "IIocKc8-J_0"},
{"videoId": "EV94Jk_wUEY"},
{"videoId": "tXKRFzTAwPk"},
{"videoId": "YuCJM2k4FYg"},
{"videoId": "2MnyWvn-sQQ"},
{"videoId": "Axu2vjhNBKk"},
{"videoId": "WYipNMklDkA"},
{"videoId": "u11hsWjvpAU"},
{"videoId": "Oo078L_2Zmg"},
{"videoId": "WYRtJI9BnaU"},
{"videoId": "b66Gg1YSfds"},
{"videoId": "WoUvoqLFlzQ"},
{"videoId": "Fmk9JzoOiTo"},
{"videoId": "B65-QjQ-LGw"},
{"videoId": "eAHc-2qKlEU"},
{"videoId": "BUn3wGb6du4"},
{"videoId": "pozbVh0Umtw"},
{"videoId": "WTAOPgh8J-c"},
{"videoId": "19S8mYs9brw"},
{"videoId": "4ex9oTZHzDQ"},
{"videoId": "m26z8escfHk"},
{"videoId": "CCF8dJ9JxnQ"},
{"videoId": "u4nSAC_K9FU"},
{"videoId": "GCUS20oeBQo"},
{"videoId": "DnzHBOdxwQA"},
{"videoId": "EQaCnoBcM-0"},
{"videoId": "I8xAR0R7jqM"},
{"videoId": "3P1CnWI62Ik"},
{"videoId": "R8tcwg-Idfs"},
{"videoId": "57ATZ_7ZxYw"},
{"videoId": "_rP-QTUCkFc"},
{"videoId": "jF52y0wLn60"},
{"videoId": "mQwyybgi_kg"},
{"videoId": "qFOU-ujEXVI"},
{"videoId": "nWSs99480X4"},
{"videoId": "bsExv9Vqul4"},
{"videoId": "96GiLDRGG1E"},
{"videoId": "G65C-mqL3ho"},
{"videoId": "UBgN_Vp6BPU"},
{"videoId": "m8h0pirDCOY"},
{"videoId": "esWuCsT-E9s"},
{"videoId": "T5SFXf-q9GE"},
{"videoId": "ChU2EYAgV_g"},
{"videoId": "hBNQEEMKPYc"},
{"videoId": "gEc3fBnd9mY"},
{"videoId": "gtumvBkg_Ik"},
{"videoId": "lsqrIX_-Uzs"},
{"videoId": "AD3mTCvJzwE"},
{"videoId": "0uIs5OVG9HI"},
{"videoId": "FvZgfGe-pVQ"},
{"videoId": "ZHB-KlPBwzA"},
{"videoId": "BE5_SUJap8A"},
{"videoId": "Uyocfq5MI_c"},
{"videoId": "SmJbm1PMAMM"},
{"videoId": "vdNE0BpgeNA"},
{"videoId": "nLNyN3CCnFo"},
{"videoId": "FkqMWa2jrjE"},
{"videoId": "xILWQlh6NYI"},
{"videoId": "ztq3GttmZnI"},
{"videoId": "X1fqTA-5dww"},
{"videoId": "EP3zd9cKdAc"},
{"videoId": "_EYcOtLlX8E"},
{"videoId": "T7VUGolk_jM"},
{"videoId": "YDNEqg8qgfQ"},
{"videoId": "AdPNQerBE5A"},
{"videoId": "QUs73kta7bc"},
{"videoId": "LwvjPE6xkFs"},
{"videoId": "o1851MEL5Cw"},
{"videoId": "zL3_oeXcYs8"},
{"videoId": "OPeuAL-hUDw"},
{"videoId": "wxgu9BN21kQ"},
{"videoId": "C3dYgweaja8"},
{"videoId": "Qg1yRQiju9A"},
{"videoId": "EmFQb0MzMew"},
{"videoId": "syAbohsKRSs"},
{"videoId": "xneo7bIqKNA"},
{"videoId": "W1SdyPGm8cI"},
{"videoId": "BR4KyUDvneU"},
{"videoId": "zNgueCX1H5k"},
{"videoId": "CIqapvgGfiE"},
{"videoId": "26vP6OVnch8"},
{"videoId": "Oylr8k53QCk"},
{"videoId": "x9RQBPmXpEQ"},
{"videoId": "E8cbwbTqmCw"},
{"videoId": "uiMXGIG_DQo"},
{"videoId": "wE6As6lym-E"},
{"videoId": "lZic-pyl73I"},
{"videoId": "zDc8hD1Tv_4"},
{"videoId": "MZ7PwRohNtg"},
{"videoId": "lZHnjiE7YpE"},
{"videoId": "uOzfG_qE-X4"},
{"videoId": "sMMdxt-0tJs"},
{"videoId": "rQ7973VbqBI"},
{"videoId": "uitWA5Iw26s"},
{"videoId": "qkdUGC-izus"},
{"videoId": "te8DUKdHRG0"},
{"videoId": "s50yml_9LPA"},
{"videoId": "GyGJ2lmkuHQ"},
{"videoId": "1WEJKNSHD4s"},
{"videoId": "NBJDZnYFIDg"},
{"videoId": "DXQYgAV37eM"},
{"videoId": "cSRJ9xJAD3Y"},
{"videoId": "bjU4xEnCwRU"},
{"videoId": "ki0x_nJYsqs"},
{"videoId": "ZigfgAOJuyU"},
{"videoId": "1-lB-u5ae0Y"},
{"videoId": "3jpK-FcJJNs"},
{"videoId": "1ir8584fmoQ"},
{"videoId": "ckcE5JD2dT8"},
{"videoId": "t14NZn6te6c"},
{"videoId": "6LqGbhQE-oY"},
{"videoId": "QKbAiE-z4ow"},
{"videoId": "W1XdKvozUWg"},
{"videoId": "CjquXTwwoaE"},
{"videoId": "MI5ziiXn-PE"},
{"videoId": "f47PY_Cx2tY"},
{"videoId": "FWvesUVyrSU"},
{"videoId": "oStp6NtM6JM"},
{"videoId": "eC526CUSm8o"},
{"videoId": "cJ69xYtAtZA"},
{"videoId": "-8W5zMXviks"},
{"videoId": "MW_Q2snT89I"},
{"videoId": "xEUtBjb2RoE"},
{"videoId": "Yfalnk6nY-U"},
{"videoId": "_VBRAeWBQME"},
{"videoId": "pxZnxsj6FSc"},
{"videoId": "1Q9pNA9dLRs"},
{"videoId": "ll8thPvVuog"},
{"videoId": "FmbIinc7Cgo"},
{"videoId": "aDAyQZlS_eU"},
{"videoId": "vJJSWTiQDJg"},
{"videoId": "HxE6FkFuJBs"},
{"videoId": "ftVRBzIN5k4"},
{"videoId": "M8TK7aVh3hc"},
{"videoId": "M9hbj3phdT8"},
{"videoId": "NQAIxY1fSOs"},
{"videoId": "3aFMEES_fAo"},
{"videoId": "PIDZbG-EMIU"},
{"videoId": "08JOd4KNDxk"},
{"videoId": "q7Rzn4Mqqgg"},
{"videoId": "zx1HBsMZzPE"},
{"videoId": "z3JzLMS4e9M"},
{"videoId": "VxxXtN5HZUA"},
{"videoId": "kCsFsDL6WeY"},
{"videoId": "kwZUzHpRZA0"},
{"videoId": "oqSlhdXAX9U"},
{"videoId": "bRNL-_qyo0Y"},
{"videoId": "EsyFvCxPcHY"},
{"videoId": "3dC8HMmskjs"},
{"videoId": "J-L0TDv38Uo"},
{"videoId": "lTTYa4tIhBI"},
{"videoId": "NO6urGav28E"},
{"videoId": "Zars1R0FjBU"},
{"videoId": "6bwi8vtfxbw"},
{"videoId": "d71N-bKHFG4"},
{"videoId": "ReGOAG4z3w0"},
{"videoId": "cqtHMo9a6EM"},
{"videoId": "in9Z8_elhaA"},
{"videoId": "HbuZlTBpC7I"},
{"videoId": "XpUSn_MnWmU"},
{"videoId": "puhQFH1xdDU"},
{"videoId": "MsucyaxqOT8"},
{"videoId": "99dkWIcCLJ4"},
{"videoId": "9FVJOSD4e0g"},
{"videoId": "oEKA5s2IuWw"},
{"videoId": "r39FRXWUF7s"},
{"videoId": "eLoDEpSRbBc"},
{"videoId": "wEDJSLPLrYc"},
{"videoId": "TGsbzSxpiLo"},
{"videoId": "5kTIx6un_3c"},
{"videoId": "u8jpkxC1eag"},
{"videoId": "D3gLJogctQ0"},
{"videoId": "pP1Pg3kUHYA"},
{"videoId": "paXRcMac7C8"},
{"videoId": "lxIF-gx-y6U"},
{"videoId": "AjdAyRlvGu8"},
{"videoId": "mjVLJbsV7J0"},
{"videoId": "SDkvpjCRG8o"},
{"videoId": "4w1De6nkxcA"},
{"videoId": "zTN4XILDUeU"},
{"videoId": "_MiE3OywAjo"},
{"videoId": "S8uGh8yqKUI"},
{"videoId": "l_ytTJtHK9Q"},
{"videoId": "m33V9ecyJMQ"},
{"videoId": "LU9LuqXjhr0"},
{"videoId": "95rC0oWByos"},
{"videoId": "2Vy7QLIQXmA"},
{"videoId": "-uM84v3YSq8"},
{"videoId": "lXqxo2kgLCc"},
{"videoId": "M4VM-7JZCK4"},
{"videoId": "G_-mLXFdl_Q"},
{"videoId": "ci7_kY6S5os"},
{"videoId": "bx0T74G8MBs"},
{"videoId": "seCjpLZ0lAk"},
{"videoId": "AFtvLxuIpHk"},
{"videoId": "7CztuGkFuAU"},
{"videoId": "2dhGmiBaIm0"},
{"videoId": "CMeTD6Qrkxo"},
{"videoId": "GLgev7wRiSc"},
{"videoId": "4iEgn84zeJI"},
{"videoId": "MxL53_NOmb0"},
{"videoId": "C-g3LkIEElI"},
{"videoId": "cVZheE7mNR4"},
{"videoId": "1_CIt11CgWQ"},
{"videoId": "bDxEQY7wFlg"},
{"videoId": "keUuL1PnDS4"},
{"videoId": "P34fglUFPtU"},
{"videoId": "BZWbKGufqZQ"},
{"videoId": "Xg0cBnJK8C8"},
{"videoId": "0ayARziwJgw"},
{"videoId": "or0YX800OJ0"},
{"videoId": "9ox2wsk15-w"},
{"videoId": "ppKHWoFUmeQ"},
{"videoId": "j2bvI5ao18c"},
{"videoId": "eSU2MbTrFSA"},
{"videoId": "gf3xs2Vm7bA"},
{"videoId": "8s1wY0R1-3I"},
{"videoId": "xs9FkTTnC8U"},
{"videoId": "KEbjyXZTp9c"},
{"videoId": "wUP0OHxCF9c"},
{"videoId": "vQOyhoyA8YM"},
{"videoId": "5_avZ7flNDw"},
{"videoId": "5jBsF6zjrQM"},
{"videoId": "nT8l1igJCYg"},
{"videoId": "A7LJrhp0tq4"},
{"videoId": "-bXP6gtHfwk"},
{"videoId": "TixYKQji_5k"},
{"videoId": "Y0aG4V7e-mM"},
{"videoId": "Va2SoFwRpCw"},
{"videoId": "vp1CXsL3-7c"},
{"videoId": "wxCb3QrO4Dg"},
{"videoId": "sQKpLahT-Ek"},
{"videoId": "IW-lNNd-uI4"},
{"videoId": "C75o5Yw1Uc4"},
{"videoId": "bptoZHw-It8"},
{"videoId": "LVLMS3t4tjw"},
{"videoId": "vXEUpda8VOw"},
{"videoId": "Kki-cUV_FCs"},
{"videoId": "EbUHp00McHE"},
{"videoId": "u4a8Wpjtlvo"},
{"videoId": "Xw0GUNOQ31c"},
{"videoId": "aa1G6D1Ks5A"},
{"videoId": "_5VteF3FLtk"},
{"videoId": "bbvGt_xJZHU"},
{"videoId": "Wk-WJkzWLV0"},
{"videoId": "E-ih1kUh44o"},
{"videoId": "JsqdaJYRGCw"},
{"videoId": "8w4uEKSBYMQ"},
{"videoId": "S7VLIMzFyT4"},
{"videoId": "DCEKsQfPcUk"},
{"videoId": "ZdhSuJ47Zqw"},
{"videoId": "2cvrlIqPhvg"},
{"videoId": "QYHDf-RzVls"},
{"videoId": "QIhMVmIOSLo"},
{"videoId": "KV01RniCGE0"},
{"videoId": "BSskNNiLQTo"},
{"videoId": "41dDUoY832Q"},
{"videoId": "kP1SnmGOFA4"},
{"videoId": "uxo2Ka_En0Q"},
{"videoId": "GuvsBxUWm24"},
{"videoId": "HHUrXgTvxgM"},
{"videoId": "zhT86VFl5c8"},
{"videoId": "2-_NxlGj5oc"},
{"videoId": "lbWsPnafo_A"},
{"videoId": "iHyLbYoyH60"},
{"videoId": "zCtQx7cfBAE"},
{"videoId": "LVFzXmCMRsc"},
{"videoId": "rTF4KANZKUA"},
{"videoId": "ZJRuvbDcBoQ"},
{"videoId": "T7PVOqKt3i4"},
{"videoId": "pzQNQlS3Jto"},
{"videoId": "qVR1vjRUq1s"},
{"videoId": "POGWdmqbprM"},
{"videoId": "UnQmEYouTS0"},
{"videoId": "UQV5w8AES24"},
{"videoId": "71dW_edQQX4"},
{"videoId": "69V9_ar6ZkY"},
{"videoId": "UShSij3_4bQ"},
{"videoId": "TwywlL1dRu4"},
{"videoId": "akMNNpabpVs"},
{"videoId": "YTETMr8PzN8"},
{"videoId": "BLz-Z9yj7WY"},
{"videoId": "g9CkP2xGNZ4"},
{"videoId": "TmIlbyLIcKg"},
{"videoId": "ctvHNKplzbQ"},
{"videoId": "JflGNFwQo0A"},
{"videoId": "2_MCktIND3Q"},
{"videoId": "ZPpsq1IAXuY"},
{"videoId": "-ohsWEtmncY"},
{"videoId": "ISzxZiqo1ts"},
{"videoId": "FTXP4NFW1Jc"},
{"videoId": "bz_kzJqxh8Q"},
{"videoId": "nrr8yezjIvc"},
{"videoId": "X_yKUbouFbc"},
{"videoId": "tyu5591ChAA"},
{"videoId": "JynRMOQ7dhc"},
{"videoId": "0LNxhDnXBTE"},
{"videoId": "Gu8sxtwaS_k"},
{"videoId": "_BR5vTI9Xq8"},
{"videoId": "fjuNbBUcA5I"},
{"videoId": "FJ2TerJByUs"},
{"videoId": "Oawwr749u_8"},
{"videoId": "pcrO_t-ylY0"},
{"videoId": "YfdV7KoFxZk"},
{"videoId": "UsCvaejl0E4"},
{"videoId": "Jj1IIhxdLjU"},
{"videoId": "BVzilgJteow"},
{"videoId": "Kf8uH8pbVN0"},
{"videoId": "1TIDWvMTSD4"},
{"videoId": "fFaEIQacPCo"},
{"videoId": "ziTVhOMcyfM"},
{"videoId": "Smises6rpG8"},
{"videoId": "T-jj6PkqzR8"},
{"videoId": "g8_T4Epm2ww"},
{"videoId": "SNBYsFQt3p8"},
{"videoId": "CzYWzByxdeY"},
{"videoId": "6C9fHN-2dx4"},
{"videoId": "X2LwIiKhczo"},
{"videoId": "ZucB8ezwtgA"},
{"videoId": "OPiLTBDq1HM"},
{"videoId": "dsoPMKmhkmc"},
{"videoId": "u_4SCPxjLMs"},
{"videoId": "PhK40pe8tD0"},
{"videoId": "-GL0FhFI9pI"},
{"videoId": "g8J6SWZQ66s"},
{"videoId": "5ywAIQoc7gM"},
{"videoId": "g59DnQFQHgM"},
{"videoId": "nUgXFvsq7mI"},
{"videoId": "X2j5b1-aKWk"},
{"videoId": "BSiefOyLcds"},
{"videoId": "QUW-bjmfc8g"},
{"videoId": "pfYqPBy73GM"},
{"videoId": "0NAG3vmkFZ8"},
{"videoId": "HGPi_mPc8MQ"},
{"videoId": "0YpivOjP4PQ"},
{"videoId": "AKy6NBCmKaU"},
{"videoId": "bFBIJ9ZsLzA"},
{"videoId": "y-7HQVtrRg8"},
{"videoId": "2MfujgD5j9Y"},
{"videoId": "zIlZkskwLfY"},
{"videoId": "wftv9ZjZk7g"},
{"videoId": "CeMfR7JSG7g"},
{"videoId": "R65cYPiJjB8"},
{"videoId": "lxHq4AsqpOg"},
{"videoId": "GByLXNwdVXc"},
{"videoId": "YzHcsus25HY"},
{"videoId": "RlSQveBV9yw"},
{"videoId": "5JdNULNVcOA"},
{"videoId": "sRB1iYRGTo8"},
{"videoId": "chEQsajkxbg"},
{"videoId": "UISAc0HqXm8"},
{"videoId": "ucN8ftwcDl4"},
{"videoId": "8C30rHKb5Fc"},
{"videoId": "lRyH7PTPQ3A"},
{"videoId": "9SLlCQiqJcU"},
{"videoId": "uYGlk0GdcCg"},
{"videoId": "hrmEO4X__6M"},
{"videoId": "h_fWRNkW6vE"},
{"videoId": "32GTZ6-bUZM"},
{"videoId": "AMbNqVd522c"},
{"videoId": "uZvoDGHN5sU"},
{"videoId": "idAwBwniC0I"},
{"videoId": "2DkWF5hzRl4"},
{"videoId": "Ta_JSBSHOoY"},
{"videoId": "JDPaNL8hab8"},
{"videoId": "VGNbZehEoJo"},
{"videoId": "as65c4Taekw"},
{"videoId": "LR7hmR14z00"},
{"videoId": "o70MzTHHNbI"},
{"videoId": "F7a9YEUmFwA"},
{"videoId": "yaaMuMjo-bA"},
{"videoId": "dUOvC4xjJaQ"},
{"videoId": "kQ6mYT2JD6E"},
{"videoId": "fPUn5qeO39o"},
{"videoId": "oJXBLkkmpEY"},
{"videoId": "r20OUz-WfJ8"},
{"videoId": "C06qTqh9V20"},
{"videoId": "12GSfjEdimY"},
{"videoId": "dHFWQDaQYT4"},
{"videoId": "u6dAUBOpddk"},
{"videoId": "mZ9w48_upko"},
{"videoId": "hOH_WUg5mJY"},
{"videoId": "EhXUPXe0qrY"},
{"videoId": "7FeMVsfzEBg"},
{"videoId": "Ap_9z6euga4"},
{"videoId": "nPrXkwqfXjw"},
{"videoId": "IKrFV4Ylzjk"},
{"videoId": "mbo3zxMdE4c"},
{"videoId": "xHvMc4NHSSY"},
{"videoId": "DlssqJvrw4w"},
{"videoId": "xt6Op5I9avI"},
{"videoId": "UfRX-HNb_bc"},
{"videoId": "kXYJ0CN6X4E"},
{"videoId": "YITXyY2ZIKU"},
{"videoId": "rj4gQ2UAxIA"},
{"videoId": "h9m5h-czCH4"},
{"videoId": "WSKa8rY1fVM"},
{"videoId": "iMLPPO9z978"},
{"videoId": "sbyvcBJcTsA"},
{"videoId": "koEWlRZtgOk"},
{"videoId": "vHryX9dVlxk"},
{"videoId": "Kr_Ggv6OkHw"},
{"videoId": "-azF37S54lU"},
{"videoId": "km804UOpqrk"},
{"videoId": "U1dM5Ij12BU"},
{"videoId": "3kpGv-nKAqc"},
{"videoId": "Rp54JAStwK8"},
{"videoId": "buwz377kC1A"},
{"videoId": "ZPV7l3O1SdU"},
{"videoId": "RxINge9nxAw"},
{"videoId": "8wX5T7lykRI"},
{"videoId": "gvHWtRrihuk"},
{"videoId": "F600bVI0BOI"},
{"videoId": "1iumQ0wr0J0"},
{"videoId": "iosfGvipZx8"},
{"videoId": "Y0GlvqmyNlk"},
{"videoId": "FS7fpU6DbqM"},
{"videoId": "tjEDnnPPREw"},
{"videoId": "D7UJCbAlY2A"},
{"videoId": "A_iUBx5xYEE"},
{"videoId": "4OoY1wn1mTs"},
{"videoId": "zPvyaXLUmVg"},
{"videoId": "DJlhMY0e5nI"},
{"videoId": "yJjP3oartHk"},
{"videoId": "sBtYWK817-0"},
{"videoId": "H562kY8cG7M"},
{"videoId": "VgF7HXeWFrw"},
{"videoId": "tNfeKaQVSyk"},
{"videoId": "M8Zd1COi7Yk"},
{"videoId": "Ulb12pUiqsM"},
{"videoId": "shcGFK3H3Fo"},
{"videoId": "gpP4yhi9Hhs"},
{"videoId": "lUvjKyOmZNA"},
{"videoId": "xGmTS2b-L7s"},
{"videoId": "KoJ8Hxqt9EE"},
{"videoId": "Ta8oXpSlZ9o"},
{"videoId": "YZWxFj86urE"},
{"videoId": "bQEQkx3819s"},
{"videoId": "kFKGKypoPUY"},
{"videoId": "vORqetwgsPM"},
{"videoId": "RJmSvbTJcwA"},
{"videoId": "JvWj7SAnZNs"},
{"videoId": "0yNot060rHM"},
{"videoId": "HicDCPkRTAs"},
{"videoId": "db59b1L0pc0"},
{"videoId": "RcSzIlxBs4g"},
{"videoId": "wU6rj_jQ9YE"},
{"videoId": "VvADdfX1iz8"},
{"videoId": "srTkbEY9rS8"},
{"videoId": "UL348iJJXgc"},
{"videoId": "lGLF1FjpTHE"},
{"videoId": "wniwceFA140"},
{"videoId": "L_QaZcQvS9I"},
{"videoId": "4xqEXRC-xyU"},
{"videoId": "ZyR_gQaM_nU"},
{"videoId": "8bAs5zcKS7I"},
{"videoId": "GSaV0akUEAg"},
{"videoId": "RT4hEmX5OJ0"},
{"videoId": "bBCIdlFSCxI"},
{"videoId": "ngNrm977jJc"},
{"videoId": "_woNw8dg0G8"},
{"videoId": "z1b0eVX7SjE"},
{"videoId": "_ikm3FGsbCU"},
{"videoId": "B2wzeqxJn0s"},
{"videoId": "YwNHhZkHD1U"},
{"videoId": "jwNALqJaLhE"},
{"videoId": "hzeIYO2t7Q4"},
{"videoId": "iER-35X1nr4"},
{"videoId": "iO27wFgSDPo"},
{"videoId": "m2Efei187cE"},
{"videoId": "a1YYkHeegDg"},
{"videoId": "Tk6FNC5YHyE"},
{"videoId": "mRq0FH0G8dQ"},
{"videoId": "ZBlYfb6t1A8"},
{"videoId": "6LhzwP7Kl8w"},
{"videoId": "Fu6YZFXReR0"},
{"videoId": "oBdkylF5fVk"},
{"videoId": "GxjEg5XQt_A"},
{"videoId": "Jy0clN5HDh4"},
{"videoId": "GJAQdFvIYzg"},
{"videoId": "QD8f3j62f_s"},
{"videoId": "ebDI6fZOe9M"},
{"videoId": "CiEdy8eDSLk"},
{"videoId": "0ZFija5kcy0"},
{"videoId": "FERxVSogRIM"},
{"videoId": "JKfeKxZ1dHw"},
{"videoId": "bmiRcusT2Iw"},
{"videoId": "8LXyuAnxb00"},
{"videoId": "c4dF8Kvfcow"},
{"videoId": "AXiDQHHRujY"},
{"videoId": "0Ulbkkc52ZQ"},
{"videoId": "ZNZSX5Nv8fs"},
{"videoId": "dYuDW3WeKYA"},
{"videoId": "XDZ9mn5NU2Q"},
{"videoId": "BDb2heXeN90"},
{"videoId": "aeKUpcB-1-g"},
{"videoId": "KteEsNwEX90"},
{"videoId": "oBh8YLSS3rw"},
{"videoId": "cZy0WFCYhRo"},
{"videoId": "qE9SEFT1vas"},
{"videoId": "K8b_znapiQs"},
{"videoId": "Dlf_8k4ZuR8"},
{"videoId": "FKCoLPuF0Dc"},
{"videoId": "BfKkNP6vuoM"},
{"videoId": "ujOZAw3Stgw"},
{"videoId": "rshCZ0rPE7U"},
{"videoId": "QJIwws_kk-Q"},
{"videoId": "ToePlw6OI6c"},
{"videoId": "wEKA5lOTJXg"},
{"videoId": "Va_9Q6ekm60"},
{"videoId": "QA-s4vgDqc8"},
{"videoId": "TgR4dffEE7g"},
{"videoId": "T5XMorGDSfY"},
{"videoId": "9apKEKoLn0o"},
{"videoId": "R6BwCuMErhw"},
{"videoId": "ulxzO1b6_4Y"},
{"videoId": "OcLsIOJOiFA"},
{"videoId": "NZfqEYgZeOY"},
{"videoId": "SDNQSiwf4hs"},
{"videoId": "dGebmsvZITo"},
{"videoId": "e2_exAgmVe8"},
{"videoId": "-10BEhI3Kg0"},
{"videoId": "3zzPk-k4Xaw"},
{"videoId": "bW7f20QOkgk"},
{"videoId": "vguI3rbb05o"},
{"videoId": "hyUN82Up2-g"},
{"videoId": "ALW-To76E44"},
{"videoId": "8ISI2bnlF4M"},
{"videoId": "GXKdfwuZIDM"},
{"videoId": "jO4OA0p7960"},
{"videoId": "b2JfHPOwKp8"},
{"videoId": "XNPGClgYu8Q"},
{"videoId": "ZKGysPm9O1s"},
{"videoId": "rgI06VbObEI"},
{"videoId": "3sx-32ITkrQ"},
{"videoId": "4jxjui2xX7A"},
{"videoId": "6LySxRp9ny4"},
{"videoId": "BEc_qq8jPdY"},
{"videoId": "XRe68ZJHRk4"},
{"videoId": "f9X9-3CetaM"},
{"videoId": "ZyJRDGJ2RDg"},
{"videoId": "sKNURGeU5qE"},
{"videoId": "cFF-sICXDvg"},
{"videoId": "ivPLdvoL4qw"},
{"videoId": "ZVkjfZRHX9w"},
{"videoId": "W355UxrTNrg"},
{"videoId": "W35bADjJTAg"},
{"videoId": "Vlr-7VsNwW0"},
{"videoId": "bjSG3MpeOWk"},
{"videoId": "I2XIjxYMHeA"},
{"videoId": "DNMgWEzSEfs"},
{"videoId": "fTmS7nS35Dc"},
{"videoId": "469poyeyLa8"},
{"videoId": "Wwd27Tl3CL0"},
{"videoId": "M14m1X0Y7H8"},
{"videoId": "5avwmQSW5yo"},
{"videoId": "AkZXE9Qo634"},
{"videoId": "5jKslOUVchM"},
{"videoId": "wLtVgLt7dBA"},
{"videoId": "7kbmHFgYlS8"},
{"videoId": "eL4sfKTdf9I"},
{"videoId": "wIGJMPb0N_s"},
{"videoId": "SYrtIRIXqa8"},
{"videoId": "7EX5wTOQTvI"},
{"videoId": "D7oInFgaeR0"},
{"videoId": "lmoZ_W4WjW0"},
{"videoId": "IWdBS5WFHNI"},
{"videoId": "qnp4DkIrYU8"},
{"videoId": "FvLqtG9l5dI"},
{"videoId": "pGiCA2XSSQs"},
{"videoId": "URDgjf_wcTY"},
{"videoId": "SzW_QDw9H0Q"},
{"videoId": "bMe7f6fxe88"},
{"videoId": "cJwgkB9PavQ"},
{"videoId": "SyB4PXsWWGk"},
{"videoId": "RQSe01H0bHA"},
{"videoId": "kmgndwt1CmM"},
{"videoId": "2Z3frGyf-1E"},
{"videoId": "efMoDReVGYA"},
{"videoId": "l0e_VestmJU"},
{"videoId": "q7BBuQ9go7s"},
{"videoId": "WdTKfn_1518"},
{"videoId": "gTwKSMwT1dY"},
{"videoId": "uT5DuMmQWxY"},
{"videoId": "VunSYVHE0Vo"},
{"videoId": "cL520XmH_a8"},
{"videoId": "1gix9T-P4C4"},
{"videoId": "LCBHTX4JYEs"},
{"videoId": "DyEYMd6ZhDs"},
{"videoId": "nWiCsPQxPm0"},
{"videoId": "3ytGYnOpV-4"},
{"videoId": "c41ddDC9fO8"},
{"videoId": "xDOTRJjQVe8"},
{"videoId": "r3V9fN__SSU"},
{"videoId": "Dzvkai3EZYM"},
{"videoId": "LItYPmqv-iw"},
{"videoId": "wMMqm0XCBFM"},
{"videoId": "TfAA1L5TXrk"},
{"videoId": "tJ4AraQMvAY"},
{"videoId": "FdCA5yxlxF8"},
{"videoId": "ajcvKUS6rHo"},
{"videoId": "YX0-pxEOGgI"},
{"videoId": "ZVcJVmyjhyw"},
{"videoId": "4qe-ztWE8QA"},
{"videoId": "QWnaAWz0KyI"},
{"videoId": "bAdH6iccPEU"},
{"videoId": "Ru__PQezKX8"},
{"videoId": "gnPA_NC7Hh0"},
{"videoId": "Q0KCt13GRJE"},
{"videoId": "S53Nm0HSw80"},
{"videoId": "4h2HqFMKuT4"},
{"videoId": "8TiJESsKCQg"},
{"videoId": "miEC_l7iV40"},
{"videoId": "gWdl_O7DMEQ"},
{"videoId": "af7YIYc-5bI"},
{"videoId": "OP4Kzb6p-sw"},
{"videoId": "m3lopipr7ZA"},
{"videoId": "l11P0lIpRKU"},
{"videoId": "w9pVfhTwRYY"},
{"videoId": "polayJ8kA1g"},
{"videoId": "0x4MPCaccHU"},
{"videoId": "W1Uz1TQ1v3w"},
{"videoId": "z5URq22-COA"},
{"videoId": "9ElZ1f0-oiQ"},
{"videoId": "WkBZY5JlkmM"},
{"videoId": "CyrHeSfvVFM"},
{"videoId": "KjaWS187tsc"},
{"videoId": "qS-L7HT5RoQ"},
{"videoId": "ask9QP0OZE0"},
{"videoId": "V6TbC_1i5OU"},
{"videoId": "2h6AKwcsB4c"},
{"videoId": "7zZKaL8Qp_w"},
{"videoId": "wu7vnrk89aM"},
{"videoId": "GY8fOTsJZr8"},
{"videoId": "5by6kTa5efg"},
{"videoId": "BI3VnzcX36I"},
{"videoId": "KCR37fonhw0"},
{"videoId": "-qgVSDjfuWg"},
{"videoId": "50lkxdu_NvE"},
{"videoId": "zcHC5Utu9h4"},
{"videoId": "sniHnzA5cxs"},
{"videoId": "13jhFFYCWVU"},
{"videoId": "aQNzparnKlc"},
{"videoId": "No4k_76Bd9s"},
{"videoId": "BdZd0Sw33DQ"},
{"videoId": "49axJtrcldw"},
{"videoId": "7xe9p4nw6Lg"},
{"videoId": "Ovac6OieO6E"},
{"videoId": "INHmpwNi6Zo"},
{"videoId": "Qaj0MbvTZsg"},
{"videoId": "w2ZRz62oHxo"},
{"videoId": "zGNuTTnnpN4"},
{"videoId": "m3M9Ri4Jtpg"},
{"videoId": "C-5XYlGeOVU"},
{"videoId": "tCwm3KHzuqM"},
{"videoId": "S5fQ9phGUek"},
{"videoId": "WnXXso3-_Xw"},
{"videoId": "Cs2aajo1zDs"},
{"videoId": "40MgTp5GosA"},
{"videoId": "aJoS2Ig2At8"},
{"videoId": "TUxhSregQ_k"},
{"videoId": "wPxgs690ZPY"},
{"videoId": "P0PZpmYnaXo"},
{"videoId": "PLF36mawmMQ"},
{"videoId": "tmdGq8xYA8o"},
{"videoId": "tFHlsPtFkBQ"},
{"videoId": "TnCTzJXVfsY"},
{"videoId": "RUzlgtIqXKo"},
{"videoId": "aI_7S6f4Qyc"},
{"videoId": "LxlCTyvnAU0"},
{"videoId": "L4QP_UQSP4M"},
{"videoId": "fWC-U_C4ZQI"},
{"videoId": "a-eYn2lZX24"},
{"videoId": "5EOA8RiwKBM"},
{"videoId": "REp8Izeyr0c"},
{"videoId": "JMKfe6KsxsY"},
{"videoId": "pwhbmORHbMs"},
{"videoId": "WuC2-AG8ZAY"},
{"videoId": "b3lzo1JaA4U"},
{"videoId": "qKujE1qoNxQ"},
{"videoId": "LrqeDxwOG78"},
{"videoId": "Nyxaj-WxKkg"},
{"videoId": "D_bKyBMw9CQ"},
{"videoId": "CZmryoWt6Rg"},
{"videoId": "FmzdhNywnNY"},
{"videoId": "x95QowftGlw"},
{"videoId": "FUeafn4VvXQ"},
{"videoId": "YAZpV7uFCQ8"},
{"videoId": "kJSKAsjUY3g"},
{"videoId": "bduJpXrdi7w"},
{"videoId": "zwSQODPZBE0"},
{"videoId": "P-KLWXCc2es"},
{"videoId": "hvuxwrJwHdQ"},
{"videoId": "1nITLFUH4NA"},
{"videoId": "kx1iIpKSx3g"},
{"videoId": "cau1lhtYaro"},
{"videoId": "scDUuTST0Sc"},
{"videoId": "GyNgY7iYZgg"},
{"videoId": "_ckEjp2NTME"},
{"videoId": "WP6ff928E00"},
{"videoId": "WgIYpD0EEmo"},
{"videoId": "_kwLs2-kZj0"},
{"videoId": "E9LqMCg5NcI"},
{"videoId": "lV7Y-ko7mcg"},
{"videoId": "jiOZ5QHuR98"},
{"videoId": "D4z8Ed3UVqw"},
{"videoId": "nKoclggSisE"},
{"videoId": "hWUkV8ymv9U"},
{"videoId": "efIgaGrgCcY"},
{"videoId": "fFjdG7Vcmqc"},
{"videoId": "xwznoKEDs_0"},
{"videoId": "CKRdp91IaKo"},
{"videoId": "qjCLQgPHkrg"},
{"videoId": "rI_LzgUgA9A"},
{"videoId": "5FXNFrUyp0A"},
{"videoId": "tc_psAFQmeo"},
{"videoId": "OkWk6Tup3I8"},
{"videoId": "Jks5sBE-q5c"},
{"videoId": "az0kC5MYJNY"},
{"videoId": "YGuSQaShDok"},
{"videoId": "Ck7SKfboLfs"},
{"videoId": "Kw13BsXwA9U"},
{"videoId": "AJUSIWSaQX4"},
{"videoId": "TGSvhr_yD98"},
{"videoId": "u0jSZXVixmg"},
{"videoId": "GrGXd1lENbc"},
{"videoId": "L5mlV1p6ZWg"},
{"videoId": "D_90AIWUfrs"},
{"videoId": "TtUj3yQdvDQ"},
{"videoId": "0xzDG8NLCxI"},
{"videoId": "gal-wAsnKA8"},
{"videoId": "eWf9s7rcRFg"},
{"videoId": "vsnYyV_X3lQ"},
{"videoId": "LpifVEGnYRo"},
{"videoId": "0lmdB1QDRbs"},
{"videoId": "7ZH26sxeot0"},
{"videoId": "TR4OoKdCuLs"},
{"videoId": "6fTrhdU2J0Q"},
{"videoId": "fQYryTwGQqc"},
{"videoId": "XIcElOH0KWc"},
{"videoId": "1chHHtwSyRQ"},
{"videoId": "hpQ5eGnRKeM"},
{"videoId": "8Am1OWuH74g"},
{"videoId": "FngEZOvnNxg"},
{"videoId": "UfjBS4C_M_4"},
{"videoId": "IdcFWWTyQXI"},
{"videoId": "s36lF5OlxqQ"},
{"videoId": "IyqyU6_9_Tc"},
{"videoId": "EJzTplLqypA"},
{"videoId": "CZTRyhyPl2c"},
{"videoId": "5UNzz1ObvcM"},
{"videoId": "6hRtG_m0QTY"},
{"videoId": "ewvm9Q4nwek"},
{"videoId": "0fbqfPeeGQ8"},
{"videoId": "9MK7IiY822w"},
{"videoId": "SYE0eTOIyYs"},
{"videoId": "Wu_PvsAWdGA"},
{"videoId": "_Jr491OotK0"},
{"videoId": "n3cNBQ05q7M"},
{"videoId": "2q7mO8cNAKg"},
{"videoId": "Nbgw_woSj40"},
{"videoId": "Pp1kZop6BTw"},
{"videoId": "G9AiRatdQD0"},
{"videoId": "8WUCUjjfR6g"},
{"videoId": "KaUTnwWjMaw"},
{"videoId": "JxfICWI2q6s"},
{"videoId": "i18nHy5CWgk"},
{"videoId": "gBDvoMFsceI"},
{"videoId": "6_OO9euQw8c"},
{"videoId": "OkuIumjh1w0"},
{"videoId": "OIcJ0LqKi9Y"},
{"videoId": "zZ4XS-yZstg"},
{"videoId": "N60KEQ3x9mM"},
{"videoId": "yTbGZNVBjN8"},
{"videoId": "JCBoHLkNug4"},
{"videoId": "oy2CwLa9vgA"},
{"videoId": "_j2Y6XBsQR4"},
{"videoId": "F1I1xzta3zw"},
{"videoId": "Ux2k6YoxfeU"},
{"videoId": "vGI9KmmI8pQ"},
{"videoId": "ykOftbUQsfM"},
{"videoId": "YiSU1m36adk"},
{"videoId": "O4NXT74Eiys"},
{"videoId": "k3WdXofrR-s"},
{"videoId": "cBTVMWJ7lgs"},
{"videoId": "3FdMGm5Nf08"},
{"videoId": "Oq7mX42V0kM"},
{"videoId": "HzXhfUttJck"},
{"videoId": "ErvqlU0-HVg"},
{"videoId": "PTZwrxdJp2c"},
{"videoId": "dlBz_N5dqnA"},
{"videoId": "XEfSfBAmsto"},
{"videoId": "bMeVVm16Fuc"},
{"videoId": "E2sW9rO-2qY"},
{"videoId": "H7LcgDQAIew"},
{"videoId": "QCT-6RfTZjA"},
{"videoId": "8UXDhaL83zI"},
{"videoId": "vPCk06L4Phs"},
{"videoId": "lnHZs_my0RU"},
{"videoId": "ANSqXvxd5HY"},
{"videoId": "zZKbGm0J1wY"},
{"videoId": "XtBBFe_E7lc"},
{"videoId": "n2mJ2eB7tso"},
{"videoId": "cPRkOQJZfLM"},
{"videoId": "v3zLeGImFqM"},
{"videoId": "SbpA8AkJlFY"},
{"videoId": "wfwoF7sJcTo"},
{"videoId": "kWAQqiAWCsA"},
{"videoId": "NpcnKUyC2N8"},
{"videoId": "528WE6P-3Io"},
{"videoId": "VglSRPqyG8o"},
{"videoId": "BmEFZYOMCgI"},
{"videoId": "RvLkqQ9TJl4"},
{"videoId": "-tQLt8QPI_c"},
{"videoId": "t2wbD73wMjA"},
{"videoId": "3CeGS_PsY2s"},
{"videoId": "0UDP-ALV59Y"},
{"videoId": "M7b8cJgTH5k"},
{"videoId": "Z_a5_vR0Ahs"},
{"videoId": "YhstBBaIDP8"},
{"videoId": "KaVzCMug96M"},
{"videoId": "5oQIUoXmm1Y"},
{"videoId": "XPnlToRKfT4"},
{"videoId": "cJ5d-6H7Z9o"},
{"videoId": "_ft602uvriQ"},
{"videoId": "oU-sP6LqvSs"},
{"videoId": "ERFrPeB3hsg"},
{"videoId": "6Tcilb0hgwQ"},
{"videoId": "5xLIY6VEq5Q"},
{"videoId": "9XWuiDean0g"},
{"videoId": "YuFkdSzklFU"},
{"videoId": "3UOCxThIolc"},
{"videoId": "Lv0UAdpTHuM"},
{"videoId": "dijNrMRybiw"},
{"videoId": "cvQ_nu810GE"},
{"videoId": "Nm7udBJFQxg"},
{"videoId": "cKvjRiqNmJU"},
{"videoId": "2I0gKwPWP1I"},
{"videoId": "vV_9228lKsE"},
{"videoId": "n5qGU3fSsho"},
{"videoId": "nU64JwuO0aw"},
{"videoId": "gQPJg12sEFo"},
{"videoId": "T3jMEGfcHlU"},
{"videoId": "fkPg2ONbfjs"},
{"videoId": "DayUxhXNDoE"},
{"videoId": "2oRusVjdw3k"},
{"videoId": "QsueAUWMmxo"},
{"videoId": "Fb51phC1jXI"},
{"videoId": "mp4vIx2t4pM"},
{"videoId": "uQVFwl63_M8"},
{"videoId": "Ip1yxHuzjB0"},
{"videoId": "Ko6-sS81Yfk"},
{"videoId": "ZfQgq_6EZN4"},
{"videoId": "XeZUEMVn7rU"},
{"videoId": "dlr79NUXzm8"},
{"videoId": "uQnTe26tpJE"},
{"videoId": "L7wwnsp9qC4"},
{"videoId": "YnHtMO2MmKA"},
{"videoId": "c5c_Efn3iAc"},
{"videoId": "V-BbNoN_W9Q"},
{"videoId": "g0MTuNzINeM"},
{"videoId": "XEsUrzwCzpI"},
{"videoId": "akWm1VVff1A"},
{"videoId": "i1K4gwC0Ka8"},
{"videoId": "pkkhdT0SKoo"},
{"videoId": "Ji7iualGmjs"},
{"videoId": "nNKu06oJpo0"},
{"videoId": "SxeKs1saIqA"},
{"videoId": "flww_oA_tzQ"},
{"videoId": "OGm7pdmKyGY"},
{"videoId": "wGbqcPZY1tQ"},
{"videoId": "0uoo0k7z6qw"},
{"videoId": "pKV53jF-Mg8"},
{"videoId": "0OgvdLjIyTg"},
{"videoId": "jMcinIPeCVI"},
{"videoId": "onywnvkOS2M"},
{"videoId": "SqYeRX6fqiQ"},
{"videoId": "OO7qFtuFyMQ"},
{"videoId": "2NzYYbSLVfU"},
{"videoId": "9--vXPiJJS4"},
{"videoId": "HFUrbHUzDik"},
{"videoId": "W3Ei2Gu0X0A"},
{"videoId": "dVSjIzT1wfo"},
{"videoId": "G7PxPBdukWg"},
{"videoId": "emJ8LNDg-LA"},
{"videoId": "8zLXw7SQvAk"},
{"videoId": "0WKdetgzXHU"},
{"videoId": "1wIAJVnSLmg"},
{"videoId": "mdX_E5-I78g"},
{"videoId": "6ZBHBxwbBDE"},
{"videoId": "aJTsGfNnnjQ"},
{"videoId": "jxQX5XI766c"},
{"videoId": "2SWmbEnnbow"},
{"videoId": "DdIf73EN3XE"},
{"videoId": "drUTDPAOAiI"},
{"videoId": "SFgpIq7KTaY"},
{"videoId": "DU8czjttKhw"},
{"videoId": "c7Ce4GPDx_8"},
{"videoId": "j_9jYzFQEnU"},
{"videoId": "o4VX5wEQMZ8"},
{"videoId": "bvzCe0_HQqg"},
{"videoId": "OX8RkBJwTKI"},
{"videoId": "Hu5oaFmEkmo"},
{"videoId": "-y34tsX_-RQ"},
{"videoId": "fvgH87UiBZY"},
{"videoId": "G0aLC78Wb2g"},
{"videoId": "znGG3M7Uc8g"},
{"videoId": "dcCQLAWSXNQ"},
{"videoId": "wtiB-tslxqE"},
{"videoId": "_kII_-RhzPc"},
{"videoId": "5xvMciThpFI"},
{"videoId": "gS2VQevXW6M"},
{"videoId": "ViideM4Zp1E"},
{"videoId": "LTBkfEXGHD4"},
{"videoId": "moZZ5YAgxYY"},
{"videoId": "zndFxxtJjHs"},
{"videoId": "3YgCXki2FWQ"},
{"videoId": "NCLRXV_5L2g"},
{"videoId": "cDlp0bJbrkg"},
{"videoId": "sg-FrT_AQN8"},
{"videoId": "Z1AzIka0jQM"},
{"videoId": "WZWOJqxwzr8"},
{"videoId": "46pKHXnM8N8"},
{"videoId": "n575sKRk4iY"},
{"videoId": "pq3sQvB59Ec"},
{"videoId": "udtN3czhkA8"},
{"videoId": "UBFn7Z3NSwY"},
{"videoId": "SApH5A410c8"},
{"videoId": "nXKhVo1vnKY"},
{"videoId": "X-xNLSQrMCs"},
{"videoId": "dfk3yC7XVsw"},
{"videoId": "MIXgTbgJSr0"},
{"videoId": "G6oVaHkCJMo"},
{"videoId": "XGFudNJU3cw"},
{"videoId": "jaKAQiKsCjA"},
{"videoId": "uiaK73lV7Z4"},
{"videoId": "1qt8XvC0IAs"},
{"videoId": "jUgySfGFohw"},
{"videoId": "cOYd-g7nF0A"},
{"videoId": "pg_55jPfryg"},
{"videoId": "RThfKd8M0Dk"},
{"videoId": "FH_txbw8n18"},
{"videoId": "Ma1GB6KgL-c"},
{"videoId": "NpWAgcNnPB8"},
{"videoId": "SHeUg1GPYi4"},
{"videoId": "k1HjrSML61U"},
{"videoId": "MKGRNFeZ60s"},
{"videoId": "e6V8pNVQ90I"},
{"videoId": "KxIVip1kEOI"},
{"videoId": "PS-7Gxl92ks"},
{"videoId": "IuTDuvYr7f0"},
{"videoId": "p8mI58SjIKw"},
{"videoId": "OOR-Mv7OQ34"},
{"videoId": "WB9lKbkMu30"},
{"videoId": "NV-7yREq7DA"},
{"videoId": "BH6F13P79nM"},
{"videoId": "QWNvlGXiklU"},
{"videoId": "dxpFYnkTVyc"},
{"videoId": "NJBj2Q3Hl_M"},
{"videoId": "nK1f0QQ18eA"},
{"videoId": "rr7He2qTSJI"},
{"videoId": "BGbYV7FDl6I"},
{"videoId": "IIC3qwKc2Zw"},
{"videoId": "X3KjIpIL_p4"},
{"videoId": "d2tNYGXhznM"},
{"videoId": "jKXN_sxrBIA"},
{"videoId": "D3gG_t2ED5o"},
{"videoId": "xJzPv0PiePI"},
{"videoId": "qrUeBUx7PPo"},
{"videoId": "GGM4id9wCYg"},
{"videoId": "mMm-9YHFbRk"},
{"videoId": "KAjGKpwqaME"},
{"videoId": "MNHOcpDhxy0"},
{"videoId": "JN53A2-gUcY"},
{"videoId": "qMuKqMxpc74"},
{"videoId": "tdfWkXJPBj0"},
{"videoId": "QvuAffcTjW8"},
{"videoId": "kqzwDl6p5Yk"},
{"videoId": "hFMIuKfu_0c"},
{"videoId": "3j9NATOoVSA"},
{"videoId": "BlBSswCVNPw"},
{"videoId": "UhVJOv2h6vg"},
{"videoId": "7iXoAamEy1Q"},
{"videoId": "Xy-8E2bHXqQ"},
{"videoId": "CQ1IcIs6Gr4"},
{"videoId": "Mu3RQYP7Heo"},
{"videoId": "cBMdODJ4kng"},
{"videoId": "_sK_PcFqG1A"},
{"videoId": "Jzug0D-FyJc"},
{"videoId": "m1h3snpyjlA"},
{"videoId": "76qpAcZe2Jk"},
{"videoId": "Lz_-4WPDp0M"},
{"videoId": "u9IJ0HoN-sY"},
{"videoId": "zAVb3a22LCc"},
{"videoId": "eqc3ga7D-Ow"},
{"videoId": "6ZLXCdDBHY8"},
{"videoId": "-MjwtEhNfAI"},
{"videoId": "ZsFe_wv0TU0"},
{"videoId": "Ikj8g4smmcU"},
{"videoId": "icNPagmUV8U"},
{"videoId": "UeJWT8xfER4"},
{"videoId": "W_dyGtEIis4"},
{"videoId": "Z1qoCENZtao"},
{"videoId": "SV6ksRisBi0"},
{"videoId": "dKxMV0wSfOE"},
{"videoId": "cr1COqMtF-M"},
{"videoId": "9ykDlZUVe38"},
{"videoId": "fGID_6K9KgI"},
{"videoId": "W-p25HSasbQ"},
{"videoId": "0AwvPqE96Fg"},
{"videoId": "zeAv-9GWcoQ"},
{"videoId": "sDnjwcHDsdg"},
{"videoId": "mKK5GDHtlfE"},
{"videoId": "o1pa7iW39iU"},
{"videoId": "TnN1r1ug0N4"},
{"videoId": "bOZri29HYNs"},
{"videoId": "P-b30Cnzc40"},
{"videoId": "eUXPHStLa6w"},
{"videoId": "dDsmiYwZZ6I"},
{"videoId": "4LI9UsJCgIM"},
{"videoId": "w-m4UON2Hlk"},
{"videoId": "TlTCa-Aiv1U"},
{"videoId": "SUnnPPftgto"},
{"videoId": "dWJIYgD-MjI"},
{"videoId": "7Z7fAWFIb6U"},
{"videoId": "8d8DUKEXSkM"},
{"videoId": "lCNZJLhOdTI"},
{"videoId": "pC8DmcF6_c4"},
{"videoId": "O4-JLLaBWUs"},
{"videoId": "kPl9_ApP4dQ"},
{"videoId": "Q4d-vMWYqZA"},
{"videoId": "-wwj3ltlI9g"},
{"videoId": "xONIYvvTYIY"},
{"videoId": "TRpZ-pTHdjs"},
{"videoId": "qgIoRLtw8NI"},
{"videoId": "TtH7iORXS14"},
{"videoId": "JY_DmPtMkH4"},
{"videoId": "fjiIznOBe_0"},
{"videoId": "7RbNqA9rGY0"},
{"videoId": "YH7WYbD2uiU"},
{"videoId": "m2_Ud5v-aVI"},
{"videoId": "hVl8c13b-k0"},
{"videoId": "pkWUUVHaToE"},
{"videoId": "sohJHBo_zt4"},
{"videoId": "e5vE-urbUYE"},
{"videoId": "s4_aU_46c1I"},
{"videoId": "dc2hohNLNW8"},
{"videoId": "4DCFFVIoD-w"},
{"videoId": "n0SiE3zST-Y"},
{"videoId": "Pbp4lHfOFBE"},
{"videoId": "geQVAmY9r-w"},
{"videoId": "nrD7hONx-YA"},
{"videoId": "6BtxZ4lU26Y"},
{"videoId": "A2FQlSodjUQ"},
{"videoId": "SqWop8LQNkA"},
{"videoId": "-m1QVTCkzB8"},
{"videoId": "K1n55zRSLCQ"},
{"videoId": "XjS8vmLcpqM"},
{"videoId": "2O9cUrhhJvc"},
{"videoId": "cClQPSfbMnM"},
{"videoId": "NZBEB5rkehA"},
{"videoId": "sz2THpgDKGA"},
{"videoId": "ESrD9RGrx4Q"},
{"videoId": "FnZblIASEyw"},
{"videoId": "jxMQ0Cti4xo"},
{"videoId": "_39g1_jEMc8"},
{"videoId": "S3hGlrP-o3o"},
{"videoId": "DRkdlb56vrs"},
{"videoId": "9KrenuG-oH8"},
{"videoId": "IzH8tngsQJM"},
{"videoId": "Wpqx8gkFG_o"},
{"videoId": "aq3yZp3Hmuk"},
{"videoId": "hPphkPTpCiQ"},
{"videoId": "sFPYSLSsgwM"},
{"videoId": "nwTuzJHW4ZM"},
{"videoId": "iwLtBXcnMpc"},
{"videoId": "Qclyxn9cXbk"},
{"videoId": "TfwxEiOrjug"},
{"videoId": "ybbM5DKlW8I"},
{"videoId": "h6F425zz5PI"},
{"videoId": "SXV3uxbHK8s"},
{"videoId": "fTwA2tDhw5Y"},
{"videoId": "Htm5Cj7sx98"},
{"videoId": "cftNdG-sp2U"},
{"videoId": "30rksQEkA4Y"},
{"videoId": "3dMxKnjiETA"},
{"videoId": "yligV73N_04"},
{"videoId": "jQTjbyHUfE8"},
{"videoId": "MwlYzleT4yA"},
{"videoId": "DqBmh_uby84"},
{"videoId": "ZuUdYLSywoU"},
{"videoId": "ZzqDqd_P6os"},
{"videoId": "Zx23OSa6AnI"},
{"videoId": "-P3GtwHri_E"},
{"videoId": "DyAaqUcXWXQ"},
{"videoId": "cjUuSwzJ_9A"},
{"videoId": "v1QSkeVtpRk"},
{"videoId": "MlqIhcanL2Y"},
{"videoId": "q3ReTI5ri_8"},
{"videoId": "lekOAxyJM64"},
{"videoId": "-sH9-yGs12M"},
{"videoId": "AJ9U6FVgWOA"},
{"videoId": "P8eIK5XCnAQ"},
{"videoId": "ya5SVVAuU8M"},
{"videoId": "UFfcvAQCqyY"},
{"videoId": "-tAragAg8kc"},
{"videoId": "_i5rjVHcGw8"},
{"videoId": "LerRnhrM6gI"},
{"videoId": "eEVghtaQLWI"},
{"videoId": "2RWQMjYkq9s"},
{"videoId": "60uhUlLG3pg"},
{"videoId": "QfBK028xvuM"},
{"videoId": "8RYv01ByGKA"},
{"videoId": "9oHJOYFKS0g"},
{"videoId": "ZANLTnCfhyc"},
{"videoId": "-ey2HgEbECo"},
{"videoId": "8x1Leni3aqk"},
{"videoId": "F7l9HrKr4YI"},
{"videoId": "RavihuwgOrg"},
{"videoId": "73bC2P2tamg"},
{"videoId": "omwQ56PLM3I"},
{"videoId": "VqlHO2G6Bro"},
{"videoId": "yJWJJvKNar0"},
{"videoId": "OIcdWlMn-Yk"},
{"videoId": "RRLBzRHPKqk"},
{"videoId": "Nv0_vGgzGXk"},
{"videoId": "nElEjVLUyAs"},
{"videoId": "FXVBYdUefQk"},
{"videoId": "5RP19udcHOg"},
{"videoId": "l0IeX69EQnc"},
{"videoId": "ocza9IC5cEw"},
{"videoId": "eL7VSr1AHbk"},
{"videoId": "Uj3XUUlYaUQ"},
{"videoId": "hIldXa32nsk"},
{"videoId": "G_gyuL5GFi8"},
{"videoId": "omKBwt5E2Ss"},
{"videoId": "z8y_LbRQpLE"},
{"videoId": "2iGxB58D2HI"},
{"videoId": "Lv48vr2vWdU"},
{"videoId": "wwm454_rS7E"},
{"videoId": "5q5CZOBlbro"},
{"videoId": "ltv1AAO5EJ4"},
{"videoId": "bvCFn6p87OQ"},
{"videoId": "LM0x6egUWuM"},
{"videoId": "tYfWhENF-oU"},
{"videoId": "lypE7WLtIPQ"},
{"videoId": "raJ1BEHd5c8"},
{"videoId": "z7beHIXVaZI"},
{"videoId": "I11Z9udn38Y"},
{"videoId": "DIfK28qHRj4"},
{"videoId": "wmIcgq87sjw"},
{"videoId": "h7Xsk-nKDXQ"},
{"videoId": "cRqrgxp4nUw"},
{"videoId": "U4vmwqNqhe4"},
{"videoId": "OtgiEq9-32M"},
{"videoId": "VnUeeDf89f0"},
{"videoId": "y6Pal5X7rjQ"},
{"videoId": "umNmD4DI-cA"},
{"videoId": "SshcLm_nfAw"},
{"videoId": "Tua5n2MdM0c"},
{"videoId": "LqTN9xrLWNA"},
{"videoId": "2z0UjKGFCuQ"},
{"videoId": "I3EA4bFoHYM"},
{"videoId": "ybhZG2KFAE0"},
{"videoId": "wMwsvUi2lrk"},
{"videoId": "cXiOMqyDRrU"},
{"videoId": "dp7IIDoWbUs"},
{"videoId": "N7UoXOpsDiM"},
{"videoId": "TmR9Dw2NBEY"},
{"videoId": "Ksj2sPmpKWU"},
{"videoId": "8kL-ct-v8k8"},
{"videoId": "VGw0fImUG_U"},
{"videoId": "gUwiVRYbeZ0"},
{"videoId": "XKVPbWR8OYg"},
{"videoId": "bzEvYW93MOw"},
{"videoId": "F6Qd1PvWraw"},
{"videoId": "8ceiEpW-i5A"},
{"videoId": "-nLPWGVGuco"},
{"videoId": "MzNzWcnKnpo"},
{"videoId": "STLpI_FiZ6E"},
{"videoId": "0t2wbrlUwgs"},
{"videoId": "TXa7sxmAIMU"},
{"videoId": "HA3rAw0Vgeo"},
{"videoId": "ppEDXSCueP0"},
{"videoId": "3P_q9fOOVfs"},
{"videoId": "Ckpvx57uqAk"},
{"videoId": "ywR31-kE39g"},
{"videoId": "yr7awOb7V4c"},
{"videoId": "AoI7j5QzdAQ"},
{"videoId": "KEokm1OJM04"},
{"videoId": "RotdAaIpcUg"},
{"videoId": "9NymWun0MEE"},
{"videoId": "EHA-9XUIiKY"},
{"videoId": "vxti_1g2bZ8"},
{"videoId": "-5zteKv8XRA"},
{"videoId": "9KZsgt5ENB4"},
{"videoId": "xkPBN4ejgoE"},
{"videoId": "Z_NaYKUR3sM"},
{"videoId": "s037L-7M-9c"},
{"videoId": "PMuavLs6Mn8"},
{"videoId": "oh6SXFovtHk"},
{"videoId": "i0tWWKOJmWI"},
{"videoId": "XcmX4qgy_mk"},
{"videoId": "xAgba7eLcNk"},
{"videoId": "0qfyHbuIIUE"},
{"videoId": "vpWSyAMDR9Y"},
{"videoId": "7JhIMXVC0Dg"},
{"videoId": "LPZMnIm6XiA"},
{"videoId": "5ex49uxBboM"},
{"videoId": "sThAWSOccBk"},
{"videoId": "V3UHcuIyEY0"},
{"videoId": "rayv3eEqLDw"},
{"videoId": "xQmPES_MXv8"},
{"videoId": "EqRoGjovCyQ"},
{"videoId": "FUiA6SXeDO4"},
{"videoId": "t05OnlsrKrY"},
{"videoId": "8tvYgSYLOUs"},
{"videoId": "1WmMaD0UpF8"},
{"videoId": "p9ec-yKMF5M"},
{"videoId": "CS4t4Bhc6RU"},
{"videoId": "0EGjSU3LU6w"},
{"videoId": "K44CM3JnxLQ"},
{"videoId": "ZuJqydGTc4Q"},
{"videoId": "i7IOwKrCQ1I"},
{"videoId": "sinoGp6w4fc"},
{"videoId": "kjA_XhHiTew"},
{"videoId": "-GvY4qZh1gI"},
{"videoId": "NRjaHZ8jkr4"},
{"videoId": "t11ETz0U3ds"},
{"videoId": "Ef0u8pcVkEU"},
{"videoId": "w9nuAluDx1k"},
{"videoId": "JzCgdx0dn4U"},
{"videoId": "imMn5BNmx_Y"},
{"videoId": "wZ_4DYm807Q"},
{"videoId": "kgfszvFC7v0"},
{"videoId": "5kDbfjQAA6Q"},
{"videoId": "emKDkgyKOFk"},
{"videoId": "sGnx8gR3ocs"},
{"videoId": "wJneAJM6noY"},
{"videoId": "E3Wbz8TotmY"},
{"videoId": "uMoSyk0rK9s"},
{"videoId": "00hyr8HKdvA"},
{"videoId": "d7dvX040beg"},
{"videoId": "ERL95-2OQOM"},
{"videoId": "WkWtxrY2TCg"},
{"videoId": "MW8W66zrdzI"},
{"videoId": "a7LjyF3b1WY"},
{"videoId": "TyF4YADHeok"},
{"videoId": "BP1Pz39YnHE"},
{"videoId": "mqlh5a6QJxs"},
{"videoId": "YmYdt7kdQOc"},
{"videoId": "cozoHUiXvzo"},
{"videoId": "TeQxnfR8r9o"},
{"videoId": "_lVtPt5hYso"},
{"videoId": "e4VT_5Hkaak"},
{"videoId": "s2sP8knlNEk"},
{"videoId": "zJNRpoIXOgs"},
{"videoId": "w6GnjgP3-0A"},
{"videoId": "iZ0kjs-oT5s"},
{"videoId": "pZfk1OgDzRs"},
{"videoId": "TOCPDGoLrHk"},
{"videoId": "G4AEHj_febY"},
{"videoId": "j3T8nEkpwE8"},
{"videoId": "AaU_T9-GzBA"},
{"videoId": "6pBB02mTi5g"},
{"videoId": "HkOWHI32MQs"},
{"videoId": "UW_dIYWCMGU"},
{"videoId": "WzstKWsvuDs"},
{"videoId": "hkBtjIB-QUw"},
{"videoId": "p1b4NL3hhSo"},
{"videoId": "H39kcbb98og"},
{"videoId": "VjEQcE13mpY"},
{"videoId": "LOd3HiY64RU"},
{"videoId": "1YVfjjp0614"},
{"videoId": "4SDerJ_RR-k"},
{"videoId": "afIDyd41hwo"},
{"videoId": "6Kot_Qxlnfk"},
{"videoId": "NUixwsjLF-E"},
{"videoId": "hq5Bj432Z08"},
{"videoId": "VUBjSHBWQ48"},
{"videoId": "f-roMOTAREk"},
{"videoId": "GRwFodzKVhs"},
{"videoId": "e74pMR_9VR0"},
{"videoId": "FJIdaT_VpAU"},
{"videoId": "VgWJzmePQkg"},
{"videoId": "Jjfbn9ztMgQ"},
{"videoId": "xVv2YtrdF4E"},
{"videoId": "MM2GQdHy_58"},
{"videoId": "4Mtc2E7fkZ4"},
{"videoId": "6DHn73GM7iw"},
{"videoId": "aTLCguGmNpc"},
{"videoId": "okoFL14zvwA"},
{"videoId": "xCldzg8-6Xk"},
{"videoId": "o7-nJLiMA3I"},
{"videoId": "r_J_pZFOK_g"},
{"videoId": "DlsdGUbznns"},
{"videoId": "KJSVP1vJaas"},
{"videoId": "PPglJItqRM4"},
{"videoId": "e4RYrXzcJ4I"},
{"videoId": "Z_UhVmlgliA"},
{"videoId": "9BPRMn8JSLg"},
{"videoId": "M6U6rPEnEJE"},
{"videoId": "Jmz4Htz-PUQ"},
{"videoId": "JRQJx6mmapc"},
{"videoId": "R3Rd__HDzjk"},
{"videoId": "2FVd-O4Ye40"},
{"videoId": "onDq1YWkE0A"},
{"videoId": "EI0Gkxzgeok"},
{"videoId": "l_t5Rq2dZgY"},
{"videoId": "evkEph1zwzc"},
{"videoId": "ZSgBzfJB9TQ"},
{"videoId": "zJjTZm847bo"},
{"videoId": "4GzxPw6-rLM"},
{"videoId": "bMJcnTNdcVQ"},
{"videoId": "vYgBw0CkNEI"},
{"videoId": "aDUZLsJGbyk"},
{"videoId": "W29X3oKA2u0"},
{"videoId": "i74m5ngkjLg"},
{"videoId": "LeJEnuLQYag"},
{"videoId": "ETEmhpKePUI"},
{"videoId": "ARGcmlvu8Hg"},
{"videoId": "tFTM3-DN1Sc"},
{"videoId": "fUKgd3omso4"},
{"videoId": "7okyZMRs4dA"},
{"videoId": "DvubPMjZnF8"},
{"videoId": "spE7ZWteKqc"},
{"videoId": "Rnz7jnjdxpY"},
{"videoId": "sq_NRP4Ggxk"},
{"videoId": "EkO2QMJEakM"},
{"videoId": "xHiFR6JtVHo"},
{"videoId": "JGpk6H0V5jI"},
{"videoId": "ts687oRlO-0"},
{"videoId": "HrcE3QG8vHA"},
{"videoId": "xKNF5ZKmKrA"},
{"videoId": "JImCeKUgPQo"},
{"videoId": "N0O_NqKle8A"},
{"videoId": "msj7B_MVnYE"},
{"videoId": "r5HWG-mgwq4"},
{"videoId": "AIG5iJjbqTI"},
{"videoId": "5zhFFf2HtOA"},
{"videoId": "VSfQisyLrIg"},
{"videoId": "6mRt4awTMns"},
{"videoId": "qzGOkg5BYQY"},
{"videoId": "HUyvMRqmn8s"},
{"videoId": "SFpbQPp1pZM"},
{"videoId": "V9FyUZfUc4s"},
{"videoId": "Ybt_PWwyj2A"},
{"videoId": "ZlB6n6O9m7w"},
{"videoId": "164y6r9cISM"},
{"videoId": "9CnSE7W18sY"},
{"videoId": "pB8bmykRvos"},
{"videoId": "ZCdY3quNWPs"},
{"videoId": "aDDO1dHTBws"},
{"videoId": "blO3pz5OKSM"},
{"videoId": "O1Lw7VMdbyI"},
{"videoId": "5kk-dP6g_Z4"},
{"videoId": "5WmD4YUNiCI"},
{"videoId": "VTsGRGeBj98"},
{"videoId": "kn9xTzefw4E"},
{"videoId": "L37Le7SwTfQ"},
{"videoId": "rOqPVOjIiEI"},
{"videoId": "NEdg2qptcBI"},
{"videoId": "0FLUiq2b-tI"},
{"videoId": "xj8RsacQBB4"},
{"videoId": "eK9Wf6GVAbg"},
{"videoId": "EYUstXyWUGQ"},
{"videoId": "bypvEIzQYpU"},
{"videoId": "Kdq6Cf8nUYU"},
{"videoId": "3ZMkCb-gHrk"},
{"videoId": "SO5w_FkgkxA"},
{"videoId": "M3sLgLAMz4w"},
{"videoId": "__YLZjpp2dU"},
{"videoId": "Bl8A7QBQllA"},
{"videoId": "t43JXiw-Z3k"},
{"videoId": "ZJJ7Eud7AoQ"},
{"videoId": "oFo0QJC4EZY"},
{"videoId": "FMkPFMQn5Xg"},
{"videoId": "dr9dsRkLbhE"},
{"videoId": "eLaKz9dDWi8"},
{"videoId": "Vw9Up-0ITyY"},
{"videoId": "NbzmzbDVPpc"},
{"videoId": "Nk2JfjE3g88"},
{"videoId": "MI9HnKN4xD0"},
{"videoId": "GH4bCErg_SU"},
{"videoId": "vlkhbadAF_E"},
{"videoId": "-GFERmC2K40"},
{"videoId": "MzUjjwBtrdc"},
{"videoId": "vzW3gh9X9LE"},
{"videoId": "Q34zsmABc0A"},
{"videoId": "iKkwrnxMH40"},
{"videoId": "KRuqjGJ5iO0"},
{"videoId": "x2VAsdGtTYc"},
{"videoId": "wgMe0yDC4es"},
{"videoId": "a8LtMnliYhA"},
{"videoId": "LGmHE8wxreY"},
{"videoId": "pWzAxCdCn9s"},
{"videoId": "kFO9kgqHkpI"},
{"videoId": "dr-3kSPzfrE"},
{"videoId": "GC2u-fjVWFc"},
{"videoId": "NimuwWuGZxA"},
{"videoId": "KL9UXI6HcWc"},
{"videoId": "vFz38wpnNJQ"},
{"videoId": "ltM6Taxdp_4"},
{"videoId": "ZpgbGF3HV9Y"},
{"videoId": "m87q-f7JDu4"},
{"videoId": "ALd_GP6e0EU"},
{"videoId": "Ap52FFrtvUY"},
{"videoId": "eVpt2wy-Bqw"},
{"videoId": "sVILpNMcN5Q"},
{"videoId": "MT-ah5zhv2Q"},
{"videoId": "mLMY5E3Ooy4"},
{"videoId": "KaBfPRA5Taw"},
{"videoId": "5Doyl4T2wDI"},
{"videoId": "_iu6aKhZAYg"},
{"videoId": "mSJL9-DyMqM"},
{"videoId": "u9FkY0RaRxU"},
{"videoId": "96GXqWaQcEE"},
{"videoId": "6Q8RCdzAtD8"},
{"videoId": "BblxnShCd38"},
{"videoId": "qkcz69J57mw"},
{"videoId": "mcPp_fx4wuM"},
{"videoId": "BjNjFkMijl8"},
{"videoId": "91K1yYCmvbs"},
{"videoId": "RgzNRJrqfJA"},
{"videoId": "WG4bJRCyyQw"},
{"videoId": "UAuHxpACzZU"},
{"videoId": "TurRK0wuBUs"},
{"videoId": "ajI-jU8fOwo"},
{"videoId": "5Du-tGMEg3E"},
{"videoId": "8l1IZIjgcxU"},
{"videoId": "x8N0bL_E5HM"},
{"videoId": "1swiuQgrLXk"},
{"videoId": "mje6KxlXPGc"},
{"videoId": "SVq7lF1B8NM"},
{"videoId": "RsJePrU0Rmk"},
{"videoId": "CVbjmQMEJb8"},
{"videoId": "0Wy3jPrt48w"},
{"videoId": "SedLu-DsNmU"},
{"videoId": "Uf75dobaqvY"},
{"videoId": "gAxWOvh5s5I"},
{"videoId": "tZjdV0y1UM0"},
{"videoId": "9BOa7kQYIWM"},
{"videoId": "ftl-6C5zaNo"},
{"videoId": "T62PxmmFDGE"},
{"videoId": "jEhPg0Cup5w"},
{"videoId": "nVtn3fZBq3o"},
{"videoId": "MNju4fINH28"},
{"videoId": "QzcPwfPocUU"},
{"videoId": "xGQZTt5DFx4"},
{"videoId": "oreZ3aRmC4c"},
{"videoId": "MCGeUHsQFHk"},
{"videoId": "FnhMurzQftU"},
{"videoId": "nKkbi1d4y4M"},
{"videoId": "cauj-xpxH7I"},
{"videoId": "Jst8d1SbulU"},
{"videoId": "cGoAJ8YZTes"},
{"videoId": "tr9nhKPyCv4"},
{"videoId": "gzRAY9N6y6I"},
{"videoId": "toP-dd3SMFo"},
{"videoId": "ngbBGonBj_w"},
{"videoId": "WvfIgz18dqE"},
{"videoId": "T5wxKR5_fq8"},
{"videoId": "VaPUB3waGdc"},
{"videoId": "mlsb9QwJ2vg"},
{"videoId": "WvlSECcw_60"},
{"videoId": "8FM3LNpaUD8"},
{"videoId": "EB2527NfWNI"},
{"videoId": "gYPCRaL2IsI"},
{"videoId": "-Gy4KR7YTiA"},
{"videoId": "M6zWfMGRAjs"},
{"videoId": "uGA9LyR3YrI"},
{"videoId": "DFiWd3qvSdA"},
{"videoId": "uJG2_NCFMVU"},
{"videoId": "D7Mj5LDIqt8"},
{"videoId": "QPbyxkKgjIw"},
{"videoId": "osf5XH_ZP_I"},
{"videoId": "NGhBuzJXWmI"},
{"videoId": "1lD9nmO3pY8"},
{"videoId": "iK8aXekmhX8"},
{"videoId": "S4MJ8uKAO4o"},
{"videoId": "HsnsRi5BG5s"},
{"videoId": "De9jLRSh5eI"},
{"videoId": "fy2mvPaf1AQ"},
{"videoId": "PclJPODGi24"},
{"videoId": "LDl0LhGL53A"},
{"videoId": "em0z5pL12JA"},
{"videoId": "W3MsTFf1NFw"},
{"videoId": "pt-xzQu1N8o"},
{"videoId": "et3dgunKOps"},
{"videoId": "2mxGxTUicRk"},
{"videoId": "d_lCL0RVI-Q"},
{"videoId": "B4S-mCmxIzc"},
{"videoId": "JhFT-P8Avf0"},
{"videoId": "auB-Py_GVnw"},
{"videoId": "DKR7iZEmKac"},
{"videoId": "-VEEycWfg_8"},
{"videoId": "edK4d40ifCE"},
{"videoId": "u32vU3OAzEQ"},
{"videoId": "UBkgcuSni5o"},
{"videoId": "6Jpnm6nM3Mc"},
{"videoId": "bLGqW4l1FTI"},
{"videoId": "q10l_lIUSwc"},
{"videoId": "OnAoGk66dnU"},
{"videoId": "rueIxbkQx40"},
{"videoId": "0YWRPWDqzVg"},
{"videoId": "8-3bW2v-VRQ"},
{"videoId": "ixvhR1H6rVg"},
{"videoId": "tuAEFkf_xng"},
{"videoId": "oN6jy0sZxDE"},
{"videoId": "E3a2tB95VVA"},
{"videoId": "873Pb3u-hvg"},
{"videoId": "St9C-Pcf01A"},
{"videoId": "D5BwOXfMqkI"},
{"videoId": "Dri_A6dasIE"},
{"videoId": "C1cZDAFPFUA"},
{"videoId": "ShBZ94O39sQ"},
{"videoId": "-pK5rZyAufc"},
{"videoId": "8DL2pmxtWk0"},
{"videoId": "S905Z7D-FHw"},
{"videoId": "bwXvvIhRh18"},
{"videoId": "AxsTvrZBkaI"},
{"videoId": "o4ILbBiFlgE"},
{"videoId": "bUSMEhgX75A"},
{"videoId": "uycG1E5luj8"},
{"videoId": "CKV5JH_1jnI"},
{"videoId": "7G4GOTxFbgs"},
{"videoId": "00l3lzVHdIk"},
{"videoId": "F9_OpfDMlpc"},
{"videoId": "QKYI_mTXuPw"},
{"videoId": "_VfUJk7EIzA"},
{"videoId": "NI015PuhTLQ"},
{"videoId": "TQuttWsUD0c"},
{"videoId": "66-caIlq6QU"},
{"videoId": "XUXX6ADqpmQ"},
{"videoId": "x0JCP4BqoVQ"},
{"videoId": "UqZYW3-MgnE"},
{"videoId": "6bRfJ94xgjU"},
{"videoId": "tzje6ufjvzs"},
{"videoId": "41IrDmjPmKE"},
{"videoId": "AfMdRRN3g2U"},
{"videoId": "cFoq9lx4LDk"},
{"videoId": "Hh1hHVzzz9Y"},
{"videoId": "td2DRVNImdw"},
{"videoId": "HKe-eRj4rc0"},
{"videoId": "PLSwlEq2wPU"},
{"videoId": "sHSnMU6fqjo"},
{"videoId": "3DGCWWG0dig"},
{"videoId": "kAq3NabapOg"},
{"videoId": "CEApYNyBwz0"},
{"videoId": "tN7cNdmsoWE"},
{"videoId": "1y5X5DPJ_Ww"},
{"videoId": "siUUJF_QljI"},
{"videoId": "4oON0ju_cxw"},
{"videoId": "7D9p9-Vno-I"},
{"videoId": "LyPmAYh_8Vw"},
{"videoId": "zw4NO0ktSb0"},
{"videoId": "gIFi3R0XfT4"},
{"videoId": "u4DIUKXVTUw"},
{"videoId": "r0LdUlGewLQ"},
{"videoId": "HwERJpKxHpI"},
{"videoId": "jQpo-LGfaDQ"},
{"videoId": "g_NdLabI0Ts"},
{"videoId": "F-6hfAUoFdM"},
{"videoId": "C4IZn0VWmw4"},
{"videoId": "w-tmsiWCm1s"},
{"videoId": "ak0ckZmCd-k"},
{"videoId": "vaZtmPz29HU"},
{"videoId": "_qAkHvXhNy0"},
{"videoId": "HFl1T2e1F3Y"},
{"videoId": "GhB1HxIUUaQ"},
{"videoId": "zdAl8KirfWg"},
{"videoId": "SDsJeS2y80A"},
{"videoId": "M6KfcUEYxc8"},
{"videoId": "CU8W3HUiSyo"},
{"videoId": "v5KR2FJk0ZA"},
{"videoId": "-arVRNnHhaA"},
{"videoId": "Cq-XK608tQo"},
{"videoId": "jCr-pH9E3TE"},
{"videoId": "IBODEPsEYF0"},
{"videoId": "TaM_45VFSjc"},
{"videoId": "5riPu9as9-4"},
{"videoId": "w2Bkh4Ba8Ak"},
{"videoId": "i4zy_DkQv74"},
{"videoId": "oDrYpVr7c9k"},
{"videoId": "xHy-lYwac2U"},
{"videoId": "CScLTdo5Zpg"},
{"videoId": "eC5Tm9N5M4M"},
{"videoId": "2MQDlNCuLaw"},
{"videoId": "YXWKvvciBC8"},
{"videoId": "S6F7WjgokyE"},
{"videoId": "27Lpb1L3Vrk"},
{"videoId": "gYyQK-6zUzM"},
{"videoId": "9WD0OPfawNo"},
{"videoId": "sPOg87oS8LQ"},
{"videoId": "xqgicOW_3g0"},
{"videoId": "RSUyXreM2pY"},
{"videoId": "RqQ6WQUSvK4"},
{"videoId": "VsdnRUCt8p4"},
{"videoId": "NIBpVuYhdew"},
{"videoId": "dkeCePrhJ70"},
{"videoId": "mUkTbNQW798"},
{"videoId": "tli25GoI8yg"},
{"videoId": "jnYzS1jNWVo"},
{"videoId": "r9_bS5wqTrM"},
{"videoId": "TVvFnCtquRs"},
{"videoId": "QQQNWgo3q-U"},
{"videoId": "KFeSC7je_IA"},
{"videoId": "SP-9s_g8bAc"},
{"videoId": "m16236A3dmM"},
{"videoId": "0WK9VGsH1ps"},
{"videoId": "SH5xYg5nkhw"},
{"videoId": "tGJXhsxPqjg"},
{"videoId": "QgGuNWOvx5A"},
{"videoId": "-eHrWnSIDK8"},
{"videoId": "pvZxrDyUh58"},
{"videoId": "kGxuTDqIccI"},
{"videoId": "ne9k8eYsZls"},
{"videoId": "T6HZO03dI48"},
{"videoId": "AEOG2XKekKk"},
{"videoId": "pWxyEpnq7rY"},
{"videoId": "G74-Iy5xMtw"},
{"videoId": "wcgdv1t0-wQ"},
{"videoId": "pkZsbnY9Bu0"},
{"videoId": "RRhYbCva8QI"},
{"videoId": "7AJjIPS12MI"},
{"videoId": "RuCAcWIpyOQ"},
{"videoId": "OxMh3m1pAlU"},
{"videoId": "F7mo8ryILB4"},
{"videoId": "OX4Vd76qug8"},
{"videoId": "cz6-c2jMNZQ"},
{"videoId": "LoUnM_t1svk"},
{"videoId": "d9HuUPsSpWs"},
{"videoId": "Q2iTCT_qEAs"},
{"videoId": "hhDIkirEvMY"},
{"videoId": "ze8ORfzIjKg"},
{"videoId": "VtfAzRomhfg"},
{"videoId": "-ZhdMTkHFX4"},
{"videoId": "e9kvH4pzL34"},
{"videoId": "yTV0UZFFDsI"},
{"videoId": "owvraCSMRJY"},
{"videoId": "vG88Uo0mtPM"},
{"videoId": "1N2loINKkTA"},
{"videoId": "uJp_c-7O50k"},
{"videoId": "M2MTsquR7aw"},
{"videoId": "e-wc5N__zsI"},
{"videoId": "PY1QlvMt4O0"},
{"videoId": "6GbtR4Rq914"},
{"videoId": "aFLB_vvMVGs"},
{"videoId": "GVvgF16QW1I"},
{"videoId": "3GfxKyi7JpQ"},
{"videoId": "sMvrcxv9bXw"},
{"videoId": "dpnh0Vqafn8"},
{"videoId": "B6NijujBLv4"},
{"videoId": "TuH18qUjtCU"},
{"videoId": "SRrfzTtQtas"},
{"videoId": "dCobQem-Ulk"},
{"videoId": "6rPJmq0Aj9c"},
{"videoId": "3fpuL6ymf18"},
{"videoId": "unNEj8ts8as"},
{"videoId": "TNW1XpHEYnE"},
{"videoId": "5t_0y1WH4u0"},
{"videoId": "hgOnvV9sJ6g"},
{"videoId": "wuLXgDP8zqM"},
{"videoId": "MLuI7dlPI4U"},
{"videoId": "bYU17GVMA_g"},
{"videoId": "42wtrVmjPM4"},
{"videoId": "1cugS8m6bYE"},
{"videoId": "kAwP8unYYwA"},
{"videoId": "gYG7gU15tQ4"},
{"videoId": "f3zCvY40J8Q"},
{"videoId": "eQAFQgqNcC0"},
{"videoId": "GMnslEn5TdM"},
{"videoId": "eI_LjETc_Ak"},
{"videoId": "ZMCIT5IgOZk"},
{"videoId": "XJwgV85h4XY"},
{"videoId": "pAB6qRgRMAU"},
{"videoId": "7FWixIb8Msc"},
{"videoId": "f91ENwfnlhQ"},
{"videoId": "SIoftXmL4Rk"},
{"videoId": "gBC08b3KPLg"},
{"videoId": "4Q8aXpAUZ0A"},
{"videoId": "4wIwpbl2fh8"},
{"videoId": "zom51aL9SiQ"},
{"videoId": "5cj99oPqz0Q"},
{"videoId": "sSlSOY6d6Yo"},
{"videoId": "JLioY-LjDSs"},
{"videoId": "C8-J_LnTKRI"},
{"videoId": "_FsHz0N5Wgo"},
{"videoId": "acqFGtRNkYg"},
{"videoId": "USRNh_WYMqU"},
{"videoId": "wVy1DN-tmK8"},
{"videoId": "pTEb8c0DphQ"},
{"videoId": "YdjvW2j6A-4"},
{"videoId": "eS7pEAI_yNM"},
{"videoId": "vvDvis2O63U"},
{"videoId": "kqUjH5eIiBg"},
{"videoId": "Wir9YUnSnI4"},
{"videoId": "lhSV2HfX__E"},
{"videoId": "X3ZXn0Kk_ts"},
{"videoId": "LmkRNbWDAsU"},
{"videoId": "MacwRaaYOyg"},
{"videoId": "wQ-5wFwQD8s"},
{"videoId": "4z4a249vqkg"},
{"videoId": "t3O7hT9JePw"},
{"videoId": "jYW1ym4q9Z8"},
{"videoId": "8Ed9E42p1k4"},
{"videoId": "OKQygBOhEiE"},
{"videoId": "FzeBGs9UYTo"},
{"videoId": "PP1Kwes8hLk"},
{"videoId": "5wcqiGVw3F4"},
{"videoId": "Mr8A-xTv9Go"},
{"videoId": "2fsUjWcvuCw"},
{"videoId": "VGsbhyLrZAM"},
{"videoId": "W_wCNvAg2Rs"},
{"videoId": "pXCIlLIw3pA"},
{"videoId": "zhjpfZPDIZM"},
{"videoId": "qYi57SPJ_eU"},
{"videoId": "pdR8239WZTc"},
{"videoId": "XPyHQsintl0"},
{"videoId": "q1vCCqW67tc"},
{"videoId": "-4SbRytOA6M"},
{"videoId": "88uwFxRr6lc"},
{"videoId": "OHwpduJWdx0"},
{"videoId": "fC8o8yQrBOc"},
{"videoId": "nKl1xxLrPLA"},
{"videoId": "EJOdKuG2K4g"},
{"videoId": "9VdYiaRg0Gk"},
{"videoId": "769ujjPnGV0"},
{"videoId": "AvGg0lHwLEU"},
{"videoId": "fXT-rWOfuiY"},
{"videoId": "3zsbZXQ7GqI"},
{"videoId": "cC84bdhktbg"},
{"videoId": "KNsueLz4KtY"},
{"videoId": "EOswWepObDw"},
{"videoId": "X3Wt87R2eQA"},
{"videoId": "oUZFL7Hewsw"},
{"videoId": "sH6W5sjEW3Q"},
{"videoId": "DGdxMy59VxU"},
{"videoId": "CEQjIces9ek"},
{"videoId": "rCXV1eh9VCI"},
{"videoId": "hJZKPieR-lc"},
{"videoId": "9RM9KI1jAp8"},
{"videoId": "RTyZPOBVYY4"},
{"videoId": "l83we0qLL2Y"},
{"videoId": "IkAOo4RNPB4"},
{"videoId": "icFCUIvFs0Q"},
{"videoId": "X7UqZELD3s8"},
{"videoId": "SVHqrNkDYac"},
{"videoId": "lmHW0XaPCk8"},
{"videoId": "-UUFF_U8V2w"},
{"videoId": "zU4NRFi58uU"},
{"videoId": "OPQdv_-_sD8"},
{"videoId": "MJ4wLM5qRj0"},
{"videoId": "NRRkAIodS44"},
{"videoId": "uniP4VL3m6w"},
{"videoId": "yRCYztxZl7M"},
{"videoId": "Kv-dqb55yaE"},
{"videoId": "X2McVSV2_Rs"},
{"videoId": "O_dPBNX4th0"},
{"videoId": "LpUBBucNHYw"},
{"videoId": "iUI3EKuBCJ0"},
{"videoId": "W2prOMrfv-c"},
{"videoId": "cHNwtWfYl-c"},
{"videoId": "VwFJZ_O8dcQ"},
{"videoId": "il_o4jZuVok"},
{"videoId": "XYqI1qb8jlE"},
{"videoId": "ATZJi63SjDk"},
{"videoId": "vMXSnQf8S0E"},
{"videoId": "cbTV35mLI5A"},
{"videoId": "Mh4DdlTB5UM"},
{"videoId": "gp8FKIR8anY"},
{"videoId": "smEwuJUOsEo"},
{"videoId": "Hrl_9FbLt_U"},
{"videoId": "gCC1sGR-lss"},
{"videoId": "ctBm2_cq22A"},
{"videoId": "f3ajfzmYBcs"},
{"videoId": "CN8koj4mnRs"},
{"videoId": "JNDDXRcW8wc"},
{"videoId": "PJXwBNpMxgs"},
{"videoId": "ywKraM3SgBg"},
{"videoId": "Xd-GBn_pxDQ"},
{"videoId": "8Tfol5JuzNs"},
{"videoId": "yglpYwRcgLQ"},
{"videoId": "rm5h8tUxDoM"},
{"videoId": "1Tk2uEFyY0U"},
{"videoId": "5c6xZIzx5UQ"},
{"videoId": "7USd1XXjlRc"},
{"videoId": "CD5QhOgoYm8"},
{"videoId": "TYEQtb-BaZw"},
{"videoId": "_m8GuCcVE1Q"},
{"videoId": "mDInPRjobUw"},
{"videoId": "TX2An9mJ3G0"},
{"videoId": "wRwsB6456co"},
{"videoId": "-wQRQmB1X0k"},
{"videoId": "iRahcC3-pso"},
{"videoId": "q-SwyfmxzV8"},
{"videoId": "2bDuOKvSePY"},
{"videoId": "obl4GzsWKQ0"},
{"videoId": "iDYLJNL3Si0"},
{"videoId": "HyiNGQU4JIY"},
{"videoId": "A2ODoqP2P5U"},
{"videoId": "5Q1FbCIoHmw"},
{"videoId": "-Mw2GFUm9vE"},
{"videoId": "8VaebdK7pi0"},
{"videoId": "64tJpGHHJSo"},
{"videoId": "uFtjqJoFKVs"},
{"videoId": "LqYr6r_MEDo"},
{"videoId": "trNO5Imf1Q8"},
{"videoId": "Ivb6JMY8W9g"},
{"videoId": "5fPJR5KzKGA"},
{"videoId": "heUAr4P_PNM"},
{"videoId": "EpsmB5dQsaU"},
{"videoId": "Mzi_HjgOJNE"},
{"videoId": "4mQaa0GWRvI"},
{"videoId": "NU6zooope8w"},
{"videoId": "or1PoW-xHt0"},
{"videoId": "h9IXmgYOVjk"},
{"videoId": "2jATdirfsQ0"},
{"videoId": "uHamWObldWk"},
{"videoId": "XZF8f4cM3hQ"},
{"videoId": "6-wUDKaKGQs"},
{"videoId": "8toNKfsFW3I"},
{"videoId": "FEDYPWdT8cE"},
{"videoId": "xTzTl1O18QY"},
{"videoId": "TFAM2P1TX2I"},
{"videoId": "r5ga2a_b9VU"},
{"videoId": "LD6aJjZcrpQ"},
{"videoId": "meNnWudM2XY"},
{"videoId": "9wvcn_xHvdM"},
{"videoId": "mxQqCAbg1ws"},
{"videoId": "UpKTnzYEsrM"},
{"videoId": "HNmmKCDxn7w"},
{"videoId": "A-Z6MOfio3s"},
{"videoId": "RnbnUu9n3RU"},
{"videoId": "1VASEMf2kIg"},
{"videoId": "ejMoRpv4ATM"},
{"videoId": "-w6CoQLfBgc"},
{"videoId": "Ho45GIKqNEk"},
{"videoId": "y3Gt7AMiJVc"},
{"videoId": "INZ8XsYAazY"},
{"videoId": "MJYOhkJNtXo"},
{"videoId": "auv4y0k3Y_s"},
{"videoId": "IO7KfOUQYYU"},
{"videoId": "tdMrqpvfACc"},
{"videoId": "cNXW9pZpozc"},
{"videoId": "3x_z27C2OOQ"},
{"videoId": "nJlT3w36RvA"},
{"videoId": "FajFDx3bO9I"},
{"videoId": "ysd51XPtnyI"},
{"videoId": "6eT3PnK9Goo"},
{"videoId": "ZbF-a0ZF57k"},
{"videoId": "OENcBv1jN7o"},
{"videoId": "Br6qSFv88p0"},
{"videoId": "v_ZQmnkBcjM"},
{"videoId": "1t8ZNTL9lE0"},
{"videoId": "JK0fXjNeSak"},
{"videoId": "cll2ecusKR4"},
{"videoId": "NPOIe7To10o"},
{"videoId": "xiS0NCwPS3M"},
{"videoId": "6QeUTFgdM7Y"},
{"videoId": "YPC8PJojchk"},
{"videoId": "B-jAs3yn7Jw"},
{"videoId": "XVgqEUgazb8"},
{"videoId": "2FV_M6BHXgo"},
{"videoId": "GpTL8pif-Tc"},
{"videoId": "Gm_a0aSYNXA"},
{"videoId": "KuiuKEudODk"},
{"videoId": "9MRP_SyeAAw"},
{"videoId": "fTm6oimK6zY"},
{"videoId": "xVGxb6v3VyU"},
{"videoId": "qBOJ4DrWBUo"},
{"videoId": "4vvweUE54pk"},
{"videoId": "GOjrylGfjdA"},
{"videoId": "95PL4kUDFbA"},
{"videoId": "l3-qptTkWX8"},
{"videoId": "T6fWvBjZhAs"},
{"videoId": "oxcEb6EZPKQ"},
{"videoId": "gfyd3hSTuB4"},
{"videoId": "yvs02fwaUJo"},
{"videoId": "CjR8P_U4jyo"},
{"videoId": "w8GiI0b76JY"},
{"videoId": "zcr_KHkIt28"},
{"videoId": "beajKodAaqA"},
{"videoId": "nymbNxlZxus"},
{"videoId": "shKckugsdlY"},
{"videoId": "h-y4uEKliaQ"},
{"videoId": "tf09h3Gycso"},
{"videoId": "qQGozG6SW08"},
{"videoId": "gCjmOz221fg"},
{"videoId": "lchPn0r6wlM"},
{"videoId": "og-DMo0XNEA"},
{"videoId": "_gdtsY8BJaQ"},
{"videoId": "WwZo-RIbTfI"},
{"videoId": "nkhj3PBHJdw"},
{"videoId": "g3jveL1JNaw"},
{"videoId": "_Bk9DkJcH3s"},
{"videoId": "nM-bZduB4aw"},
{"videoId": "U175vl0hkWY"},
{"videoId": "Jv_WYLb_WMY"},
{"videoId": "10PXs5uNizg"},
{"videoId": "w9IgSXA0VwY"},
{"videoId": "xcryZBodRVw"},
{"videoId": "SRpMapyw6Aw"},
{"videoId": "Kfst599pkQw"},
{"videoId": "tAc8jYkvnfc"},
{"videoId": "Tl2isdL5r2w"},
{"videoId": "3_hAGPtOP_Q"},
{"videoId": "roiSQFuH-CE"},
{"videoId": "EoycZCjhYGE"},
{"videoId": "Zbp-J1mjnn4"},
{"videoId": "V3h6ygGjedo"},
{"videoId": "JuW3pAaTx20"},
{"videoId": "e7vsPqNmlFI"},
{"videoId": "sqt7YLtF9PI"},
{"videoId": "LGf0AAoG6sU"},
{"videoId": "K8860FZI7Nc"},
{"videoId": "6Y3WsiFW020"},
{"videoId": "od4tMllZEXw"},
{"videoId": "MnyPmiAonVs"},
{"videoId": "NrVEnYlhgT0"},
{"videoId": "Kxp9D34c3_Y"},
{"videoId": "z9r9nT8_ND8"},
{"videoId": "kL3hLuFB6zw"},
{"videoId": "Z1Fm0wbcLKI"},
{"videoId": "6KBA1MVrvI8"},
{"videoId": "F1uDfgq4Rp4"},
{"videoId": "iTfX7vlO3Ro"},
{"videoId": "up_bNA9wqrM"},
{"videoId": "p6_yoVrnR8A"},
{"videoId": "YjdSs-yJdpk"},
{"videoId": "mN9MB4PEv7E"},
{"videoId": "4B5uUzJHjSM"},
{"videoId": "SmF1DH_D7rU"},
{"videoId": "e90z2gIkFeA"},
{"videoId": "R-XYZZmIaXE"},
{"videoId": "ILe91UyT-HQ"},
{"videoId": "plr_BDXLG5s"},
{"videoId": "g8RWwDG-mc8"},
{"videoId": "PooQvoG-a5c"},
{"videoId": "fnu88Dtv9K4"},
{"videoId": "ED6SjplkRbY"},
{"videoId": "EXmGDT24wuM"},
{"videoId": "9hgfhYfwBsQ"},
{"videoId": "OPfGS0-6ALA"},
{"videoId": "kfCGzYnmh2c"},
{"videoId": "87jQG3FDpYw"},
{"videoId": "6xQ2dpjFZok"},
{"videoId": "fXnIZXpbpu8"},
{"videoId": "tKHATgLyMyM"},
{"videoId": "YIA_E_3A3CQ"},
{"videoId": "8c_JAKbzI70"},
{"videoId": "yzuFpfhD0L4"},
{"videoId": "dMSDqdC_6es"},
{"videoId": "fL-KoQD3pLA"},
{"videoId": "yuS4TGRNeC0"},
{"videoId": "cvhQaH7zAng"},
{"videoId": "bED5d2j52CU"},
{"videoId": "CDLB3TyMjkU"},
{"videoId": "oN3BggAaCWw"},
{"videoId": "iAe6tRT5z5M"},
{"videoId": "CF2Z5eLcUag"},
{"videoId": "FHBTfPe7nio"},
{"videoId": "OT3m5umBg7M"},
{"videoId": "BEFXG19sK3w"},
{"videoId": "atnSVvBaJl0"},
{"videoId": "Adyb5dcCHHI"},
{"videoId": "8sp5SDFa7ic"},
{"videoId": "39xh5meMAr4"},
{"videoId": "fW7H3LbytQQ"},
{"videoId": "hp7hLOVNv08"},
{"videoId": "Lhmq5CQ8tWw"},
{"videoId": "FoW5qKwpY4w"},
{"videoId": "VCVl-HSi9FQ"},
{"videoId": "n5qjQR2sirE"},
{"videoId": "jRjbU85USWY"},
{"videoId": "5IjSA4WhyOk"},
{"videoId": "t059zEY5M_k"},
{"videoId": "wJumaWoWi6w"},
{"videoId": "CZvYvUGLNMg"},
{"videoId": "Ek4zmQEPkS0"},
{"videoId": "rAnciTaSGP4"},
{"videoId": "0X-_XeLZqQQ"},
{"videoId": "xy-pP0YS0-4"},
{"videoId": "-YTjz3wD1os"},
{"videoId": "5Qxi8mMOD-g"},
{"videoId": "5LXM5l7t7iQ"},
{"videoId": "AWADuuDrnIg"},
{"videoId": "4Q4BjeA1S_o"},
{"videoId": "gTIfhqqyLj4"},
{"videoId": "2dM_YcsPCNU"},
{"videoId": "ioCb_LJHjPs"},
{"videoId": "ZG0Xq4Of3hM"},
{"videoId": "O92a4q3O7Zk"},
{"videoId": "gZtbf6OVnwg"},
{"videoId": "QDkJicof6PI"},
{"videoId": "M_mM4rh5uUc"},
{"videoId": "3mPOKCRoCvw"},
{"videoId": "6xDdl3PCvn4"},
{"videoId": "BYQOS00NqJU"},
{"videoId": "cAZ1F1axujU"},
{"videoId": "N-whp7RHwIs"},
{"videoId": "RFh4_wy72cU"},
{"videoId": "o9OBDWensWM"},
{"videoId": "ldojh4xlZi4"},
{"videoId": "UHlkrcZyZ1M"},
{"videoId": "rKMP8Gvj9Vk"},
{"videoId": "gfhhoZ4BJv4"},
{"videoId": "Ixvdbe6gQaM"},
{"videoId": "PnNU_OP4qaw"},
{"videoId": "azMCEpEGIKA"},
{"videoId": "3aCJrkWz494"},
{"videoId": "smRP9t6M_oI"},
{"videoId": "XHIsj7yDcYk"},
{"videoId": "wtZNDB5oBco"},
{"videoId": "_xXy5gR9oNE"},
{"videoId": "CQ9_Y8UdJxc"},
{"videoId": "fTpUs-mUu7g"},
{"videoId": "BdbHspGW15U"},
{"videoId": "IPTOjpZEZro"},
{"videoId": "JeqtT7s31aA"},
{"videoId": "UXj7mPFdhXE"},
{"videoId": "q86tEygL4QM"},
{"videoId": "cdnLxsKRZ3U"},
{"videoId": "8UeE-46nqjo"},
{"videoId": "CT47RkjqMKQ"},
{"videoId": "DzB0EIR1kRo"},
{"videoId": "XV8i4zDNAWY"},
{"videoId": "ajs9zAT0WW4"},
{"videoId": "zkp9P7pGz94"},
{"videoId": "syozlhMyZeQ"},
{"videoId": "JctkxlLW18g"},
{"videoId": "jywhkbCaR10"},
{"videoId": "YSd-_KdpH8Y"},
{"videoId": "xHypiQpL2yQ"},
{"videoId": "vl2mFHZeWO0"},
{"videoId": "pObPqffympM"},
{"videoId": "TmLH-_WLffg"},
{"videoId": "tU_XKbXLfPo"},
{"videoId": "-hxsTEBDk9Q"},
{"videoId": "KOGXhc5mJV4"},
{"videoId": "0VMzJ3J6R1A"},
{"videoId": "fuuQQOa_xyw"},
{"videoId": "FKaFizfF-qI"},
{"videoId": "ez4QCAcWo0Y"},
{"videoId": "AlF1pBVM48E"},
{"videoId": "mF8Mq0iRBMA"},
{"videoId": "uwlMWji09QI"},
{"videoId": "LAJbVKfC6lY"},
{"videoId": "DRoPXUa0JZs"},
{"videoId": "LC0GYkdjG1w"},
{"videoId": "fk1BTcmjVFU"},
{"videoId": "pGTJATIuHM0"},
{"videoId": "dAtBP1TR1RE"},
{"videoId": "kDalvXoa-KU"},
{"videoId": "95_nAtAEITA"},
{"videoId": "kJS1LgUTEms"},
{"videoId": "RxoFjb0-xKA"},
{"videoId": "cthgUMH_SEM"},
{"videoId": "diEXsmZ64G0"},
{"videoId": "yKVM8R3oDtA"},
{"videoId": "i0QCwNYH99k"},
{"videoId": "rsIqY_3HTxw"},
{"videoId": "n4OTysjgzFY"},
{"videoId": "AAjPp9EF604"},
{"videoId": "EwUAimkmCYk"},
{"videoId": "ZcBIODHBcBU"},
{"videoId": "d9xfXAN6T2I"},
{"videoId": "4gCUyWxuuds"},
{"videoId": "KpgIOxmZHAs"},
{"videoId": "B8SOGJpcXUM"},
{"videoId": "ifKvqndUkmw"},
{"videoId": "iQDUMnpLbIY"},
{"videoId": "1XF24TYzx8A"},
{"videoId": "OIYpW27hzSc"},
{"videoId": "sej3WAlN6uU"},
{"videoId": "Loih-pjqxnc"},
{"videoId": "ZIKLGUJV7jo"},
{"videoId": "7ueQDORQEBI"},
{"videoId": "W9Q9yKxfGMY"},
{"videoId": "Lx2K0Mm9CT0"},
{"videoId": "Aw8EPAlKQLQ"},
{"videoId": "CGgkDv1QKtw"},
{"videoId": "O0Dki4uwMoU"},
{"videoId": "_-4p0t_cCcw"},
{"videoId": "HoG1NdWYSjk"},
{"videoId": "9VUZlO7-K78"},
{"videoId": "jCLwtBx-Ot8"},
{"videoId": "O7A1NIcAlMA"},
{"videoId": "IyZ4wmRY3W8"},
{"videoId": "Ja5gtCpLPLk"},
{"videoId": "TNGbC8II07E"},
{"videoId": "Gd9HQQcCisI"},
{"videoId": "BJwSpOBkxDE"},
{"videoId": "9fSQ2ENY72Y"},
{"videoId": "cU-yLHhXxn8"},
{"videoId": "1HdpBIxvVLE"},
{"videoId": "a7UI-CGGPoA"},
{"videoId": "-3WTZ9RfAcI"},
{"videoId": "0NtJ4-0Soz0"},
{"videoId": "WmWTPZxcOyA"},
{"videoId": "thP4ZY4ceXE"},
{"videoId": "8ItGSIrP2bs"},
{"videoId": "eUwX4wuT0Ec"},
{"videoId": "RDYhAMBsUjk"},
{"videoId": "f1S6ej3ZpCA"},
{"videoId": "8aPn5pJ1wg4"},
{"videoId": "LYIhsxFqy74"},
{"videoId": "SiPfliKi-Z8"},
{"videoId": "gagtW_mjRvA"},
{"videoId": "YSgzuAdTwnY"},
{"videoId": "3PZ0ip8q19k"},
{"videoId": "AYDHqEJjt1o"},
{"videoId": "_eTrjOf2-Z0"},
{"videoId": "y7M64iPxfz4"},
{"videoId": "puGIqKD8NSE"},
{"videoId": "xdqQs1_9uhc"},
{"videoId": "-z7SGoKAV8Q"},
{"videoId": "lqWkCUFz1OE"},
{"videoId": "zMRIElL7gvo"},
{"videoId": "x5hpLz-R50I"},
{"videoId": "ggnpqoC7U9Y"},
{"videoId": "ex0cSpjMDQs"},
{"videoId": "OKn0bl82rwc"},
{"videoId": "9DzphLunCko"},
{"videoId": "Uy7jsPnTFd4"},
{"videoId": "eTlbs6-Z4Qk"},
{"videoId": "Y1CMa234ykU"},
{"videoId": "uzD5Lk5buVY"},
{"videoId": "Dme8X2N9FI4"},
{"videoId": "m5VahV3jbYM"},
{"videoId": "3kqLqAWRzDM"},
{"videoId": "gB5bc9zD-Qs"},
{"videoId": "hMFjqWPzRfQ"},
{"videoId": "eAEc-lnIQhw"},
{"videoId": "ihsuUKJkOPQ"},
{"videoId": "0TRrGhLCcqE"},
{"videoId": "24e6kFFTQsE"},
{"videoId": "i3qkju-rmQo"},
{"videoId": "URedkxnVKM4"},
{"videoId": "wztdyQvMaD4"},
{"videoId": "WuDAif7TOjY"},
{"videoId": "WPfyKli9jIQ"},
{"videoId": "1WJa0VDvUH0"},
{"videoId": "xTCOzZkEFlQ"},
{"videoId": "2s4dRGKa4IM"},
{"videoId": "tMfGNYZifZ8"},
{"videoId": "5ZaEa66t_DA"},
{"videoId": "FwSxEW1SbX8"},
{"videoId": "kUVSNgoY-00"},
{"videoId": "H1dkiDWiZkM"},
{"videoId": "m_aF4nPAe6s"},
{"videoId": "s5k9nPxvbo8"},
{"videoId": "OeydAaJ-qFI"},
{"videoId": "qZXYj4G4vzg"},
{"videoId": "6ICMP9b1YGc"},
{"videoId": "5Xtzz1XfPzI"},
{"videoId": "ruk2yR2vLSc"},
{"videoId": "_b7tLZFk_wQ"},
{"videoId": "h2rEeZt4mEg"},
{"videoId": "coQzG1xHMK0"},
{"videoId": "ZP43wdQt4G4"},
{"videoId": "C8ujYkKJcXI"},
{"videoId": "a8yDu98eyjI"},
{"videoId": "PZKtHjWvIsM"},
{"videoId": "uMV6ExeLLxI"},
{"videoId": "e8JecFlwjNk"},
{"videoId": "Ps0FPF3WWP0"},
{"videoId": "U5Jal8_WgeM"},
{"videoId": "9d5hLwQXuko"},
{"videoId": "ceKlciwrK1Y"},
{"videoId": "1Jun0BIEjpM"},
{"videoId": "pve5ciS_DqE"},
{"videoId": "pGo_52KHRvM"},
{"videoId": "kjHg6cpmeWY"},
{"videoId": "b4mVR8h2288"},
{"videoId": "LGId5HkH7QE"},
{"videoId": "49d4tbT7FSY"},
{"videoId": "0h3kzWKbVYw"},
{"videoId": "q8VS4poaxcA"},
{"videoId": "2LsQXGm4T5w"},
{"videoId": "8heOKMjz1U4"},
{"videoId": "gblx2Xh90XY"},
{"videoId": "5_HRAbMTW1g"},
{"videoId": "IGIY5n3dn48"},
{"videoId": "CkK2BXaWKpM"},
{"videoId": "on9bggrSoqY"},
{"videoId": "3wvXKET6S50"},
{"videoId": "tWSdhGudMFI"},
{"videoId": "YjD8xxH9ah0"},
{"videoId": "BjZGLKTmkXg"},
{"videoId": "J-Ae3ViqtL4"},
{"videoId": "2osL45g0j2E"},
{"videoId": "_91tC0XFXJs"},
{"videoId": "5nejOn3n-Rs"},
{"videoId": "mhvhYTMcfS4"},
{"videoId": "jzB74c79Pqk"},
{"videoId": "WUOq0MH2REE"},
{"videoId": "4jIlnLqmu08"},
{"videoId": "iJsDZNQNoYU"},
{"videoId": "IiSF9KPJ4t8"},
{"videoId": "MfMvM1EUMgQ"},
{"videoId": "35t2a2GeNq4"},
{"videoId": "Y_mkcQPga-8"},
{"videoId": "6MCiVCkXHcM"},
{"videoId": "Epavh3b4PeA"},
{"videoId": "j3jLyqhFeXk"},
{"videoId": "Sqo6fQayAaw"},
{"videoId": "aSvUa60MOfs"},
{"videoId": "2NIsCBc4V10"},
{"videoId": "b_9aLYQn0gQ"},
{"videoId": "nEMolVKXmeQ"},
{"videoId": "KlmP1f50bVM"},
{"videoId": "0zTy6iE66uA"},
{"videoId": "QcDaHnXl4Kw"},
{"videoId": "sqcYtpoR17k"},
{"videoId": "YC7w1tLa6xo"},
{"videoId": "qvRTXmsg2Ko"},
{"videoId": "EtrlL1YBEls"},
{"videoId": "w_dn30bq-as"},
{"videoId": "GpjkO93qYNU"},
{"videoId": "25P31wN8la0"},
{"videoId": "By7-SVS9sxQ"},
{"videoId": "uQlq175xMAs"},
{"videoId": "_UEwXqfkaJg"},
{"videoId": "cbzFO-mu20Q"},
{"videoId": "pRr-AM6s658"},
{"videoId": "BR7q2H1esM8"},
{"videoId": "OUoIiH6l5ZI"},
{"videoId": "RTAEfm-jiLc"},
{"videoId": "JObimITax8A"},
{"videoId": "SKV6Zpf9H_4"},
{"videoId": "lufCZ3bFYjo"},
{"videoId": "xH3rjHHDMSs"},
{"videoId": "WU72wrzl0K0"},
{"videoId": "cgvtZsh-hCs"},
{"videoId": "Ko1bqasNDls"},
{"videoId": "PTSr5R35Dyw"},
{"videoId": "dQ4-Z5i0TR4"},
{"videoId": "sU_Qj46feCg"},
{"videoId": "OWEgNcrlpII"},
{"videoId": "b78_DLm_rhQ"},
{"videoId": "IavjkqW1aBI"},
{"videoId": "zL5MnrLdMpQ"},
{"videoId": "Xvx6YnJ83C4"},
{"videoId": "IGQmkmO6X6w"},
{"videoId": "j4a2X_frKZM"},
{"videoId": "FWqu2RqiILE"},
{"videoId": "ryy5sm9CVf8"},
{"videoId": "I1sBqK_wdHE"},
{"videoId": "YA7eDJhLJOM"},
{"videoId": "AjW0DMyi4Uc"},
{"videoId": "kD6YAHfB4NM"},
{"videoId": "5h72tQ_4rkI"},
{"videoId": "L0DiamOPcWY"},
{"videoId": "AAUky5P6xFA"},
{"videoId": "bX2ACyzUPdw"},
{"videoId": "-odpUeBQSz8"},
{"videoId": "liCI0Mc20CA"},
{"videoId": "fDPuZklAl0c"},
{"videoId": "xV8nwEBXxs4"},
{"videoId": "TXkk9QMtgSY"},
{"videoId": "0pxhnXRSVHI"},
{"videoId": "-BaolC5VY3k"},
{"videoId": "bIOUk8d6vWU"},
{"videoId": "5tRnWbkKj_8"},
{"videoId": "1zn_9uE9uzE"},
{"videoId": "ibEcjMrImjs"},
{"videoId": "TyzBFlm_awo"},
{"videoId": "ffJUbFdZ6sI"},
{"videoId": "N9lTOiXM2Rg"},
{"videoId": "Ws0zuw5bLQE"},
{"videoId": "6jZgpV41w7g"},
{"videoId": "4JVu92zHCIc"},
{"videoId": "uIV6oRTp8YQ"},
{"videoId": "49S1gM5aQa8"},
{"videoId": "pls7oQag1bs"},
{"videoId": "9DRqmxOC6NU"},
{"videoId": "wews05T-LiU"},
{"videoId": "IgbP2DLNKo0"},
{"videoId": "NFMm4haPHKY"},
{"videoId": "uCkwmc3i9mY"},
{"videoId": "dg3ppz9TLYw"},
{"videoId": "xOdB0Goi0YQ"},
{"videoId": "5vzMwnL7gAI"},
{"videoId": "-tVNp2nGofs"},
{"videoId": "1nlx4R9U1YY"},
{"videoId": "sP9-nUM6CZY"},
{"videoId": "ulveE-YeTLA"},
{"videoId": "DW72acSlSSI"},
{"videoId": "vGZ9Bmxgz8w"},
{"videoId": "H3R1y1ADCZw"},
{"videoId": "xnNffPju1xg"},
{"videoId": "eE0IDkp2VHI"},
{"videoId": "FMFkXAq1BZM"},
{"videoId": "54N6M7E1jeA"},
{"videoId": "eSuI2tHcOR0"},
{"videoId": "Bn5KslpMBJE"},
{"videoId": "S2wwP7JoKVo"},
{"videoId": "Jgd4OIFLybI"},
{"videoId": "y_7uvkrNR74"},
{"videoId": "4RnjJKS59ZQ"},
{"videoId": "6BenEHjZYdM"},
{"videoId": "b6apJfaIMHk"},
{"videoId": "H7aCZMwMCRw"},
{"videoId": "J1k33Z3jF6o"},
{"videoId": "9zF2DRxOOeA"},
{"videoId": "wuam05MD4xU"},
{"videoId": "I2uexpoLFDk"},
{"videoId": "W4vU6zunUPU"},
{"videoId": "3TKQFr4BvG4"},
{"videoId": "b3vYVzlu_X4"},
{"videoId": "fplHhRaCtAM"},
{"videoId": "zViSqvprrFw"},
{"videoId": "3zBQA6YLp4I"},
{"videoId": "FvA-SZq05i4"},
{"videoId": "kKrImsv_s_w"},
{"videoId": "RYnijvXJVKY"},
{"videoId": "rvkEJsIqzXU"},
{"videoId": "XyHmwT53juo"},
{"videoId": "Lrg_XWUlmIg"},
{"videoId": "ltviYSypLFU"},
{"videoId": "PciatoxRs2k"},
{"videoId": "fthBdRg9BEo"},
{"videoId": "hYth1L2L_Yo"},
{"videoId": "JjUqQaKSB5g"},
{"videoId": "h0keLIGNDoU"},
{"videoId": "pzsCQ3pBHUY"},
{"videoId": "oV9Nk1ctHYc"},
{"videoId": "nGZzY6endZg"},
{"videoId": "wSJGfI1b4nA"},
{"videoId": "qF_NBzr9hdQ"},
{"videoId": "HIyd3N9_8d8"},
{"videoId": "cG8OwQJBtVQ"},
{"videoId": "-maaonZV67U"},
{"videoId": "Q37xYfDvuK0"},
{"videoId": "T1cWTuPTW_E"},
{"videoId": "GG3gLXslRmE"},
{"videoId": "W6STMEu7nlM"},
{"videoId": "Fj1EXHYaNdA"},
{"videoId": "MPdMN6AB9Jo"},
{"videoId": "TlmXVQAb8UQ"},
{"videoId": "MKf59EOp7YI"},
{"videoId": "n_lOXJ6nWus"},
{"videoId": "mqqtIb-jPxE"},
{"videoId": "2iefCwGSHSI"},
{"videoId": "DUMDKf6Vscc"},
{"videoId": "VMwSmQcub50"},
{"videoId": "8s2QUgKnyhM"},
{"videoId": "VV2_L0xVEfc"},
{"videoId": "XuN3ylqqUfE"},
{"videoId": "tSB_xavesUs"},
{"videoId": "xVWwDc5aNDM"},
{"videoId": "zDzH-NF_EE8"},
{"videoId": "O7h6-32Wo-s"},
{"videoId": "mlUPKqUzw8o"},
{"videoId": "atpPG36fUpQ"},
{"videoId": "fTysBBsTEas"},
{"videoId": "lWf8LNPV4Zs"},
{"videoId": "JlNuleYEgH4"},
{"videoId": "Xs7gE6gO9_Y"},
{"videoId": "4oshMk2ZtGI"},
{"videoId": "h0qNcEGpcZw"},
{"videoId": "pp3tiTkCTis"},
{"videoId": "oDrohzc06GY"},
{"videoId": "B7VJaa-owbo"},
{"videoId": "ETV3BQzaah8"},
{"videoId": "vI7FOf2ZeN4"},
{"videoId": "4bIc88hQJ6M"},
{"videoId": "y4791uY4plg"},
{"videoId": "GhOg5KufDzs"},
{"videoId": "aAc3lOyYAYU"},
{"videoId": "2wwFcX5jATU"},
{"videoId": "0Jq4-3izx2g"},
{"videoId": "-HZWxclxNU0"},
{"videoId": "qhmAYTo0zPw"},
{"videoId": "2Q3LUa7L95g"},
{"videoId": "34L47L_DGZU"},
{"videoId": "UjZcaKEpE60"},
{"videoId": "yiMp1UqUe78"},
{"videoId": "h0zsdyHfwSg"},
{"videoId": "4mPh4EiclUY"},
{"videoId": "BV3Cx5RifU4"},
{"videoId": "SBM6CvnqUmw"},
{"videoId": "KOQhcRSPPRo"},
{"videoId": "0hN5KdYWuAU"},
{"videoId": "oD8q_kXEH4U"},
{"videoId": "cgjlIFbs-DY"},
{"videoId": "3gNztROIi_Q"},
{"videoId": "dQ-M6e5xzrk"},
{"videoId": "dYZxRg6CvX4"},
{"videoId": "pDNRMtPcXjw"},
{"videoId": "rzDgonuEZ68"},
{"videoId": "6IObjr1bg74"},
{"videoId": "v2yf0PW9bmc"},
{"videoId": "xZJYv9hikjM"},
{"videoId": "HxhW8SktpCE"},
{"videoId": "xJftAOdboBo"},
{"videoId": "pUa-2qJTnLI"},
{"videoId": "Url4ohxxxdk"},
{"videoId": "TTN-XrRzqqw"},
{"videoId": "arfOITcYhX8"},
{"videoId": "OYE7a5jeWqw"},
{"videoId": "82OkFlYyL34"},
{"videoId": "vyhxpnq4j48"},
{"videoId": "ACRnXMpvq80"},
{"videoId": "tLcdCRaPLZ8"},
{"videoId": "6dVpobiIZmw"},
{"videoId": "GHiCZ5yHYW0"},
{"videoId": "lYdgrgeLPdA"},
{"videoId": "NUSv1ptSXF0"},
{"videoId": "obLiSMN3phU"},
{"videoId": "XgICthGS6qY"},
{"videoId": "fVF8sFU6j04"},
{"videoId": "iOqoPlSfbm4"},
{"videoId": "DW7LFUBqYvk"},
{"videoId": "v-F9O_5r6wk"},
{"videoId": "RQTsJN-D7UM"},
{"videoId": "xtXrhhCiJ6g"},
{"videoId": "ngMBYF5vITw"},
{"videoId": "97oLyx1Z7U8"},
{"videoId": "WkUexvXl30o"},
{"videoId": "mnnwizypewk"},
{"videoId": "olQROwJtH3g"},
{"videoId": "FCxd2DMGa3c"},
{"videoId": "XXrqaWPxfNQ"},
{"videoId": "JlhVpUOrGl4"},
{"videoId": "P7fvpeJRs-s"},
{"videoId": "pCo0iR1FjGY"},
{"videoId": "i3pNZJ8p3Hk"},
{"videoId": "r_42VoyUPBs"},
{"videoId": "VFEL4_11rXM"},
{"videoId": "Sl1ZnvbWGL8"},
{"videoId": "8eIrMDEAK14"},
{"videoId": "HLhQcFHUADY"},
{"videoId": "Crdvvg1h0nY"},
{"videoId": "pUx6HTquIiU"},
{"videoId": "86-iDJ2LNxw"},
{"videoId": "cTHR-viHxaM"},
{"videoId": "cNX7hI3DUvY"},
{"videoId": "-o05Uf_X08Y"},
{"videoId": "YoPGgJWe3Tc"},
{"videoId": "iA1nwJMAtCY"},
{"videoId": "8ioudp5fNhE"},
{"videoId": "Ne7eAWvOh8U"},
{"videoId": "KSFGDGc5ZMw"},
{"videoId": "CDK_jS4Rc1M"},
{"videoId": "30vjthbGOt0"},
{"videoId": "RZ4V1cMFWj8"},
{"videoId": "t8JQMpeHMp4"},
{"videoId": "_S_WPCMMidU"},
{"videoId": "bZtoNt5lbpo"},
{"videoId": "CHLLv-ELC5c"},
{"videoId": "xRRGYZtBq6o"},
{"videoId": "CuaSIiwEjwo"},
{"videoId": "yHtMwk0SRhc"},
{"videoId": "ZAeBaAAo0NQ"},
{"videoId": "rSqPrbR99mE"},
{"videoId": "I5dXH4OyfOM"},
{"videoId": "f7OlPu3s_E0"},
{"videoId": "dHcgRpr8MCw"},
{"videoId": "zFzkTFq6dhE"},
{"videoId": "A8Tyb8hU00U"},
{"videoId": "guXLVWUPTCY"},
{"videoId": "EzTD3ENv0rI"},
{"videoId": "YIKlrCvlfI0"},
{"videoId": "jBhehk-iGiA"},
{"videoId": "5hL_XlekFA0"},
{"videoId": "kPM5RCDZ-XQ"},
{"videoId": "Q1IoEBaeumo"},
{"videoId": "iwZUQLCmS0Q"},
{"videoId": "TF1oW-N6FtU"},
{"videoId": "zkgkYduUZu4"},
{"videoId": "QKfDnmtAIjw"},
{"videoId": "be2OWEu3-GQ"},
{"videoId": "CVhqIL8nVLw"},
{"videoId": "SPghJ4anZBI"},
{"videoId": "KltrD1D3xhk"},
{"videoId": "xqRyLCexOpo"},
{"videoId": "nPBAyfg_GUM"},
{"videoId": "NdhC_Dai64g"},
{"videoId": "44QXY2XmNR0"},
{"videoId": "jSyvrjHvGDA"},
{"videoId": "bboe9jZJMYo"},
{"videoId": "v4fZP3ROIb4"},
{"videoId": "5G0lg-tjyvo"},
{"videoId": "U4mLgKEPTdE"},
{"videoId": "pWuxYBIe4nY"},
{"videoId": "HL588lzeX_M"},
{"videoId": "p7rqViXj6Y4"},
{"videoId": "5z447A6KmVc"},
{"videoId": "nlXBpAONky0"},
{"videoId": "fayHdfOgOXs"},
{"videoId": "Z8cCdOjGyLs"},
{"videoId": "KZ_wdlhCIC4"},
{"videoId": "_fR1P4um0JU"},
{"videoId": "RmagWIWOM4w"},
{"videoId": "9v8muaFMcS0"},
{"videoId": "Z-tCBzFdwDQ"},
{"videoId": "s8hFYWvZzdo"},
{"videoId": "v8hpsc-smsg"},
{"videoId": "soXtvoa7JLw"},
{"videoId": "BMmiZtd_hl8"},
{"videoId": "PbVQPb7R7w4"},
{"videoId": "3UzN5ILtq6E"},
{"videoId": "UM8wLHFCOG8"},
{"videoId": "lOTEsmZulic"},
{"videoId": "ATdwbyGdWyc"},
{"videoId": "2WD5ejcW12o"},
{"videoId": "cFl9NG1GuE8"},
{"videoId": "iLgn8VVfPr4"},
{"videoId": "jSuco8FZ36I"},
{"videoId": "5zXzVIwiiYI"},
{"videoId": "zYHGcxqDn4w"},
{"videoId": "7Jupez523X0"},
{"videoId": "BFdJpSboOL0"},
{"videoId": "Ja6Zwcqf1dA"},
{"videoId": "iDqilkancU8"},
{"videoId": "TmHyUgFxkx8"},
{"videoId": "RiKs1QpGwjg"},
{"videoId": "tLcxw5XARm4"},
{"videoId": "YeCaGIeOrgk"},
{"videoId": "jajY5tz90II"},
{"videoId": "J3NmF9UN0j0"},
{"videoId": "qkTaKkSMQBM"},
{"videoId": "MOA4LISf4-k"},
{"videoId": "0YYjRBAlqfc"},
{"videoId": "D30RwSSsbWc"},
{"videoId": "GyG_cYR071c"},
{"videoId": "jjQKWDLgsCQ"},
{"videoId": "js0TqWKCF20"},
{"videoId": "s9VoDSMylOc"},
{"videoId": "B2wthjdicLQ"},
{"videoId": "lcxsFQlOTyg"},
{"videoId": "45bdy4Xolew"},
{"videoId": "6BNKcdruyXg"},
{"videoId": "4aWED2GvouA"},
{"videoId": "gIWgXOKl-lk"},
{"videoId": "TaAB3F1IwqI"},
{"videoId": "H-c2KZvZ9cU"},
{"videoId": "1c7sOrjVQa8"},
{"videoId": "YC5hiuxtkRw"},
{"videoId": "NVR55fp7uOk"},
{"videoId": "W7QWYkX3a-I"},
{"videoId": "meZk6jBFUWs"},
{"videoId": "dd7raEUVIOU"},
{"videoId": "P6n6bDqyI_s"},
{"videoId": "PDDkze546nQ"},
{"videoId": "GU3RM5eqeho"},
{"videoId": "TJnUb99FMlE"},
{"videoId": "4uWhZGVYAlA"},
{"videoId": "-60zMryfYGE"},
{"videoId": "JbJXLeAy9W8"},
{"videoId": "AtGaKCgWhrM"},
{"videoId": "PipeMcpQ_ss"},
{"videoId": "-BLShJ8O96o"},
{"videoId": "51foaTjOYaY"},
{"videoId": "bbR6oNLUS3Q"},
{"videoId": "iX1H6C4kaOU"},
{"videoId": "b7ZrwD4jLXk"},
{"videoId": "rqdhpRnNXrQ"},
{"videoId": "0BipKv2fcno"},
{"videoId": "fG5f1rmgN1c"},
{"videoId": "qxujRj4-8-k"},
{"videoId": "5kuN_lrVx-M"},
{"videoId": "Y7GwJHb0z6k"},
{"videoId": "L7SSENh1Esk"},
{"videoId": "OgXFhERpl2E"},
{"videoId": "0HPySzl1rTU"},
{"videoId": "UQdlJv6kCAw"},
{"videoId": "AsHPmlfWEt0"},
{"videoId": "NSKG4XRTU5g"},
{"videoId": "NQzdq71KP80"},
{"videoId": "eznbAaBME3E"},
{"videoId": "UBMzsmpMGoc"},
{"videoId": "RbUjAzEyxpA"},
{"videoId": "PK6Sgj6hIYs"},
{"videoId": "u0F03Lr79M0"},
{"videoId": "of7CmKDdke0"},
{"videoId": "tILjvqkEzW4"},
{"videoId": "tpedykMNTXw"},
{"videoId": "d1OOCb-KKm8"},
{"videoId": "MOm-UmD84rQ"},
{"videoId": "2K-_WPUFP40"},
{"videoId": "VNmLDuGZCKg"},
{"videoId": "MyLTdk6GN3Y"},
{"videoId": "nQ_R9hhHB5A"},
{"videoId": "XvhBpbYMopM"},
{"videoId": "bspVWbMaWdo"},
{"videoId": "zzkpCikADwI"},
{"videoId": "zl4Qb1D844Y"},
{"videoId": "dIiwcILFalQ"},
{"videoId": "-Xt-LSWhTHQ"},
{"videoId": "uqLeqnGORA4"},
{"videoId": "ceYOSm_Gq-o"},
{"videoId": "JpU6P_1fhRo"},
{"videoId": "wFACB1okDVY"},
{"videoId": "egYFlVkcvW4"},
{"videoId": "RK-ix48mACo"},
{"videoId": "I8aQQGfuLTE"},
{"videoId": "1H3h0JB7NOQ"},
{"videoId": "A2i3Jd0Exq8"},
{"videoId": "RcmVcaYxCJU"},
{"videoId": "OLJpv9K3_TQ"},
{"videoId": "-_b0k4N20Cw"},
{"videoId": "9LPUTad-ZO4"},
{"videoId": "mR__wWuREs4"},
{"videoId": "xhsN_36OW4w"},
{"videoId": "iVo242R_X8I"},
{"videoId": "LhxVUGzRpGQ"},
{"videoId": "pO9Da-P-fj0"},
{"videoId": "xA9HMTYuZHk"},
{"videoId": "3cCFnSeleL0"},
{"videoId": "z7SsF6cE5wc"},
{"videoId": "sjYx_mvcZl0"},
{"videoId": "DWLpX_1C4ew"},
{"videoId": "z7eMPcvodEA"},
{"videoId": "oB9liMW4_IM"},
{"videoId": "Yqx6Y-xI-eA"},
{"videoId": "Dm1tbY7bG8o"},
{"videoId": "B9eFQa2fenY"},
{"videoId": "5D8rkTF-bWU"},
{"videoId": "-BBbBnJ2FqQ"},
{"videoId": "HyzSO1Bx1jA"},
{"videoId": "zFE7Uhxxa9c"},
{"videoId": "zCGP1GseKmM"},
{"videoId": "tN6oQpasntM"},
{"videoId": "4ngdDQsCY_s"},
{"videoId": "CZ2iTurleIg"},
{"videoId": "V6Ap3jc5_g8"},
{"videoId": "cItWPyPGZzA"},
{"videoId": "mRhRFE_Fr10"},
{"videoId": "fkeP1r1ZX10"},
{"videoId": "VFV0pURKzGU"},
{"videoId": "tzae5ephvfc"},
{"videoId": "HoIOGop_Zkg"},
{"videoId": "P1XgEWCqF1c"},
{"videoId": "p9hGggnxq7s"},
{"videoId": "VQqoC2qD9Ww"},
{"videoId": "S3-hgpylHVk"},
{"videoId": "488P4hPuANc"},
{"videoId": "3DdllIgzBbE"},
{"videoId": "yowe-2hj7ec"},
{"videoId": "TWe9m0K61Io"},
{"videoId": "jOyean34UEg"},
{"videoId": "SZ5M-u3bU8A"},
{"videoId": "McBtk3ny46I"},
{"videoId": "JxFjiBJ3YbQ"},
{"videoId": "RdsHRLiSsHo"},
{"videoId": "9tDxjLZ9yxw"},
{"videoId": "ZZfSsaSr3GA"},
{"videoId": "PoDmSgmo3wc"},
{"videoId": "iDBQ7YjzHTs"},
{"videoId": "IN-ViF82klk"},
{"videoId": "dzS930D35rk"},
{"videoId": "s0GmxGwaQxI"},
{"videoId": "7RfX_l0W_6g"},
{"videoId": "oK3FxDot4IA"},
{"videoId": "l2Bnb2akpHs"},
{"videoId": "7Dt0O2TEGb0"},
{"videoId": "2l-TXPAw8tQ"},
{"videoId": "eP3KWD3JmvA"},
{"videoId": "oTMeAVXjfiE"},
{"videoId": "oPvOGpd1yeI"},
{"videoId": "VM2nBlyL848"},
{"videoId": "Fs1LjTOpCKs"},
{"videoId": "ONQeQo_vfTM"},
{"videoId": "GKAbnkuITEo"},
{"videoId": "N3LymAGJhBQ"},
{"videoId": "YmQ6CxjZRS0"},
{"videoId": "mhpQaVsMBpk"},
{"videoId": "xHrxcT1WUTM"},
{"videoId": "JXzqcgQVZXQ"},
{"videoId": "KrAWjVGfZnc"},
{"videoId": "K1LslJqZdl4"},
{"videoId": "4PAeMGt-EC0"},
{"videoId": "tWEacxwH3Ys"},
{"videoId": "y-z8StaGW6w"},
{"videoId": "p53-BmM9yNk"},
{"videoId": "7S3Jsxx7afY"},
{"videoId": "E0yH1M9wqEs"},
{"videoId": "BtQXZbnJRNs"},
{"videoId": "P93j-dK8mmY"},
{"videoId": "xzGqxWLWRRQ"},
{"videoId": "fM-SpaUBnbI"},
{"videoId": "Nf65VhP5CLI"},
{"videoId": "WZV9ldrdgNA"},
{"videoId": "xRl0mcfGh-M"},
{"videoId": "TZNJw00a1u0"},
{"videoId": "hZ853h0Sgww"},
{"videoId": "f5wpq7WrKCk"},
{"videoId": "3P3IALCIf1Y"},
{"videoId": "lLzr2VjGwmA"},
{"videoId": "jT2kF2uw9ik"},
{"videoId": "_rOf-rO4L9E"},
{"videoId": "t-owdG7t-Y0"},
{"videoId": "IGqyTbxyAGA"},
{"videoId": "3pWTcSK4mVA"},
{"videoId": "YBtoz4RalrE"},
{"videoId": "Vv37hftYQOo"},
{"videoId": "nWbE8tp2VSA"},
{"videoId": "bXuQv-HnxhQ"},
{"videoId": "1bB6McsnbY0"},
{"videoId": "ZSAoETxubSI"},
{"videoId": "94aBcc_Ej-I"},
{"videoId": "9x-nSIZUS0o"},
{"videoId": "Jih1egYWG0s"},
{"videoId": "4YYSis1OBoc"},
{"videoId": "HQkmvodhaZQ"},
{"videoId": "kIeYDSDCtyo"},
{"videoId": "jSY46Gq_ouE"},
{"videoId": "zBgecgp7XfA"},
{"videoId": "yWxSybS3NIA"},
{"videoId": "jBYMnL5ymB0"},
{"videoId": "2pvlBnxzWuo"},
{"videoId": "Uia4YofmQnA"},
{"videoId": "l7G6ivvUzD4"},
{"videoId": "PIbawCN_54I"},
{"videoId": "pWXDofqB7O8"},
{"videoId": "4rS5MgYd624"},
{"videoId": "qoyhF7Qb7z8"},
{"videoId": "iln-DTp_Xy8"},
{"videoId": "Pq0pFR7YZ4Y"},
{"videoId": "o-kMci33dfY"},
{"videoId": "rm_P44BB3FU"},
{"videoId": "qdker2cgg1M"},
{"videoId": "Is7wqHtZlw8"},
{"videoId": "qwDhYA1-Eus"},
{"videoId": "gisjdDQuuoI"},
{"videoId": "dP-ycgAP06Y"},
{"videoId": "_HFQ_WrDOGI"},
{"videoId": "KIBH5tQCtIU"},
{"videoId": "786-8lTnFMY"},
{"videoId": "hUiF0mCBmkw"},
{"videoId": "_woTrrq0FLM"},
{"videoId": "P8RCbp-vKsQ"},
{"videoId": "9f9kX6stRKE"},
{"videoId": "KQ9PX6R96gM"},
{"videoId": "1lVujYRbnhI"},
{"videoId": "upkQea_Z4Fs"},
{"videoId": "Y0DqSgcTAWw"},
{"videoId": "aJR8TVjt-Nk"},
{"videoId": "5v6lrth0Mbk"},
{"videoId": "sYYCuFOaWQo"},
{"videoId": "AQa0DfHcZRc"},
{"videoId": "El8HR-dmEjE"},
{"videoId": "Dm80WfFvBCM"},
{"videoId": "CmD0kYNw6xc"},
{"videoId": "PpjQAfUzcOg"},
{"videoId": "30XcopUG3GA"},
{"videoId": "OyNvYk53Vaw"},
{"videoId": "TLsosQTtmqg"},
{"videoId": "7GQoFvycGbk"},
{"videoId": "CzU7dTcqec4"},
{"videoId": "QP07zgyWKC0"},
{"videoId": "eRJp5yb6qmI"},
{"videoId": "7suiUg8vcpA"},
{"videoId": "Ha1DGIIc8Zw"},
{"videoId": "Lk1RZVfeA-I"},
{"videoId": "-Q3M2c0L_lA"},
{"videoId": "skQZgxAN6sU"},
{"videoId": "FH7czEXhnA8"},
{"videoId": "cGNQzuirFpk"},
{"videoId": "JgVAYaaMdcg"},
{"videoId": "eETa0-6zW0U"},
{"videoId": "zO-SV5M3YIA"},
{"videoId": "CuPlusgQFtM"},
{"videoId": "SOfr5Pu5kwc"},
{"videoId": "eh3nA920oD8"},
{"videoId": "6kVgyTnLcMI"},
{"videoId": "aegRejucB98"},
{"videoId": "xMF1ILddHnw"},
{"videoId": "kK0MMv4lVWY"},
{"videoId": "5yiG6Lt1GYE"},
{"videoId": "ZU3QzrY4xo0"},
{"videoId": "gqzrBMq3VR0"},
{"videoId": "mcSYUXLluPE"},
{"videoId": "Oexq2PeE5qQ"},
{"videoId": "XOulSuOXKPU"},
{"videoId": "ds-yPxOqUJo"},
{"videoId": "rMDnlLYy9go"},
{"videoId": "ipBjaqbhxlE"},
{"videoId": "FnOQ49-uXkg"},
{"videoId": "bW5A0t2ymHw"},
{"videoId": "h6SwaFpaBuY"},
{"videoId": "o1qS5qbHp3U"},
{"videoId": "J8mm1Y6n0Oo"},
{"videoId": "kk8Nvrci7-M"},
{"videoId": "sdO6p0gKHgI"},
{"videoId": "m85TWy6PF-s"},
{"videoId": "pgcQZ98jCAQ"},
{"videoId": "hbPaFK3tgWw"},
{"videoId": "JHSFawjDU3s"},
{"videoId": "b6Lnm7dPmI0"},
{"videoId": "dtI5Ga5ie8c"},
{"videoId": "SuC3pKs8jWM"},
{"videoId": "PLOPHEexKCg"},
{"videoId": "NhTwnaDD4k4"},
{"videoId": "He-dROKOFZ0"},
{"videoId": "gsEi8y4wxNg"},
{"videoId": "MIZpOp1FgyY"},
{"videoId": "QXzELTrR3lg"},
{"videoId": "dLR4ltQu53Q"},
{"videoId": "wo8ALfCeN3s"},
{"videoId": "QIvk3Ya0wPw"},
{"videoId": "egFIMPY6nWA"},
{"videoId": "DJljIMpKadI"},
{"videoId": "_2Ic6llTFKA"},
{"videoId": "L-saf1UCK3Q"},
{"videoId": "EhGnKhFkLvo"},
{"videoId": "ccmxQJm0aRg"},
{"videoId": "2BKSD_LA38c"},
{"videoId": "GKAqBwC1zhs"},
{"videoId": "ZzBKHY1szXg"},
{"videoId": "_taJnfqORD4"},
{"videoId": "kkyUbEMO7YI"},
{"videoId": "o-1jvJwUL6E"},
{"videoId": "kALAPCINwfQ"},
{"videoId": "CAgyYJZXjWo"},
{"videoId": "mL_487AOxuE"},
{"videoId": "ayz4ohhecsU"},
{"videoId": "-eTqk1hmX8I"},
{"videoId": "EHmsOYvXtDs"},
{"videoId": "0Vvc447d7MA"},
{"videoId": "_V_YqzJDP6o"},
{"videoId": "ws5MxD98Mk8"},
{"videoId": "g0BOS9SBfUg"},
{"videoId": "BPKpgCSFsLM"},
{"videoId": "5isWn1FIaa0"},
{"videoId": "b0QaPCGZig8"},
{"videoId": "EMome2jBoxI"},
{"videoId": "3mqDbhwGtSo"},
{"videoId": "6D-KCGvoLCE"},
{"videoId": "PA4oN3vnT3g"},
{"videoId": "HTDGsV7KjCY"},
{"videoId": "Woc79c0zhcQ"},
{"videoId": "jacLtlMcYXw"},
{"videoId": "kaRrhWFvQ28"},
{"videoId": "VlROw0Crojc"},
{"videoId": "g1MVAGiy6RA"},
{"videoId": "X-RpUatiV7o"},
{"videoId": "BTp-eHBPEzI"},
{"videoId": "JpeGPozM0pY"},
{"videoId": "_4CL6XIn85s"},
{"videoId": "xTesgx6enAs"},
{"videoId": "jLTyFU0PXC0"},
{"videoId": "hWSIWNyFRdE"},
{"videoId": "Hd-Zs9gFAyY"},
{"videoId": "8hd_yO-7Ub8"},
{"videoId": "gXTCQ7cRa6c"},
{"videoId": "UZ1j3C0c8Hw"},
{"videoId": "uE6LR5l0Zc0"},
{"videoId": "1Ggl2ydtK4k"},
{"videoId": "lf6WxJ4PODg"},
{"videoId": "0DaF_YgLjIg"},
{"videoId": "u0iWqgTfkig"},
{"videoId": "MQ569ZY7zJo"},
{"videoId": "EmSFdouB1UQ"},
{"videoId": "wy9Oi5cf8b8"},
{"videoId": "MTGFfpVkjs0"},
{"videoId": "HM7leeoboIM"},
{"videoId": "N7asU6vO8fI"},
{"videoId": "DVjEMzLLPns"},
{"videoId": "rl79xpdu6e8"},
{"videoId": "D7Dm0Px_Xy0"},
{"videoId": "8LcGT9IY_vw"},
{"videoId": "pGo9eYB_-BI"},
{"videoId": "bsvkklAWrD8"},
{"videoId": "Yis3oPdO3E8"},
{"videoId": "_PV5JbJMzek"},
{"videoId": "h2JGK6Nmk44"},
{"videoId": "2mjRjDzgJn4"},
{"videoId": "arqC0TGsv84"},
{"videoId": "DQpzys0gjaw"},
{"videoId": "QqGEW-vsXg0"},
{"videoId": "cWE1RykLpeU"},
{"videoId": "HbGt3Jsy6PU"},
{"videoId": "fIJtdTO5p3o"},
{"videoId": "XBHQiEJmeUQ"},
{"videoId": "6IS87j03xxo"},
{"videoId": "oEfJSg3aYLs"},
{"videoId": "4QcoLp_warU"},
{"videoId": "mQh9zWlZo8I"},
{"videoId": "ZbicQc03p8o"},
{"videoId": "ruGWSwFOzKA"},
{"videoId": "caMXFcqHfqs"},
{"videoId": "m4h5ND4puP0"},
{"videoId": "xRzZY4brH4M"},
{"videoId": "ywsnlUwKKnQ"},
{"videoId": "AQR0JyzdVMw"},
{"videoId": "NLxgGRElMbs"},
{"videoId": "phKzxWHlqAg"},
{"videoId": "qC5IB2lDbQM"},
{"videoId": "O67nz1l1DUU"},
{"videoId": "D_ZItJk1Uvs"},
{"videoId": "j8l_HXKO2jc"},
{"videoId": "r8nku8GD4vY"},
{"videoId": "IonKdf2TjvI"},
{"videoId": "enfKS-ZoHG4"},
{"videoId": "nRLbl6y9foE"},
{"videoId": "Mw5rWs7TA_E"},
{"videoId": "rwB4fe__y8o"},
{"videoId": "T7oBAvpLNQ0"},
{"videoId": "vzL48Zt2-WQ"},
{"videoId": "Z6mbpcpNeeQ"},
{"videoId": "Ck738Upff5A"},
{"videoId": "Q3kvbOg4Fyo"},
{"videoId": "P4Zfak4ZE9k"},
{"videoId": "czv8XpRSa7I"},
{"videoId": "JBz9V22B8Ys"},
{"videoId": "xXAphNOVyd4"},
{"videoId": "Q8vTuss367k"},
{"videoId": "szKTpyT9gPA"},
{"videoId": "LGnlOKqedqo"},
{"videoId": "mhLqD8JNXKw"},
{"videoId": "qlnh9CCEARY"},
{"videoId": "JuCTRztbOik"},
{"videoId": "M89RU1Ox_GI"},
{"videoId": "62bWGurXEs4"},
{"videoId": "N6ptpanoqEQ"},
{"videoId": "K8bNJCp1BIw"},
{"videoId": "tqJ9fffK7_U"},
{"videoId": "Pbd4E2dIUxg"},
{"videoId": "8bcGX7kiGeo"},
{"videoId": "et4Co9_knzo"},
{"videoId": "-k_IJjCSJfw"},
{"videoId": "Lt2glzZhzTQ"},
{"videoId": "gy4EqHWsHq4"},
{"videoId": "wzGU6WWa9Bc"},
{"videoId": "3fighw5zRX4"},
{"videoId": "TuuOhF-N1Pg"},
{"videoId": "-eDqYC7rHtk"},
{"videoId": "p4qq7PjNx60"},
{"videoId": "aoXRmh9AfMU"},
{"videoId": "5z4HD2J6Nv8"},
{"videoId": "gcK1XA3Klag"},
{"videoId": "rQ86lhzFY68"},
{"videoId": "_ncKsnt1SNw"},
{"videoId": "gR0rP6toL5Y"},
{"videoId": "-3GnzTqHVO0"},
{"videoId": "84uRb1XRj2s"},
{"videoId": "QMGp3AElWGc"},
{"videoId": "OcPfbCHqOGw"},
{"videoId": "mkDK0kYRx5c"},
{"videoId": "8haxtK-uvpU"},
{"videoId": "_CEn3FY5S9w"},
{"videoId": "KQaYVw6Cots"},
{"videoId": "YdmtK3IxKDc"},
{"videoId": "r-BlDxPjAwg"},
{"videoId": "SJKEZA7T4_8"},
{"videoId": "DGC_gKqdmf0"},
{"videoId": "OZIzrcl8m3g"},
{"videoId": "UmemcyGlEbA"},
{"videoId": "NDSnA8idJfQ"},
{"videoId": "j8lMNxmTmW8"},
{"videoId": "rUDfgh4WJPo"},
{"videoId": "XC4pGYnU79o"},
{"videoId": "zDwyvSUs5_w"},
{"videoId": "clUO8B3Fjl0"},
{"videoId": "HnCJ3uRkJ5o"},
{"videoId": "v7oYixXvMXw"},
{"videoId": "XCG2qqB9sJE"},
{"videoId": "yuRr4xA6fTw"},
{"videoId": "c1h1cgVypKk"},
{"videoId": "csXXc_ub0sU"},
{"videoId": "OPIEFnLbXYM"},
{"videoId": "9RR8jLoyy3U"},
{"videoId": "9hPpDGW7bq8"},
{"videoId": "lEhZVFSJiZU"},
{"videoId": "4aAXJsBri-s"},
{"videoId": "jYN1loTk18M"},
{"videoId": "3DXLE1SEoFE"},
{"videoId": "vwYTEA83_z0"},
{"videoId": "5aiaxjHnMYg"},
{"videoId": "Gj1U1R_khi8"},
{"videoId": "d5xO73zIjWY"},
{"videoId": "dL3_LaEHPI4"},
{"videoId": "NWunw2v-Jcc"},
{"videoId": "hn1Td5psjzE"},
{"videoId": "eEvpa7U5T-0"},
{"videoId": "tcp4ZbidzMY"},
{"videoId": "CNzH13_3OWQ"},
{"videoId": "TlDCtXLKL18"},
{"videoId": "ljva4ybjwOU"},
{"videoId": "FpLU3gn0CwE"},
{"videoId": "nTY5rCZP3bc"},
{"videoId": "IXWVznMCD7A"},
{"videoId": "1ZIi1GT9O-o"},
{"videoId": "0Nrltv6nMiE"},
{"videoId": "esERsxwxaf0"},
{"videoId": "2-anBDLJrQs"},
{"videoId": "e8OqSg-hb9Y"},
{"videoId": "lhyhpuXdRXA"},
{"videoId": "khcDRhUrUNc"},
{"videoId": "nO04FFU7to0"},
{"videoId": "2YBlP2OBcnU"},
{"videoId": "NN12NF_leco"},
{"videoId": "tdL_Sk1ajHQ"},
{"videoId": "rQIgFzJ_AgY"},
{"videoId": "zt-e6k6pShc"},
{"videoId": "1J52lo3URt0"},
{"videoId": "G74Xu8x34Iw"},
{"videoId": "ewNXoxRRckc"},
{"videoId": "4i5YVx0qn28"},
{"videoId": "2Y0VSRguV1Y"},
{"videoId": "ym6ofNCFmBM"},
{"videoId": "zK034MMfvME"},
{"videoId": "aeQ_PkiHDu0"},
{"videoId": "YhV4B_CRua8"},
{"videoId": "sKmA_-Blt58"},
{"videoId": "jIRUvca1XXA"},
{"videoId": "0GO5k_oI8aU"},
{"videoId": "JqZH57djFUI"},
{"videoId": "_GafJi4e7i0"},
{"videoId": "yTIQMnnaBZo"},
{"videoId": "RGlKmb9xb20"},
{"videoId": "b6F_KFa0vzQ"},
{"videoId": "o-ikLYV89tE"},
{"videoId": "PJ5XrsQEKjk"},
{"videoId": "2PR6vO2-4wc"},
{"videoId": "ZSj-uJT-bWM"},
{"videoId": "UBJ1Q4gG-6o"},
{"videoId": "Ps8MhknevVM"},
{"videoId": "QBMMnZz4UqU"},
{"videoId": "t3AefO9Jv-I"},
{"videoId": "RgIcPTAf6Ew"},
{"videoId": "_9FkOH-ghgw"},
{"videoId": "ZsOGADN_epU"},
{"videoId": "akfLx_ZjKrM"},
{"videoId": "IIYRUcckpEE"},
{"videoId": "AYbl2isNUAA"},
{"videoId": "sG6LYHfM_L8"},
{"videoId": "DF_sVl_jOrc"},
{"videoId": "M4-cOdx0i7o"},
{"videoId": "3-5YCrjES5U"},
{"videoId": "jmCn_QaZKhI"},
{"videoId": "kZjPiC9yCUM"},
{"videoId": "RXyxw3idygI"},
{"videoId": "AE672pDhjo8"},
{"videoId": "QwUejkLM_Y8"},
{"videoId": "ACt_-NRsg-A"},
{"videoId": "ljDUEIfD2SQ"},
{"videoId": "3LsgR50fJ7M"},
{"videoId": "lDa5FRnZW8M"},
{"videoId": "QxPwbe944Mc"},
{"videoId": "IF0pqURKQfw"},
{"videoId": "EWVhAGwGpo0"},
{"videoId": "KEMOASx2nYw"},
{"videoId": "Tn1j2s33dUs"},
{"videoId": "6ypLLDMW9Tg"},
{"videoId": "SSCtblTVkkc"},
{"videoId": "-nkDQyMGu7c"}
]}