{"videos": [
{"videoId": "Y8M8MrSar0Y"},
{"videoId": "05PzEx8qb1k"},
{"videoId": "E9LqMCg5NcI"},
{"videoId": "ki1XW-raSNI"},
{"videoId": "YCw09PY--W8"},
{"videoId": "MoRuJ63LSVg"},
{"videoId": "YIvGHNjOzsA"},
{"videoId": "7QCPFn9M59I"},
{"videoId": "vvfO8eANTH8"},
{"videoId": "P8KFy7eIqcs"},
{"videoId": "JSISb5XqYYc"},
{"videoId": "pQZNjYtzBbI"},
{"videoId": "V-a-u1A8sSM"},
{"videoId": "3J4SO0eHUNA"},
{"videoId": "k6NcEW_zMLg"},
{"videoId": "InYO-mSfk70"},
{"videoId": "VjMERlR371s"},
{"videoId": "4pkDKuK1lH8"},
{"videoId": "GjqpwSbPnP0"},
{"videoId": "jUoCPme7CeI"},
{"videoId": "_yXwlcZwHMg"},
{"videoId": "B1QLX375JaE"},
{"videoId": "_hw6M8Epd9c"},
{"videoId": "aYPGyVmk9fY"},
{"videoId": "kYV_Os4z0Rw"},
{"videoId": "-7TSYrt78-I"},
{"videoId": "fvt2s8tM654"},
{"videoId": "FWkLMRWQNQQ"},
{"videoId": "PkHgxtQXqmM"},
{"videoId": "BlQFClBYHE0"},
{"videoId": "IHUXp49Xlzg"},
{"videoId": "B_jHs8WbGAs"},
{"videoId": "Mc1s-e178bw"},
{"videoId": "kjaG8y-tqY4"},
{"videoId": "RcEXLkthzko"},
{"videoId": "FSgZPr-UtFI"},
{"videoId": "3tDvLLVmo20"},
{"videoId": "nRASbZZKFQ4"},
{"videoId": "zG2W-GVSe9I"},
{"videoId": "oAazh1PxbYw"},
{"videoId": "1lhusczXNJw"},
{"videoId": "k4OZ_0yFYNg"},
{"videoId": "7DoZ-7OpSKY"},
{"videoId": "VQzQ0LhAzB0"},
{"videoId": "NfrG8aF1TB4"},
{"videoId": "BjEdRaS_eYY"},
{"videoId": "Xa270kgyoZE"},
{"videoId": "6u0A-7v2sp8"},
{"videoId": "KQwnwa5YvHI"},
{"videoId": "ejhFToabT5M"},
{"videoId": "3WgrEWykCHg"},
{"videoId": "f5lU6R2-VzE"},
{"videoId": "CM7Pdf2kEY4"},
{"videoId": "ijFDYvWFzIs"},
{"videoId": "s1AKr1IqZzs"},
{"videoId": "AUhJGTMMOt0"},
{"videoId": "lFRTWdvYjbY"},
{"videoId": "UxXB-F3RiuU"},
{"videoId": "LRr9w7LxmhM"},
{"videoId": "-bKt6YyH1JU"},
{"videoId": "yjRa90Apajo"},
{"videoId": "a0h4Az9YxD4"},
{"videoId": "_MM_d6qSpvc"},
{"videoId": "uEikyxHTCRA"},
{"videoId": "LuVMNUErHgs"},
{"videoId": "EwmHiGlkcLg"},
{"videoId": "PCt5k0N6nTw"},
{"videoId": "9PI5lDfoYP8"},
{"videoId": "xyhjiDDVTMk"},
{"videoId": "rBT1q82oJtM"},
{"videoId": "3RRD765-bHU"},
{"videoId": "Coaq520GgzM"},
{"videoId": "OXcnrzfbIBQ"},
{"videoId": "dMyxOnyGRro"},
{"videoId": "noCSBLrfFaI"},
{"videoId": "B7KEvayGeso"},
{"videoId": "flqJxxd-ySU"},
{"videoId": "TnyHQfZ6oJQ"},
{"videoId": "UeWRYKZ5--U"},
{"videoId": "R1So0NBVoPI"},
{"videoId": "zK33F2cc660"},
{"videoId": "bCb_H7a1kVE"},
{"videoId": "sKISwOgdBvk"},
{"videoId": "B3sNFT-0qrk"},
{"videoId": "xh69e4RrqpQ"},
{"videoId": "spiRF62Q914"},
{"videoId": "nh30H0fk-T4"},
{"videoId": "s5DVxZluwQU"},
{"videoId": "K5Hvf3l04wQ"},
{"videoId": "M7JZ8Z9tw2U"},
{"videoId": "iVJ2o5yD3nw"},
{"videoId": "VTcex32H5dA"},
{"videoId": "mv07-MOUlxk"},
{"videoId": "CqEPThj773E"},
{"videoId": "sj-wWR9lmZs"},
{"videoId": "c6PiC2iLLfY"},
{"videoId": "rvbC5y0z5M0"},
{"videoId": "q0rWi9zxFeo"},
{"videoId": "BzAoKbfpczI"},
{"videoId": "_EIMqgYNu0c"},
{"videoId": "GdNPmQ-DEUA"},
{"videoId": "ZRFVDBgU9Mc"},
{"videoId": "Ri1Fz9gYysg"},
{"videoId": "JsVj8nMAAPo"},
{"videoId": "yodKNnagdJU"},
{"videoId": "Sc50t8-qwxM"},
{"videoId": "ADdlb6tvTTQ"},
{"videoId": "HKVgZCHSUJY"},
{"videoId": "ZZyurJW29xI"},
{"videoId": "wS2KJf5fLCo"},
{"videoId": "8pFB5qfTVJY"},
{"videoId": "mwTkhAuu1JU"},
{"videoId": "bdB2PyJfOhA"},
{"videoId": "-zKk4reTBEA"},
{"videoId": "aQqnZJ18q7Y"},
{"videoId": "oh8gsMQK5I8"},
{"videoId": "x18EAjbTWjA"},
{"videoId": "lAoGznK0Ebk"},
{"videoId": "UQNG7JyCWIU"},
{"videoId": "iL3CyXTENRo"},
{"videoId": "hm3JK2dqoAU"},
{"videoId": "6Urp5-mGsXI"},
{"videoId": "lO8ONkpnCO8"},
{"videoId": "TgwRWe0eu4s"},
{"videoId": "q2fmQy-IQW0"},
{"videoId": "mk_3sx8xDhw"},
{"videoId": "BtQqJlVxG7g"},
{"videoId": "0153XTDb524"},
{"videoId": "8jVR0Xxkb5k"},
{"videoId": "rx8k0D7tn4w"},
{"videoId": "VTT5gxPPBvU"},
{"videoId": "37GLAmSd1cg"},
{"videoId": "UIk0VslCIMY"},
{"videoId": "OYA4QnRue98"},
{"videoId": "W0LxeJLj9h8"},
{"videoId": "RLNrDPbIOqE"},
{"videoId": "h5wJu200vBE"},
{"videoId": "A_mPGgiEhdM"},
{"videoId": "TK7q5Jl-Pkc"},
{"videoId": "K_sHIP50rlM"},
{"videoId": "O5EoRGMca4Y"},
{"videoId": "Wo2IaqzEyB0"},
{"videoId": "abIxJ0JUhqo"},
{"videoId": "33E0ksVVpis"},
{"videoId": "h2gkWNBqgAs"},
{"videoId": "wmuYsCAQrNE"},
{"videoId": "FOQ04oPcrKk"},
{"videoId": "G2j2eOthcoA"},
{"videoId": "ZEb_-zEVNNQ"},
{"videoId": "biWn1N2zpEs"},
{"videoId": "eq0qfa7Hho8"},
{"videoId": "O2_lvx0mydw"},
{"videoId": "mzQ9BLl3b5Y"},
{"videoId": "F_CiNNoysM4"},
{"videoId": "-6AYrNrB8aY"},
{"videoId": "pS_hv_Oh_Ms"},
{"videoId": "gWFVyab9U6s"},
{"videoId": "ZFKHPn6mHRc"},
{"videoId": "NpatIU5LSfg"},
{"videoId": "sn3lGFZR5C4"},
{"videoId": "bOKdjZRYh-A"},
{"videoId": "rQ67I3Tqm8A"},
{"videoId": "t461N_EAu8I"},
{"videoId": "5l6_qQTI-OE"},
{"videoId": "xtZx-YXr43c"},
{"videoId": "81bdDrxhXz8"},
{"videoId": "kKZZmxMWtfc"},
{"videoId": "Uu58lfKl5JE"},
{"videoId": "ygvhUL8vqYk"},
{"videoId": "QMNWY0-Eafk"},
{"videoId": "MUe8w_aqQGA"},
{"videoId": "FKzh4tVqWf0"},
{"videoId": "-UM27ckvQQQ"},
{"videoId": "o4Wcf4dY7CE"},
{"videoId": "7jox7MIFulQ"},
{"videoId": "xPpe3HuCPPU"},
{"videoId": "h1S78C5O90U"},
{"videoId": "6pl3lL3fV54"},
{"videoId": "FnYYr3TNElw"},
{"videoId": "58xCbHbRF6o"},
{"videoId": "fmPOithJjzI"},
{"videoId": "zE9dhx999iA"},
{"videoId": "btV-oxjBALI"},
{"videoId": "epV9THSuI0g"},
{"videoId": "LnxFHxv9Q54"},
{"videoId": "USVM_7yqZps"},
{"videoId": "_wruxITx0Q8"},
{"videoId": "Vb3E650C5JU"},
{"videoId": "bkaL4vWZ0vA"},
{"videoId": "P5jsLbaHQno"},
{"videoId": "SD24tHKdoUM"},
{"videoId": "w1gDKYtEaMY"},
{"videoId": "xCafbcB3rgM"},
{"videoId": "8rKR1Erykmk"},
{"videoId": "OuFb6_G3Gks"},
{"videoId": "oW2JR09xoH4"},
{"videoId": "x4Y2YnQgKDg"},
{"videoId": "8vzP4jh7n5k"},
{"videoId": "SJDF1CThIbE"},
{"videoId": "omt5dcm-Dsc"},
{"videoId": "xogX9nbiGwQ"},
{"videoId": "2XNz6MIUtLM"},
{"videoId": "tH6ytLoPiz4"},
{"videoId": "mZSUi8LOvhA"},
{"videoId": "JTlkv0IoryA"},
{"videoId": "ERLJuFlTiNw"},
{"videoId": "lV0NyRgffKw"},
{"videoId": "7uoKW-JUU-s"},
{"videoId": "FQvClOpAZII"},
{"videoId": "z9IYgahvC0o"},
{"videoId": "rdYUiA77Owg"},
{"videoId": "Pcmyob0eOSQ"},
{"videoId": "7JAwWoInNng"},
{"videoId": "Zv9m657GxKQ"},
{"videoId": "BsIHWo_hIMg"},
{"videoId": "11zMQR5o0LE"},
{"videoId": "Rz-UPtDgJHY"},
{"videoId": "Phzibwxt5JU"},
{"videoId": "lmsyhAHZe_Y"},
{"videoId": "IIrQzrX2bBQ"},
{"videoId": "vYpj4izJ9yw"},
{"videoId": "k2-IuX80qfI"},
{"videoId": "UXDOYqydY1o"},
{"videoId": "drlRhuTJ7uM"},
{"videoId": "eKXuodvYITs"},
{"videoId": "LADbGRBxyxs"},
{"videoId": "fXwwIM9aQgs"},
{"videoId": "vM9fJ-VlVw8"},
{"videoId": "OVXgBy2_SvU"},
{"videoId": "p-EP5BE3Zi0"},
{"videoId": "FjB5O1PvXOU"},
{"videoId": "t_ZLUf5KeDo"},
{"videoId": "wnK_tGXEBqQ"},
{"videoId": "aYgzHmM4yUs"}
]}