{"videos": [
{"videoId": "G35EJ_OSCos"},
{"videoId": "AUHZbgDHDy8"},
{"videoId": "y2tZ78EOPS4"},
{"videoId": "BGbYV7FDl6I"},
{"videoId": "HYlwYjRPbPo"},
{"videoId": "tx_6wi4TNcI"},
{"videoId": "c2fAm4xkFp4"},
{"videoId": "9dYxW_0Ya5U"},
{"videoId": "2fKfvZjr4-w"},
{"videoId": "fTSV1qIKCHU"},
{"videoId": "vXHBfRNJzqE"},
{"videoId": "LGNISgYlYic"},
{"videoId": "J6OCtqEsFIc"},
{"videoId": "szGxCtCAjLQ"},
{"videoId": "VxxXtN5HZUA"},
{"videoId": "HTfiSATmJLs"},
{"videoId": "4fhmQWYOfrk"},
{"videoId": "9WE3wCA13-A"},
{"videoId": "JwW8vV8rFKg"},
{"videoId": "fc-3UqAQJiI"},
{"videoId": "vDXyFkGiiJc"},
{"videoId": "rR4NCG1KcXs"},
{"videoId": "9oO-33c35WE"},
{"videoId": "1v-cFYTrpIE"},
{"videoId": "rju86e79XN8"},
{"videoId": "khRSsdy6RZY"},
{"videoId": "X2uhJ_O5EF4"},
{"videoId": "O4OAA-ohGBQ"},
{"videoId": "hDMXna0bKMg"},
{"videoId": "poalPAQqTVQ"},
{"videoId": "R_ueYQVhoH0"},
{"videoId": "P9n7l_mdMRA"},
{"videoId": "n-tImcQT2G4"},
{"videoId": "fbidGstg4tk"},
{"videoId": "Bqqw_5vrdi0"},
{"videoId": "0FSxgUAGwzY"},
{"videoId": "Ztg1UKdGy3k"},
{"videoId": "HXLdEKeE39I"},
{"videoId": "hOFt40DCHxM"},
{"videoId": "02YzqbH2vjU"},
{"videoId": "QxDdkgj_PDw"},
{"videoId": "vQOyhoyA8YM"},
{"videoId": "P7eCigAzgew"},
{"videoId": "4nPxV0ZlF-0"},
{"videoId": "cPCv5p0tyFg"},
{"videoId": "OZRfz7oWStc"},
{"videoId": "jvNbIwQkLSM"},
{"videoId": "Wl25wyxkbTs"},
{"videoId": "uqnK8lQAh0Y"},
{"videoId": "4AeWE6BLi_U"},
{"videoId": "2PtZRK6AbxM"},
{"videoId": "a1j0HqdLoog"},
{"videoId": "y7Db250QM58"},
{"videoId": "2poesLXnoPs"},
{"videoId": "zFUUgM6GgkU"},
{"videoId": "VZHGHqtKlOY"},
{"videoId": "axq5XByBcZk"},
{"videoId": "Y4_NiE66mtY"},
{"videoId": "uJo79IKxat0"},
{"videoId": "QB3zQcBa9SE"},
{"videoId": "FSEX1SZPaSU"},
{"videoId": "Y4ecXDf_imQ"},
{"videoId": "C3X8PdG7-1g"},
{"videoId": "CWclBZQggjc"},
{"videoId": "UE8RPsiLUis"},
{"videoId": "ik5Oaggkl3k"},
{"videoId": "uAhjHecGbKM"},
{"videoId": "_7fh_AHj528"},
{"videoId": "LToUElTWhjU"},
{"videoId": "MscnSLZpL_g"},
{"videoId": "tEHVnLUsufc"},
{"videoId": "J6pbZq0xp18"},
{"videoId": "dJxsK51GdtU"},
{"videoId": "LogPDN6B5Yo"},
{"videoId": "AUcXH75hXWE"},
{"videoId": "lwueyXbYD2k"},
{"videoId": "-MdztHkQ7MI"},
{"videoId": "UXDOYqydY1o"},
{"videoId": "hkv4WEuJeT0"},
{"videoId": "Lv9nOEV_NI0"},
{"videoId": "NPeyg6cPQWg"},
{"videoId": "WTaInk0o-g0"},
{"videoId": "Xw0GUNOQ31c"},
{"videoId": "OH0yTJHXYsM"},
{"videoId": "4mFoYQyPlgw"},
{"videoId": "pefbMId6qaw"},
{"videoId": "L-P2phn4dfU"},
{"videoId": "cQxM4GJNXB0"},
{"videoId": "t4MAOtmwlW4"},
{"videoId": "-IriV70Fx7Q"},
{"videoId": "fEC_Z6Zh0IY"},
{"videoId": "YgLyWFKS62w"},
{"videoId": "5oQIUoXmm1Y"},
{"videoId": "iuxCIqH7OjA"},
{"videoId": "btYcSKZ6MD8"},
{"videoId": "Kd2EVZO3XH8"},
{"videoId": "oV7HIWSLQ80"},
{"videoId": "vz5kA_jW1gs"},
{"videoId": "8yeEgH0KQ0c"},
{"videoId": "xXC4ydvXgE4"},
{"videoId": "RElB75FsAwk"},
{"videoId": "yV0iiqGNX2A"},
{"videoId": "C2EknVpSMRM"},
{"videoId": "BWFLOsiIAhY"},
{"videoId": "eC526CUSm8o"},
{"videoId": "1x8phN6tfg4"},
{"videoId": "93LSs89WTbI"},
{"videoId": "VMOk6aC9o8U"},
{"videoId": "tZupGzpYdw0"},
{"videoId": "3X5nA2qeb9c"},
{"videoId": "OQy3dasjDv8"},
{"videoId": "dCRalT0sAwo"},
{"videoId": "iKRy6B4ebKE"},
{"videoId": "KCf6C3MePCk"},
{"videoId": "gfy43lYUV1U"},
{"videoId": "AWHRtQ17sCk"},
{"videoId": "U6xzL7eEwYo"},
{"videoId": "D3AhXEqsYn8"},
{"videoId": "ie0UJ4gNU8E"},
{"videoId": "bDxEQY7wFlg"},
{"videoId": "qkdUGC-izus"},
{"videoId": "dhbRjPKVs5Q"},
{"videoId": "2QCySNv7cxA"},
{"videoId": "c01_Odx9O4o"},
{"videoId": "WMGoCmTnAoI"},
{"videoId": "i8oFut33nD0"},
{"videoId": "y-EGTBgJJCI"},
{"videoId": "KQwnwa5YvHI"},
{"videoId": "13jhFFYCWVU"},
{"videoId": "Zl6s8sjqG7c"},
{"videoId": "QHQTzeve7OM"},
{"videoId": "OET5MVeQD6w"},
{"videoId": "h2F4wu3xwsY"},
{"videoId": "vGW3T-FwxqU"},
{"videoId": "UVFiS8YXy-Y"},
{"videoId": "58GwyVRiNlU"},
{"videoId": "aFXriCY0DMk"},
{"videoId": "TyF4YADHeok"},
{"videoId": "5plbcwyoC3Y"},
{"videoId": "5m8iyx0ha4I"},
{"videoId": "X-33_A_YsWg"},
{"videoId": "-fINeCPsKtg"},
{"videoId": "crRMCsLTpYY"},
{"videoId": "5ojwnvtl38k"},
{"videoId": "ya8y-yj8tG4"},
{"videoId": "VXVRxJpHhd8"},
{"videoId": "5oaJtQIW70Q"},
{"videoId": "m7kIEeahmKE"},
{"videoId": "FWBHXJVtlNI"},
{"videoId": "i9b_YLYfD_I"},
{"videoId": "S97Z-un0tCE"},
{"videoId": "dlHRZ9gwyH8"},
{"videoId": "40d5nNFiKZ0"},
{"videoId": "d08O0NcO9YQ"},
{"videoId": "B-ahgj7Ogjw"},
{"videoId": "Dj6p4HDCAQU"},
{"videoId": "J_vjd20sU_o"},
{"videoId": "_uNmjncqF5U"},
{"videoId": "fy-uTugEHBw"},
{"videoId": "xZzbOTzf21k"},
{"videoId": "wnK_tGXEBqQ"},
{"videoId": "jN0Rd7-nuQI"},
{"videoId": "gHVOtY7ASzA"},
{"videoId": "EPCh_QXJppE"},
{"videoId": "1DXojsPU15U"},
{"videoId": "BI5jiX2hDJ0"},
{"videoId": "OWdQbu-w0CM"},
{"videoId": "-EKOV71m-PY"},
{"videoId": "FBXZ3G2Y8HQ"},
{"videoId": "j7do1P6Dsi4"},
{"videoId": "IMckdAbfZEY"},
{"videoId": "KuZXY5FwHUg"},
{"videoId": "mHjSG6Jr4hk"},
{"videoId": "5op5FQO9HiA"},
{"videoId": "SZHIjhwzIXA"},
{"videoId": "BUzdbZBU_Ws"},
{"videoId": "fkZHengo7Co"},
{"videoId": "lHeYisIzin8"},
{"videoId": "q3WjBAC-hIo"},
{"videoId": "tYAjuUNea94"},
{"videoId": "my_WKUsnIVs"},
{"videoId": "ldjMnhapzic"},
{"videoId": "z7IIKN3Sco4"},
{"videoId": "TCEmnjcaCMQ"},
{"videoId": "gjGisKZE1DY"},
{"videoId": "LVWu0S9PMYE"},
{"videoId": "zRDA_Ve0m_4"},
{"videoId": "M2H1KSE2olE"},
{"videoId": "UwHXkmWTqGA"},
{"videoId": "LDnsswFB3Is"},
{"videoId": "gJo1hRJE82o"},
{"videoId": "JQnD2li1AmE"},
{"videoId": "a9lUZWdMLjQ"},
{"videoId": "uijMg7ZAS5Q"},
{"videoId": "08Ptu11q1fg"},
{"videoId": "7QCPFn9M59I"},
{"videoId": "YROVHOiKTno"},
{"videoId": "W5r1itEFFtA"},
{"videoId": "SbPJD26W1uE"},
{"videoId": "XAcepJXAxMY"},
{"videoId": "Hkxih6ciTB8"},
{"videoId": "BFhihGQBivQ"},
{"videoId": "8V0niEYddQI"},
{"videoId": "eaq9D0dydUs"},
{"videoId": "OEevnpgpjts"},
{"videoId": "0fJ04AfajWA"},
{"videoId": "SSj_lGhkhmY"},
{"videoId": "alNVV_9Wo10"},
{"videoId": "9H6rHmaKUfU"},
{"videoId": "DwAyUV6hTf8"},
{"videoId": "M0S0501bdn0"},
{"videoId": "H7FaGkK_qRI"},
{"videoId": "XHs-bK8g2Ww"},
{"videoId": "abG0j-Sm9cw"},
{"videoId": "E9tbXFE43lM"},
{"videoId": "tVlmUlHw-0o"},
{"videoId": "-EhNpUqm0Q0"},
{"videoId": "_9BF8xhgZ8o"},
{"videoId": "S4AwvGK_2vc"},
{"videoId": "GlYRfWOxcRY"},
{"videoId": "4cjy_JfLgbI"},
{"videoId": "wEbrdxWw7ew"},
{"videoId": "T1DMTBFbMT8"},
{"videoId": "Ey-5VzxaphE"},
{"videoId": "ib1z7bdQm2w"},
{"videoId": "8pJRz287VjU"},
{"videoId": "rUqqMytfwTw"},
{"videoId": "CuLMweGdu_I"},
{"videoId": "DmcSbmiq0nc"},
{"videoId": "KHsN41lg51w"},
{"videoId": "9lf2uF5ofYU"},
{"videoId": "7aqMHOWXObw"},
{"videoId": "Kp_fGVwBdFY"},
{"videoId": "NWPr3AEWQo0"},
{"videoId": "odyF1Ea2Ro8"},
{"videoId": "anmT0okmHbM"},
{"videoId": "wzi-4FQ75is"},
{"videoId": "6DzUsDehvCw"},
{"videoId": "DgiZRwmkjPc"},
{"videoId": "WAHo3B2x8c4"}
]}