{"videos": [
{"videoId": "5fYXySwNtpI"},
{"videoId": "w59wg5CP1Dk"},
{"videoId": "iaBMBjPutyk"},
{"videoId": "tjt7W3YQDHk"},
{"videoId": "cfg12mB5ic4"},
{"videoId": "eFkb1oDL29s"},
{"videoId": "6m2W7F60apc"},
{"videoId": "yqVtYSJWkrQ"},
{"videoId": "18BnAMbFPJE"},
{"videoId": "dD1D9dT8cPM"},
{"videoId": "mAGQCNFxFXY"},
{"videoId": "JBB7dgB4vYg"},
{"videoId": "tF2cE1GbLes"},
{"videoId": "xJ7S_wSDWA4"},
{"videoId": "no6lsoOsFds"},
{"videoId": "jzz9V3SaQlE"},
{"videoId": "iTSSx6JCUw8"},
{"videoId": "gxyuN8jCNN0"},
{"videoId": "rxu029y929U"},
{"videoId": "p9eMVTLC_O8"},
{"videoId": "-n-ye9N58fk"},
{"videoId": "1gQR6yb9KHM"},
{"videoId": "W5cTcu9NyTE"},
{"videoId": "PxUk_tiKKmM"},
{"videoId": "fq8TntvpcQE"},
{"videoId": "H3PGgYe6YvQ"},
{"videoId": "g9uXY3kw5Ts"},
{"videoId": "J385u_BDwIs"},
{"videoId": "w1gDKYtEaMY"},
{"videoId": "IwlzGRptyQI"},
{"videoId": "astY7uzOaas"},
{"videoId": "H1qKgHGPOuM"},
{"videoId": "JPMyQp9Wlyo"},
{"videoId": "C4HgA9HEeWY"},
{"videoId": "WVUvopiD-pc"},
{"videoId": "PXa1ZdCQ_x8"},
{"videoId": "5vBaaBbfS4Y"},
{"videoId": "HRA74wIUdRo"},
{"videoId": "r_I5-004ZQI"},
{"videoId": "eVpt2wy-Bqw"},
{"videoId": "nlnw3GrEBCc"},
{"videoId": "I7vfCTonwjo"},
{"videoId": "alaBPuyPY_8"},
{"videoId": "mdcoybfNRgI"},
{"videoId": "oX3P65U7TxQ"},
{"videoId": "vcOWtW8YUmE"},
{"videoId": "f0P59ooQQ_M"},
{"videoId": "nhSmMjJDHG4"},
{"videoId": "Z9KCaXuF1WA"},
{"videoId": "uwJ62hKPYNk"},
{"videoId": "yQphXkiRUaw"},
{"videoId": "PYiNEersPYQ"},
{"videoId": "5P465ujm79c"},
{"videoId": "ElCykY9y32U"},
{"videoId": "20RZQX7pqUc"},
{"videoId": "ucylSxJn4Hc"},
{"videoId": "70pp26uPlRg"},
{"videoId": "6w25Ettxt18"},
{"videoId": "bc3UqNwUkAs"},
{"videoId": "BEwNWC92Aaw"},
{"videoId": "uKerYC14xbA"},
{"videoId": "TCXSrsOrV0w"},
{"videoId": "bg52bG84HtM"},
{"videoId": "t_uvql9ZIyc"},
{"videoId": "cifM0P9PeBg"},
{"videoId": "K9r3gjryg0w"},
{"videoId": "WSC07U7uo3s"},
{"videoId": "CiT43q__X5I"},
{"videoId": "r95w01PUHJ0"},
{"videoId": "Rt6WlaZ1pbQ"},
{"videoId": "vAnqiJZxC_c"},
{"videoId": "6Ae-CSO6dDE"},
{"videoId": "xXnStuiQJXw"},
{"videoId": "0R9pka6tTw4"},
{"videoId": "VAM-n-mLS8c"},
{"videoId": "39eYUj3RGEs"},
{"videoId": "46H2r5IioPU"},
{"videoId": "qqmmKhuolT8"},
{"videoId": "IWtEUvX30Dw"},
{"videoId": "0ap4Lw_jx94"},
{"videoId": "kzusZJwiOcM"},
{"videoId": "Vl8EDOjqhhk"},
{"videoId": "yBxWoD8WDbA"},
{"videoId": "TJIsa-DkEnc"},
{"videoId": "owhARUX3uoY"},
{"videoId": "8eQKg7iz_3c"},
{"videoId": "TpiPrNQrAsE"},
{"videoId": "D9IP3GW06yE"},
{"videoId": "ko5AuRfE4r4"},
{"videoId": "pSKi7P9_aeM"},
{"videoId": "qjI0S4DVh4s"},
{"videoId": "DT9na7PsWJ0"},
{"videoId": "_QGMhoHMfFY"},
{"videoId": "JPbGLCy1EXU"},
{"videoId": "jmhCa7hNyrY"},
{"videoId": "MgRoSHuZ1Es"},
{"videoId": "1ROSpRIEQfU"},
{"videoId": "rPtF61dA7D0"},
{"videoId": "4TmlMF6YXxw"},
{"videoId": "5eKdDQrgoiw"},
{"videoId": "M3L1MemClCc"},
{"videoId": "YEtU35VsOho"},
{"videoId": "fzw-VBxFEYw"},
{"videoId": "6guvDA4dNLk"},
{"videoId": "AtD-S7-JARQ"},
{"videoId": "b3I85jkvVas"},
{"videoId": "Llt7bUJMlog"},
{"videoId": "NpwDbRglfmU"},
{"videoId": "bna_yfA9pU0"},
{"videoId": "SOU-IBz9dJQ"},
{"videoId": "Zc-Cxmo3aMg"},
{"videoId": "3fmzjQVoK28"},
{"videoId": "4XJs2cU7xMU"},
{"videoId": "PjEuYmvud8A"}
]}